Workbook
Name CommentVC: Data!$S$9
Name CoverVC: Data!$T$9
Name EnterpriseVC: Data!$I$9
Name HostedSecurityVC: Data!#REF!
Name IsPublicVC: Data!$G$9
Name ManagedVC: Data!#REF!
Name ManagedVC: Data!#REF!
Name ManagedVC: Data!#REF!
Name ManagedVC: Data!#REF!
Name ManagedVC: Data!#REF!
Name ManagedVC: Data!#REF!
Name ManagedVC: Data!#REF!
Name ManagedVC: Data!#REF!
Name ManagedVC: Data!#REF!
Name ManagedVC: Data!#REF!
Name ManagedVC: Data!#REF!
Name ManagedVC: Data!#REF!
Name ManagedVC: Data!#REF!
Name ManagedVC: Data!#REF!
Name ManagedVC: Data!#REF!
Name ManagedVC: Data!#REF!
Name ManagedVC: Data!#REF!
Name ManagedVC: Data!#REF!
Name MediaVC: Data!$N$9
Name MigrationVC: Data!$R$9
Name ProductCompositionMatrixVC: Data!$Q$9
Name ProductCompositionVC: Data!$P$9
Name ProductSelectorVC: Data!$O$9
Name PSLicenseType: Data!$A$108:$A$115
Name PSTerm: Data!$A$101:$A$103
Name SOHOVC: Data!$H$9
Name TrafficVC: Data!$M$9
Name xSPVC: Data!$L$9

Sheet Main
B7: =CONCATENATE("Price List applicable for ",Data!A9,". Effective from ",Data!A11,". ") -> Price List applicable for Vietnam. Effective from July 1, 2026.
B8: =CONCATENATE(Data!A5,". ",Data!A7) -> Kaspersky Lab. 39A/3 Leningradskoe Shosse Moscow, 125212. 0
B9: Table of contents
B10: Price list | C10: Home+SOHO | D10: Home user, Small and Home office products. | G10: +
C11: CBA Subscription | D11: CBA Subscription. | G11: -
C12: SMB+Enterprise (License) | D12: SMB and Enterprise products. Commercial licenses. | G12: +
C13: SMB+Enterprise (Pack) | D13: SMB and Enterprise products. Commercial packs. | G13: +
C14: Subscription&MSP | D14: Subscription&MSP. | G14: +
C15: Professional Services | D15: Professional Services. | G15: +
C16: Security Services | D16: Security Services. | G16: +
C17: xSP | D17: Licences for ISP/ASP. | G17: =xSPVC -> 0
C18: Traffic | D18: Traffic licenses. | G18: =TrafficVC -> 0
C19: SIEM | D19: SIEM. | G19: +
C20: Scan Engine | D20: Scan Engine. | G20: +
C21: SD-WAN | D21: SD-WAN. | G21: +
C22: ATC | D22: Authorized Training Center | G22: +
B23: Additional Data | C23: Comment | D23: Description of pricing rules and licensing. | G23: =CommentVC -> +

Sheet Home+SOHO
C7: =CONCATENATE("Price List applicable for ",Data!A9,". Effective from ",Data!A11,". ") -> Price List applicable for Vietnam. Effective from July 1, 2026.
C8: =CONCATENATE(Data!A5,". ",Data!A7) -> Kaspersky Lab. 39A/3 Leningradskoe Shosse Moscow, 125212. 0
B9: Max of Price | H9: Type | I9: Term
H10: Base | L10: Renewal
B11: Code | C11: Product | D11: Package | E11: Volume | F11: LicenceObject | G11: SKU | H11: 1 month | I11: 1 year | J11: 2 year | K11: 3 year | L11: 1 year | M11: 2 year | N11: 3 year
B12: 1000 | C12: New 2022 Product Line | D12: - | E12: - | F12: - | G12: -
B13: 1001 | C13: Kaspersky Standard | D13: Retail Pack | E13: 1Dvc | G13: KL1041WUA** | I13: 290909.09 | J13: 581818.18
E14: 3Dvc | G14: KL1041WUC** | I14: 513636.36 | J14: 1027272.7
E15: 5Dvc | G15: KL1041WUE** | I15: 660000 | J15: 1320000
E16: 10Dvc | G16: KL1041WUK** | I16: 940000 | J16: 1880000
D17: Download Pack | E17: 1Dvc | G17: KL1041WDA** | I17: 290909.09 | J17: 581818.18
E18: 3Dvc | G18: KL1041WDC** | I18: 513636.36 | J18: 1027272.7
E19: 5Dvc | G19: KL1041WDE** | I19: 660000 | J19: 1320000
E20: 10Dvc | G20: KL1041WDK** | I20: 940000 | J20: 1880000
B21: 1002 | C21: Kaspersky Plus | D21: Retail Pack | E21: 1Dvc | G21: KL1042WUA** | I21: 456363.64 | J21: 912727.27
E22: 3Dvc | G22: KL1042WUC** | I22: 672727.27 | J22: 1345454.5
E23: 5Dvc | G23: KL1042WUE** | I23: 796363.64 | J23: 1592727.3
E24: 10Dvc | G24: KL1042WUK** | I24: 999090.91 | J24: 1998181.8
D25: Download Pack | E25: 1Dvc | G25: KL1042WDA** | I25: 456363.64 | J25: 912727.27
E26: 3Dvc | G26: KL1042WDC** | I26: 672727.27 | J26: 1345454.5
E27: 5Dvc | G27: KL1042WDE** | I27: 796363.64 | J27: 1592727.3
E28: 10Dvc | G28: KL1042WDK** | I28: 999090.91 | J28: 1998181.8
B29: 1003 | C29: Kaspersky Premium + Customer Support | D29: Retail Pack | E29: 1Dvc | G29: KL1047WUA** | I29: 578181.82 | J29: 1156363.6
E30: 3Dvc | G30: KL1047WUC** | I30: 790909.09 | J30: 1581818.2
E31: 5Dvc | G31: KL1047WUE** | I31: 935454.55 | J31: 1870909.1
E32: 10Dvc | G32: KL1047WUK** | I32: 1134545.5 | J32: 2269090.9
D33: Download Pack | E33: 1Dvc | G33: KL1047WDA** | I33: 578181.82 | J33: 1156363.6
E34: 3Dvc | G34: KL1047WDC** | I34: 790909.09 | J34: 1581818.2
E35: 5Dvc | G35: KL1047WDE** | I35: 935454.55 | J35: 1870909.1
E36: 10Dvc | G36: KL1047WDK** | I36: 1134545.5 | J36: 2269090.9
E37: 20Dvc | G37: KL1047WDN** | I37: 1537272.7 | J37: 3074545.5
B38: 1004 | C38: Kaspersky Standard Mobile | D38: Retail Pack | E38: 1Dvc | G38: KL1048WUA** | I38: 190000
D39: Download Pack | E39: 1Dvc | G39: KL1048WDA** | I39: 190000
B40: 1005 | C40: Kaspersky Premium Mobile | D40: Retail Pack | E40: 1Dvc | F40: Dvc | G40: KL1004WUA** | I40: 462727.27
D41: Download Pack | E41: 1Dvc | F41: Dvc | G41: KL1004WDA** | I41: 462727.27
B42: 1200 | C42: Other | D42: - | E42: - | F42: - | G42: -
B43: 1201 | C43: Kaspersky Secure Connection | D43: Download Pack | E43: 5Dvc | G43: KL1987WDE** | H43: 117273 | I43: 620000
B44: 1202 | C44: Kaspersky Cloud Password Manager | D44: Download Pack | E44: 1User | F44: User | G44: KL1956WDA** | I44: 373636.36
B45: 1203 | C45: Kaspersky Safe Kids | D45: Retail Pack | E45: 1User | G45: KL1962WUA** | I45: 373636.36
D46: Download Pack | E46: 1User | G46: KL1962WDA** | I46: 373636.36
B47: 1205 | C47: Kaspersky Small Office Security for Desktops, Mobiles and File Servers | D47: Retail Pack | E47: 5-MD; 5-Dt; 1-FS; 5-User | G47: KL4541WUE** | I47: 9609600 | J47: 14414400 | K47: 17763900 | L47: 5751900 | M47: 8639400 | N47: 10649100
E48: 10-MD; 10-Dt; 1-FS; 10-User | G48: KL4541WUK** | I48: 11180400 | J48: 16770600 | K48: 20674500 | L48: 6699000 | M48: 10071600 | N48: 12404700
E49: 15-MD; 15-Dt; 2-FS; 15-User | G49: KL4541WUM** | I49: 16793700 | J49: 25179000 | K49: 31046400 | L49: 10071600 | M49: 15107400 | N49: 18618600
E50: 20-MD; 20-Dt; 2-FS; 20-User | G50: KL4541WUN** | I50: 22383900 | J50: 33564300 | K50: 41395200 | L50: 13421100 | M50: 20143200 | N50: 24832500
E51: 25-MD; 25-Dt; 3-FS; 25-User | G51: KL4541WUP** | I51: 25063500 | J51: 37606800 | K51: 46384800 | L51: 15038100 | M51: 22568700 | N51: 27835500
D52: License Pack | E52: 5-MD; 5-Dt; 1-FS; 5-User | G52: KL4541WCE** | I52: 9609600 | J52: 14414400 | K52: 17763900 | L52: 5751900 | M52: 8639400 | N52: 10649100
E53: 10-MD; 10-Dt; 1-FS; 10-User | G53: KL4541WCK** | I53: 11180400 | J53: 16770600 | K53: 20674500 | L53: 6699000 | M53: 10071600 | N53: 12404700
E54: 15-MD; 15-Dt; 2-FS; 15-User | G54: KL4541WCM** | I54: 16793700 | J54: 25179000 | K54: 31046400 | L54: 10071600 | M54: 15107400 | N54: 18618600
E55: 20-MD; 20-Dt; 2-FS; 20-User | G55: KL4541WCN** | I55: 22383900 | J55: 33564300 | K55: 41395200 | L55: 13421100 | M55: 20143200 | N55: 24832500
E56: 25-MD; 25-Dt; 3-FS; 25-User | G56: KL4541WCP** | I56: 25063500 | J56: 37606800 | K56: 46384800 | L56: 15038100 | M56: 22568700 | N56: 27835500

Sheet CBA Subscription
C7: =CONCATENATE("Price List applicable for ",Data!A9,". Effective from ",Data!A11,". ") -> Price List applicable for Vietnam. Effective from July 1, 2026. | H7: * For additional details please see
C8: =CONCATENATE(Data!A5,". ",Data!A7) -> Kaspersky Lab. 39A/3 Leningradskoe Shosse Moscow, 125212. 0 | H8: specifications in Comment section
B9: Max of Price | H9: Type | I9: Term
H10: Subscription Limit
B11: Code | C11: Product | D11: Package | E11: Volume | F11: LicenceObject | G11: SKU | H11: 1 year
B12: 1000 | C12: New 2022 Product Line | D12: - | E12: - | F12: - | G12: -
B13: 1001 | C13: Kaspersky Standard | D13: xSP Pack | E13: 1Dvc | G13: KL10414GA** | H13: 43.52
E14: 3Dvc | G14: KL10414GC** | H14: 68.52
E15: 5Dvc | G15: KL10414GE** | H15: 87.96
E16: 10Dvc | G16: KL10414GK** | H16: 125
B17: 1002 | C17: Kaspersky Plus | D17: xSP Pack | E17: 1Dvc | G17: KL10424GA** | H17: 62.96
E18: 3Dvc | G18: KL10424GC** | H18: 87.96
E19: 5Dvc | G19: KL10424GE** | H19: 106.48
E20: 10Dvc | G20: KL10424GK** | H20: 144.44
B21: 1003 | C21: Kaspersky Premium + Customer Support | D21: xSP Pack | E21: 1Dvc | G21: KL10474GA** | H21: 99.07
E22: 3Dvc | G22: KL10474GC** | H22: 124.07
E23: 5Dvc | G23: KL10474GE** | H23: 143.52
E24: 10Dvc | G24: KL10474GK** | H24: 180.56
E25: 20Dvc | G25: KL10474GN** | H25: 243.52
B26: 1100 | C26: Frontline | D26: - | E26: - | F26: - | G26: -
B27: 1101 | C27: Kaspersky Anti-Virus | D27: xSP Pack | E27: 1Dt | G27: KL11714GA** | H27: 27.95
E28: 3Dt | G28: KL11714GC** | H28: 43.95
E29: 5Dt | G29: KL11714GE** | H29: 69.95
B30: 1102 | C30: Kaspersky Internet Security | D30: xSP Pack | E30: 1Dvc | G30: KL19394GA** | H30: 40.95
E31: 3Dvc | G31: KL19394GC** | H31: 77.95
E32: 5Dvc | G32: KL19394GE** | H32: 109.95
E33: 10Dvc | G33: KL19394GK** | H33: 165.95
B34: 1103 | C34: Kaspersky Total Security | D34: xSP Pack | E34: 1Dvc | G34: KL19494GA** | H34: 61.95
E35: 3Dvc | G35: KL19494GC** | H35: 94.95
E36: 5Dvc | G36: KL19494GE** | H36: 135.95
B37: 1200 | C37: Other | D37: - | E37: - | F37: - | G37: -
B38: 1201 | C38: Kaspersky Cloud Password Manager | D38: xSP Pack | E38: 1User | F38: User | G38: KL19564GA** | H38: 19.32
B39: 1202 | C39: Kaspersky Safe Kids | D39: xSP Pack | E39: 1User | G39: KL19624GA** | H39: 22.22
B40: 1203 | C40: Kaspersky Secure Connection | D40: xSP Pack | E40: 5Dvc | G40: KL19874GE** | H40: 38.89

Sheet SMB+Enterprise (License)
C7: =CONCATENATE("Price List applicable for ",Data!A9,". Effective from ",Data!A11,". ") -> Price List applicable for Vietnam. Effective from July 1, 2026. | M7: * For additional details on Kaspersky Security for Virtualization, Kaspersky Data Leakage Protection products
C8: =CONCATENATE(Data!A5,". ",Data!A7) -> Kaspersky Lab. 39A/3 Leningradskoe Shosse Moscow, 125212. 0 | O8: please see specifications in Comment section
B9: Max of Price | J9: Band
B10: Code | C10: Product | D10: LicenceDescription | E10: Package | F10: LicenceObject | G10: Type | H10: Term | I10: SKU | J10: Band M: 15-19 | K10: Band N: 20-24 | L10: Band P: 25-49 | M10: Band Q: 50-99 | N10: Band R: 100-149
B11: 2003 | C11: Kaspersky Next EDR Optimum | E11: License | G11: Base Plus | H11: 1 year | I11: KL4066WA*F8 | J11: 2402400 | K11: 2402400 | L11: 2180640 | M11: 1928850 | N11: 1732500
H12: 2 year | I12: KL4066WA*D8 | J12: 3603600 | K12: 3603600 | L12: 3280200 | M12: 2887500 | N12: 2610300
H13: 3 year | I13: KL4066WA*T8 | J13: 4458300 | K13: 4458300 | L13: 4042500 | M13: 3557400 | N13: 3210900
G14: Renewal Plus | H14: 1 year | I14: KL4066WA*F9 | J14: 1924230 | K14: 1924230 | L14: 1744050 | M14: 1543080 | N14: 1388310
H15: 2 year | I15: KL4066WA*D9 | J15: 3164700 | K15: 3164700 | L15: 2887500 | M15: 2541000 | N15: 2286900
H16: 3 year | I16: KL4066WA*T9 | J16: 3903900 | K16: 3903900 | L16: 3557400 | M16: 3141600 | N16: 2818200

Sheet SMB+Enterprise (Pack)
C7: =CONCATENATE("Price List applicable for ",Data!A9,". Effective from ",Data!A11,". ") -> Price List applicable for Vietnam. Effective from July 1, 2026. | AD7: * For additional details on Acronis Backup Advanced Universa product
C8: =CONCATENATE(Data!A5,". ",Data!A7) -> Kaspersky Lab. 39A/3 Leningradskoe Shosse Moscow, 125212. 0 | AD8: please see specifications in Comment section
B9: Max of Price | J9: Band
B10: Code | C10: Product | D10: LicenceDescription | E10: Package | F10: LicenceObject | G10: Type | H10: Term | I10: SKU | K10: Band A: 1 | L10: Band B: 2 | M10: Band C: 3 | N10: Band D: 4 | O10: Band E: 5 | P10: Band F: 6 | Q10: Band H: 8 | R10: Band K: 10 | S10: Band L: 12 | T10: Band 2: 16 | U10: Band N: 20 | V10: Band Q: 50 | W10: Band R: 100 | X10: Band S: 150 | Y10: Band T: 250 | Z10: Band U: 500 | AA10: Band V: 1000 | AB10: Band W: 2500 | AC10: Band X: 5000 | AD10: Band Y: 10000
B11: 8000 | C11: Threat Intelligence* | D11: (blank) | E11: - | F11: - | G11: - | H11: - | I11: -
B12: 8001 | C12: Kaspersky Online Security Trainings for Experts. Targeted Malware Reverse Engineering | D12: Trainee | E12: License Pack | G12: Base | H12: 6 months | I12: KL7580WC*HS | K12: 41510700
B13: 8002 | C13: Kaspersky Online Security Trainings for Experts.Yara | D13: Trainee | E13: License Pack | G13: Base | H13: 6 months | I13: KL7579WC*HS | K13: 22314600
B14: 8003 | C14: Kaspersky Online Security Trainings for Experts. Advanced Malware Analysis Techniques | D14: Trainee | E14: License Pack | G14: Base | H14: 6 months | I14: KL7590WC*HS | K14: 79233000
B15: 8004 | C15: Kaspersky Online Security Trainings for Experts. Windows Incident Response | D15: Trainee | E15: License Pack | G15: Base | H15: 6 months | I15: KL7518WC*HS | K15: 30884700
B16: 8005 | C16: Kaspersky Online Security Trainings For Experts. Security Operations And Threat Hunting | D16: Trainee | E16: License Pack | G16: Base | H16: 6 months | I16: KL7510WC*HS | K16: 41834100
B17: 8006 | C17: Kaspersky Online Security Trainings For Experts. Reverse Engineering 101 | D17: Trainee | E17: License Pack | G17: Base | H17: 6 months | I17: KL7511WC*HS | K17: 24370500
B18: 8007 | C18: Kaspersky Online Security Trainings For Experts. Mobile Malware Reverse Engineering | D18: Trainee | E18: License Pack | G18: Base | H18: 6 months | I18: KL7578WC*HS | K18: 23515800
B19: 8008 | C19: Kaspersky Online Security Trainings For Experts. Suricata for Incident Response and Threat Hunting | D19: Trainee | E19: License Pack | G19: Base | H19: 6 months | I19: KL7512WC*HS | K19: 26611200
B20: 8009 | C20: Kaspersky Online Security Trainings For Experts. Advanced malware reverse engineering with Ghidra | D20: Trainee | E20: License Pack | G20: Base | H20: 6 months | I20: KL7513WC*HS | K20: 53823000
B21: 8011 | C21: Kaspersky Online Security Trainings For Experts. Windows Digital Forensics | E21: License Pack | G21: Base | H21: 6 months | I21: KL7514WC*HS | K21: 37745400
B22: 8012 | C22: Kaspersky Online Security Trainings For Experts. LLM Security | D22: Trainee | E22: License Pack | F22: Trainee | G22: Base | H22: 6 months | I22: KL7403WC*HS | K22: 22176000
B23: 8016 | C23: Kaspersky Private Security Network, Standard | D23: Instance | E23: License Pack | G23: Base Plus | H23: 1 year | I23: KL8552WC*F8 | K23: 3182232900
H24: 2 year | I24: KL8552WC*D8 | K24: 4773314700
H25: 3 year | I25: KL8552WC*T8 | K25: 6364442700
G26: Renewal Plus | H26: 1 year | I26: KL8552WC*F9 | K26: 2227533000
H27: 2 year | I27: KL8552WC*D9 | K27: 3341345700
H28: 3 year | I28: KL8552WC*T9 | K28: 4455112200
B29: 8017 | C29: Kaspersky Private Security Network, Advanced | D29: Instance | E29: License Pack | G29: Base Plus | H29: 1 year | I29: KL8553WC*F8 | R29: 7425194700
H30: 2 year | I30: KL8553WC*D8 | R30: 11137757400
H31: 3 year | I31: KL8553WC*T8 | R31: 14850366300
G32: Renewal Plus | H32: 1 year | I32: KL8553WC*F9 | R32: 5197615500
H33: 2 year | I33: KL8553WC*D9 | R33: 7796457900
H34: 3 year | I34: KL8553WC*T9 | R34: 10395254100
B35: 8018 | C35: Kaspersky Cloud Sandbox | D35: Queries per day | E35: License Pack | G35: Base Plus | H35: 1 year | I35: KL7953WC*F8 | R35: 249041100 | U35: 415083900 | V35: 705635700 | W35: 1245228600 | Z35: 1867842900 | AA35: 2697987600 | AC35: 3943170000
H36: 2 year | I36: KL7953WC*D8 | R36: 448278600 | U36: 747123300 | V36: 1270130400 | W36: 2241393000 | Z36: 3362089500 | AA36: 4856359200 | AC36: 7097729100
H37: 3 year | I37: KL7953WC*T8 | R37: 635065200 | U37: 1058418900 | V37: 1799328300 | W37: 3175302900 | Z37: 4762942800 | AA37: 6879826800 | AC37: 10055129700
G38: Renewal Plus | H38: 1 year | I38: KL7953WC*F9 | R38: 236590200 | U38: 394317000 | V38: 670338900 | W38: 1182974100 | Z38: 1774426500 | AA38: 2563083600 | AC38: 3746011500
H39: 2 year | I39: KL7953WC*D9 | R39: 425871600 | U39: 709770600 | V39: 1206628500 | W39: 2129334900 | Z39: 3193990800 | AA39: 4613532000 | AC39: 6742843800
H40: 3 year | I40: KL7953WC*T9 | R40: 603302700 | U40: 1005519900 | V40: 1709376900 | W40: 3016559700 | Z40: 4524804900 | AA40: 6535844700 | AC40: 9552381300
B41: 8019 | C41: Kaspersky Research Sandbox* | D41: Queries per day | E41: License Pack | G41: Base Plus | H41: 1 year | I41: KL7954WC*F8 | J41: 14527543800 | W41: 830144700 | Y41: 1867842900 | AA41: 3943170000
H42: 2 year | I42: KL7954WC*D8 | J42: 26668880700 | W42: 1523930100 | Y42: 3428848500 | AA42: 7238708400
H43: 3 year | I43: KL7954WC*T8 | J43: 37055726400 | W43: 2117461500 | Y43: 4764305700 | AA43: 10057994100
G44: Renewal Plus | H44: 1 year | I44: KL7954WC*F9 | J44: 13895897400 | W44: 794062500 | Y44: 1786623300 | AA44: 3771744900
H45: 2 year | I45: KL7954WC*D9 | J45: 25405634100 | W45: 1451742600 | Y45: 3266432400 | AA45: 6895812000
H46: 3 year | I46: KL7954WC*T9 | J46: 35202944700 | W46: 2011617300 | Y46: 4526098500 | AA46: 9555084000
B47: 8021 | C47: Kaspersky Threat Attribution Engine | D47: Queries per day | E47: License Pack | G47: Base Plus | H47: 1 year | I47: KL4988WC*F8 | J47: 14873004300 | W47: 4674516000 | Y47: 7649079900
H48: 2 year | I48: KL4988WC*D8 | J48: 27303091200 | W48: 8581257300 | Y48: 14041773900
H49: 3 year | I49: KL4988WC*T8 | J49: 37936945200 | W49: 11923434600 | Y49: 19510652700
G50: Renewal Plus | H50: 1 year | I50: KL4988WC*F9 | J50: 14226342900 | W50: 4471305300 | Y50: 7316509200
H51: 2 year | I51: KL4988WC*D9 | J51: 26009814600 | W51: 8174789700 | Y51: 13376632500
H52: 3 year | I52: KL4988WC*T9 | J52: 36040088700 | W52: 11327246700 | Y52: 18535139700
B53: 8022 | C53: Kaspersky Threat Lookup Lite | D53: Search | E53: License Pack | F53: Search | G53: Base | H53: 1 year | I53: KL8796WC*FS | AC53: 1983135000 | AD53: 3050978700
H54: 2 year | I54: KL8796WC*DS | AC54: 3569666100 | AD54: 5491770900
H55: 3 year | I55: KL8796WC*TS | AC55: 5057005800 | AD55: 7780033800
G56: Renewal | H56: 1 year | I56: KL8796WC*FR | AC56: 1883989800 | AD56: 2898449400
H57: 2 year | I57: KL8796WC*DR | AC57: 3391172400 | AD57: 5217204300
H58: 3 year | I58: KL8796WC*TR | AC58: 4804176300 | AD58: 7391029800
B59: 8023 | C59: Kaspersky Threat Lookup | D59: Search | E59: License Pack | G59: Base Plus | H59: 1 year | I59: KL7966WC*F8 | W59: 4667262600 | X59: 5834089800 | Y59: 7876014300 | Z59: 14001764700 | AA59: 20302566900 | AB59: 31482782100 | AD59: 46672579800
H60: 2 year | I60: KL7966WC*D8 | W60: 8401054200 | X60: 10501352400 | Y60: 14176793400 | Z60: 25203185700 | AA60: 36544638900 | AB60: 56669012400 | AD60: 84010634400
H61: 3 year | I61: KL7966WC*T8 | W61: 11901512700 | X61: 14876885100 | Y61: 20083809900 | Z61: 35704538100 | AA61: 51771558300 | AB61: 80281093200 | AD61: 119015080800
G62: Renewal Plus | H62: 1 year | I62: KL7966WC*F9 | W62: 4433883300 | X62: 5542383000 | Y62: 7482205500 | Z62: 13301673000 | AA62: 19287437400 | AB62: 29908632600 | AD62: 44338948500
H63: 2 year | I63: KL7966WC*D9 | W63: 7981003800 | X63: 9976266300 | Y63: 13467969900 | Z63: 23943034500 | AA63: 34717405800 | AB63: 53835566400 | AD63: 79810107300
H64: 3 year | I64: KL7966WC*T9 | W64: 11306433600 | X64: 14133042000 | Y64: 19079629800 | Z64: 33919300800 | AA64: 49182995400 | AB64: 76267029300 | AD64: 113064336000
B65: 8024 | C65: Kaspersky Cloud Threat Attribution Engine | D65: Queries per day | E65: License Pack | G65: Base Plus | H65: 1 year | I65: KL7891WC*F8 | R65: 249041100 | U65: 415083900 | V65: 705635700 | W65: 1245228600 | Z65: 1867842900 | AA65: 2697987600 | AC65: 3943170000
H66: 2 year | I66: KL7891WC*D8 | R66: 448278600 | U66: 747123300 | V66: 1270130400 | W66: 2241393000 | Z66: 3362089500 | AA66: 4856359200 | AC66: 7097729100
H67: 3 year | I67: KL7891WC*T8 | R67: 635065200 | U67: 1058418900 | V67: 1799328300 | W67: 3175302900 | Z67: 4762942800 | AA67: 6879826800 | AC67: 10055129700
G68: Renewal Plus | H68: 1 year | I68: KL7891WC*F9 | R68: 236590200 | U68: 394317000 | V68: 670338900 | W68: 1182974100 | Z68: 1774426500 | AA68: 2563083600 | AC68: 3746011500
H69: 2 year | I69: KL7891WC*D9 | R69: 425871600 | U69: 709770600 | V69: 1206628500 | W69: 2129334900 | Z69: 3193990800 | AA69: 4613532000 | AC69: 6742843800
H70: 3 year | I70: KL7891WC*T9 | R70: 603302700 | U70: 1005519900 | V70: 1709376900 | W70: 3016559700 | Z70: 4524804900 | AA70: 6535844700 | AC70: 9552381300
B71: 8025 | C71: Kaspersky Threat Analysis | E71: License Pack | G71: Base | H71: 1 year | I71: KL7892WC*FS | AA71: 267913800 | AB71: 446523000 | AC71: 759089100 | AD71: 1339592100
G72: Renewal | H72: 1 year | I72: KL7892WC*FR | AA72: 254538900 | AB72: 424185300 | AC72: 721135800 | AD72: 1272602100
B73: 8026 | C73: Kaspersky CyberTrace: TIP Enterprise | D73: Instance | E73: License Pack | G73: Base | H73: 1 year | I73: KL8614WC*FS | K73: 4460979600 | L73: 8475852000 | M73: 12446118300 | N73: 16059535800 | O73: 19628301000
H74: 2 year | I74: KL8614WC*DS | K74: 8189227200 | L74: 15559559400 | M74: 22847979000 | N74: 29481259500 | O74: 36032650500
H75: 3 year | I75: KL8614WC*TS | K75: 11378736600 | L75: 21619590300 | M75: 31746676500 | N75: 40963437900 | O75: 50066408700
G76: Renewal | H76: 1 year | I76: KL8614WC*FR | K76: 4267032000 | L76: 8107337700 | M76: 11905000800 | N76: 15361292100 | O76: 18774917700
H77: 2 year | I77: KL8614WC*DR | K77: 7801332000 | L77: 14822507700 | M77: 21765697800 | N77: 28084795200 | O77: 34325837700
H78: 3 year | I78: KL8614WC*TR | K78: 10809806700 | L78: 20538602700 | M78: 30159336900 | N78: 38915253300 | O78: 47563107900
B79: 8027 | C79: Kaspersky Threat Data Feeds - Network Security URL | E79: License Pack | G79: Base | H79: 1 year | I79: KL7347WC*FS | V79: 54885600 | W79: 82328400 | X79: 102910500 | Y79: 137214000 | Z79: 222984300 | AA79: 308731500 | AB79: 463108800 | AC79: 686070000 | AD79: 1029105000
H80: 2 year | I80: KL7347WC*DS | V80: 98798700 | W80: 148186500 | X80: 185238900 | Y80: 246985200 | Z80: 401362500 | AA80: 555716700 | AB80: 833586600 | AC80: 1234926000 | AD80: 1852389000
H81: 3 year | I81: KL7347WC*TS | V81: 139962900 | W81: 209932800 | X81: 262439100 | Y81: 349895700 | Z81: 568583400 | AA81: 787248000 | AB81: 1180895100 | AC81: 1749478500 | AD81: 2624229300
G82: Renewal | H82: 1 year | I82: KL7347WC*FR | V82: 52136700 | W82: 78216600 | X82: 97782300 | Y82: 130353300 | Z82: 211827000 | AA82: 293277600 | AB82: 439939500 | AC82: 651766500 | AD82: 977661300
H83: 2 year | I83: KL7347WC*DR | V83: 93855300 | W83: 140771400 | X83: 175998900 | Y83: 234626700 | Z83: 381288600 | AA83: 527927400 | AB83: 791914200 | AC83: 1173179700 | AD83: 1759781100
H84: 3 year | I84: KL7347WC*TR | V84: 132963600 | W84: 199445400 | X84: 249295200 | Y84: 332062500 | Z84: 539616000 | AA84: 747123300 | AB84: 1120673400 | AC84: 1660289400 | AD84: 2490434100
B85: 8028 | C85: Kaspersky Threat Data Feeds - Network Security IP | E85: License Pack | G85: Base | H85: 1 year | I85: KL7348WC*FS | V85: 27442800 | W85: 41164200 | X85: 51466800 | Y85: 68607000 | Z85: 102910500 | AA85: 137214000 | AB85: 205821000 | AC85: 343035000 | AD85: 514552500
H86: 2 year | I86: KL7348WC*DS | V86: 49387800 | W86: 74104800 | X86: 92631000 | Y86: 123492600 | Z86: 185238900 | AA86: 246985200 | AB86: 370477800 | AC86: 617463000 | AD86: 926194500
H87: 3 year | I87: KL7348WC*TS | V87: 69969900 | W87: 104966400 | X87: 131208000 | Y87: 174959400 | Z87: 262439100 | AA87: 349895700 | AB87: 524855100 | AC87: 874750800 | AD87: 1312126200
G88: Renewal | H88: 1 year | I88: KL7348WC*FR | V88: 26079900 | W88: 39108300 | X88: 48879600 | Y88: 65188200 | Z88: 97782300 | AA88: 130353300 | AB88: 195541500 | AC88: 325894800 | AD88: 488842200
H89: 2 year | I89: KL7348WC*DR | V89: 46939200 | W89: 70385700 | X89: 87987900 | Y89: 117324900 | Z89: 175998900 | AA89: 234626700 | AB89: 351951600 | AC89: 586601400 | AD89: 879902100
H90: 3 year | I90: KL7348WC*TR | V90: 66481800 | W90: 99699600 | X90: 124670700 | Y90: 166019700 | Z90: 249041100 | AA90: 332062500 | AB90: 498082200 | AC90: 830144700 | AD90: 1245228600
B91: 8029 | C91: Kaspersky Brand Monitoring | E91: License Pack | G91: Base | H91: 1 year | I91: KL7229WC*FS | V91: 1341648000 | W91: 2012472000 | X91: 2347884000 | Y91: 3018708000
H92: 2 year | I92: KL7229WC*DS | V92: 2683296000 | W92: 4024944000 | X92: 4695768000 | Y92: 6037416000
H93: 3 year | I93: KL7229WC*TS | V93: 4024944000 | W93: 6037416000 | X93: 7043652000 | Y93: 9056124000
G94: Renewal | H94: 1 year | I94: KL7229WC*FR | V94: 1274565600 | W94: 1911848400 | X94: 2230489800 | Y94: 2867772600
H95: 2 year | I95: KL7229WC*DR | V95: 2549131200 | W95: 3823696800 | X95: 4460979600 | Y95: 5735545200
H96: 3 year | I96: KL7229WC*TR | V96: 3823696800 | W96: 5735545200 | X96: 6691469400 | Y96: 8603317800
B97: 8100 | C97: Security Awareness* | D97: - | E97: - | F97: - | G97: - | H97: - | I97: -
B98: 8101 | C98: Kaspersky Gamified Assessment Tool | D98: Case | E98: License Pack | G98: Renewal | H98: 1 year | I98: KL7942WC*FR | V98: 14044800
B99: 8102 | C99: Kaspersky Express Course | D99: (blank) | E99: License Pack | G99: Base | H99: 3 year | I99: KL7938WC*TS | V99: 47747700
E100: License Pack | G100: Base | H100: 1 year | I100: KL7938WC*FS | V100: 18734100
H101: 2 year | I101: KL7938WC*DS | V101: 33726000
G102: Renewal | H102: 1 year | I102: KL7938WC*FR | V102: 16839900
H103: 2 year | I103: KL7938WC*DR | V103: 30330300
H104: 3 year | I104: KL7938WC*TR | V104: 42966000
B105: 9000 | C105: Kaspersky Anti Targeted Attack Platform | D105: - | E105: - | F105: - | G105: - | H105: - | I105: -
B106: 9001 | C106: Kaspersky Anti Targeted Attack | E106: License Pack | G106: Base Plus | H106: 1 year | I106: KL4774WC*F8 | K106: 943357800 | L106: 1660289400 | N106: 3207388800 | P106: 4716742800 | Q106: 6037416000 | S106: 8603317800 | T106: 11320155000 | U106: 13584186000
...

Sheet Subscription&MSP
C7: =CONCATENATE("Price List applicable for ",Data!A9,". Effective from ",Data!A11,". ") -> Price List applicable for Vietnam. Effective from July 1, 2026. | AB7: * For additional details on Acronis Backup Advanced Universa product
C8: =CONCATENATE(Data!A5,". ",Data!A7) -> Kaspersky Lab. 39A/3 Leningradskoe Shosse Moscow, 125212. 0 | AB8: please see specifications in Comment section
B9: Max of Price | J9: Band
B10: Code | C10: Product | D10: LicenceDescription | E10: Package | F10: LicenceObject | G10: Type | H10: Term | I10: SKU | J10: Band Z: 1-1 | K10: Band A: 1-1 | L10: Band B: 2-2 | M10: Band C: 3-3 | N10: Band D: 4-4 | O10: Band E: 5-9 | P10: Band K: 10-14 | Q10: Band M: 15-19 | R10: Band N: 20-24 | S10: Band P: 25-49 | T10: Band Q: 50-99 | U10: Band R: 100-149 | V10: Band S: 150-249 | W10: Band T: 250-499 | X10: Band U: 500-999 | Y10: Band V: 1000-1499 | Z10: Band W: 1500-2499 | AA10: Band X: 2500-4999 | AB10: Band Y: 5000+
B11: 2000 | C11: Kaspersky NEXT | D11: (blank) | E11: - | F11: - | G11: - | H11: - | I11: -
B12: 2002 | C12: Kaspersky Next EDR Foundations | E12: License | G12: Successive | H12: 1 month | I12: KL4065WA*MG | K12: 139755 | L12: 139755 | M12: 139755 | N12: 139755 | O12: 139755 | P12: 139755 | Q12: 139755 | R12: 139755 | S12: 129591 | T12: 114345 | U12: 101640 | V12: 101640 | W12: 91476 | X12: 81312 | Y12: 68607 | Z12: 63525 | AA12: 53361 | AB12: 50820
H13: 1 year | I13: KL4065WA*FG | K13: 1397550 | L13: 1397550 | M13: 1397550 | N13: 1397550 | O13: 1397550 | P13: 1397550 | Q13: 1397550 | R13: 1397550 | S13: 1295910 | T13: 1143450 | U13: 1016400 | V13: 1016400 | W13: 914760 | X13: 813120 | Y13: 686070 | Z13: 635250 | AA13: 533610 | AB13: 508200
H14: 2 year | I14: KL4065WA*DG | K14: 2097480 | L14: 2097480 | M14: 2097480 | N14: 2097480 | O14: 2097480 | P14: 2097480 | Q14: 2097480 | R14: 2097480 | S14: 1945020 | T14: 1716330 | U14: 1524600 | V14: 1524600 | W14: 1372140 | X14: 1219680 | Y14: 1030260 | Z14: 954030 | AA14: 801570 | AB14: 762300
H15: 3 year | I15: KL4065WA*TG | K15: 2587200 | L15: 2587200 | M15: 2587200 | N15: 2587200 | O15: 2587200 | P15: 2587200 | Q15: 2587200 | R15: 2587200 | S15: 2402400 | T15: 2113650 | U15: 1880340 | V15: 1880340 | W15: 1693230 | X15: 1503810 | Y15: 1270500 | Z15: 1173480 | AA15: 986370 | AB15: 940170
G16: Successive Plus | H16: 1 month | I16: KL4065WA*M4 | K16: 152460 | L16: 152460 | M16: 152460 | N16: 152460 | O16: 152460 | P16: 152460 | Q16: 152460 | R16: 152460 | S16: 142296 | T16: 127050 | U16: 111804 | V16: 111804 | W16: 101640 | X16: 88935 | Y16: 76230 | Z16: 71148 | AA16: 58443 | AB16: 55902
H17: 1 year | I17: KL4065WA*F4 | K17: 1538460 | L17: 1538460 | M17: 1538460 | N17: 1538460 | O17: 1538460 | P17: 1538460 | Q17: 1538460 | R17: 1538460 | S17: 1425270 | T17: 1258950 | U17: 1118040 | V17: 1118040 | W17: 1007160 | X17: 893970 | Y17: 755370 | Z17: 699930 | AA17: 586740 | AB17: 559020
H18: 2 year | I18: KL4065WA*D4 | K18: 2310000 | L18: 2310000 | M18: 2310000 | N18: 2310000 | O18: 2310000 | P18: 2310000 | Q18: 2310000 | R18: 2310000 | S18: 2136750 | T18: 1884960 | U18: 1677060 | V18: 1677060 | W18: 1508430 | X18: 1342110 | Y18: 1134210 | Z18: 1046430 | AA18: 880110 | AB18: 838530
H19: 3 year | I19: KL4065WA*T4 | K19: 2841300 | L19: 2841300 | M19: 2841300 | N19: 2841300 | O19: 2841300 | P19: 2841300 | Q19: 2841300 | R19: 2841300 | S19: 2633400 | T19: 2333100 | U19: 2067450 | V19: 2067450 | W19: 1861860 | X19: 1653960 | Y19: 1395240 | Z19: 1293600 | AA19: 1085700 | AB19: 1034880
B20: 2003 | C20: Kaspersky Next EDR Optimum | E20: License | G20: Successive | H20: 1 month | I20: KL4066WA*MG | K20: 218526 | L20: 218526 | M20: 218526 | N20: 218526 | O20: 218526 | P20: 218526 | Q20: 218526 | R20: 218526 | S20: 198198 | T20: 175329 | U20: 157542 | V20: 157542 | W20: 142296 | X20: 129591 | Y20: 114345 | Z20: 104181 | AA20: 91476 | AB20: 86394
H21: 1 year | I21: KL4066WA*FG | K21: 2185260 | L21: 2185260 | M21: 2185260 | N21: 2185260 | O21: 2185260 | P21: 2185260 | Q21: 2185260 | R21: 2185260 | S21: 1981980 | T21: 1753290 | U21: 1575420 | V21: 1575420 | W21: 1422960 | X21: 1295910 | Y21: 1143450 | Z21: 1041810 | AA21: 914760 | AB21: 863940
H22: 2 year | I22: KL4066WA*DG | K22: 3280200 | L22: 3280200 | M22: 3280200 | N22: 3280200 | O22: 3280200 | P22: 3280200 | Q22: 3280200 | R22: 3280200 | S22: 2979900 | T22: 2633400 | U22: 2356200 | V22: 2356200 | W22: 2134440 | X22: 1945020 | Y22: 1716330 | Z22: 1563870 | AA22: 1372140 | AB22: 1295910
H23: 3 year | I23: KL4066WA*TG | K23: 4042500 | L23: 4042500 | M23: 4042500 | N23: 4042500 | O23: 4042500 | P23: 4042500 | Q23: 4042500 | R23: 4042500 | S23: 3672900 | T23: 3234000 | U23: 2910600 | V23: 2910600 | W23: 2633400 | X23: 2402400 | Y23: 2113650 | Z23: 1928850 | AA23: 1693230 | AB23: 1598520
G24: Successive Plus | H24: 1 month | I24: KL4066WA*M4 | K24: 241395 | L24: 241395 | M24: 241395 | N24: 241395 | O24: 241395 | P24: 241395 | Q24: 241395 | R24: 241395 | S24: 218526 | T24: 193116 | U24: 172788 | V24: 172788 | W24: 157542 | X24: 142296 | Y24: 127050 | Z24: 114345 | AA24: 101640 | AB24: 94017
H25: 1 year | I25: KL4066WA*F4 | K25: 2402400 | L25: 2402400 | M25: 2402400 | N25: 2402400 | O25: 2402400 | P25: 2402400 | Q25: 2402400 | R25: 2402400 | S25: 2180640 | T25: 1928850 | U25: 1732500 | V25: 1732500 | W25: 1566180 | X25: 1425270 | Y25: 1258950 | Z25: 1145760 | AA25: 1007160 | AB25: 949410
H26: 2 year | I26: KL4066WA*D4 | K26: 3603600 | L26: 3603600 | M26: 3603600 | N26: 3603600 | O26: 3603600 | P26: 3603600 | Q26: 3603600 | R26: 3603600 | S26: 3280200 | T26: 2887500 | U26: 2610300 | V26: 2610300 | W26: 2356200 | X26: 2136750 | Y26: 1884960 | Z26: 1718640 | AA26: 1508430 | AB26: 1425270
H27: 3 year | I27: KL4066WA*T4 | K27: 4458300 | L27: 4458300 | M27: 4458300 | N27: 4458300 | O27: 4458300 | P27: 4458300 | Q27: 4458300 | R27: 4458300 | S27: 4042500 | T27: 3557400 | U27: 3210900 | V27: 3210900 | W27: 2887500 | X27: 2633400 | Y27: 2333100 | Z27: 2118270 | AA27: 1861860 | AB27: 1757910
B28: 2004 | C28: Kaspersky Next EDR Expert | D28: User | E28: License | F28: User | G28: Successive Plus | H28: 1 month | I28: KL4069WA*M4 | W28: 443520 | X28: 334257 | Y28: 279510 | Z28: 270732 | AA28: 265650 | AB28: 263109
H29: 1 year | I29: KL4069WA*F4 | W29: 4435200 | X29: 3349500 | Y29: 2795100 | Z29: 2702700 | AA29: 2656500 | AB29: 2633400
H30: 2 year | I30: KL4069WA*D4 | W30: 7091700 | X30: 5359200 | Y30: 4481400 | Z30: 4342800 | AA30: 4250400 | AB30: 4204200
H31: 3 year | I31: KL4069WA*T4 | W31: 9979200 | X31: 7530600 | Y31: 6283200 | Z31: 6098400 | AA31: 5982900 | AB31: 5913600
B32: 2005 | C32: Kaspersky Next XDR Optimum | D32: User | E32: License | F32: User | G32: Successive | H32: 1 month | I32: KL4085WA*MG | O32: 284130 | P32: 284130 | Q32: 284130 | R32: 284130 | S32: 257565 | T32: 227997 | U32: 204897 | V32: 204897 | W32: 185031 | X32: 168399 | Y32: 148764 | Z32: 135366 | AA32: 118965 | AB32: 112266
H33: 1 year | I33: KL4085WA*FG | O33: 2841300 | P33: 2841300 | Q33: 2841300 | R33: 2841300 | S33: 2587200 | T33: 2286900 | U33: 2055900 | V33: 2055900 | W33: 1848000 | X33: 1683990 | Y33: 1487640 | Z33: 1353660 | AA33: 1189650 | AB33: 1122660
H34: 2 year | I34: KL4085WA*DG | O34: 4273500 | P34: 4273500 | Q34: 4273500 | R34: 4273500 | S34: 3880800 | T34: 3418800 | U34: 3072300 | V34: 3072300 | W34: 2772000 | X34: 2517900 | Y34: 2240700 | Z34: 2032800 | AA34: 1778700 | AB34: 1683990
H35: 3 year | I35: KL4085WA*TG | O35: 5266800 | P35: 5266800 | Q35: 5266800 | R35: 5266800 | S35: 4781700 | T35: 4204200 | U35: 3788400 | V35: 3788400 | W35: 3418800 | X35: 3118500 | Y35: 2748900 | Z35: 2517900 | AA35: 2194500 | AB35: 2079000
G36: Successive Plus | H36: 1 month | I36: KL4085WA*M4 | O36: 313929 | P36: 313929 | Q36: 313929 | R36: 313929 | S36: 284130 | T36: 251097 | U36: 224532 | V36: 224532 | W36: 204897 | X36: 185031 | Y36: 165165 | Z36: 148764 | AA36: 132132 | AB36: 122199
H37: 1 year | I37: KL4085WA*F4 | O37: 3118500 | P37: 3118500 | Q37: 3118500 | R37: 3118500 | S37: 2841300 | T37: 2517900 | U37: 2263800 | V37: 2263800 | W37: 2032800 | X37: 1848000 | Y37: 1637790 | Z37: 1489950 | AA37: 1309770 | AB37: 1233540
H38: 2 year | I38: KL4085WA*D4 | O38: 4689300 | P38: 4689300 | Q38: 4689300 | R38: 4689300 | S38: 4273500 | T38: 3765300 | U38: 3395700 | V38: 3395700 | W38: 3072300 | X38: 2772000 | Y38: 2448600 | Z38: 2240700 | AA38: 1963500 | AB38: 1848000
H39: 3 year | I39: KL4085WA*T4 | O39: 5798100 | P39: 5798100 | Q39: 5798100 | R39: 5798100 | S39: 5266800 | T39: 4620000 | U39: 4181100 | V39: 4181100 | W39: 3765300 | X39: 3418800 | Y39: 3026100 | Z39: 2748900 | AA39: 2425500 | AB39: 2286900
B40: 2006 | C40: Kaspersky Next XDR Expert | D40: User | E40: License | F40: User | G40: Successive | H40: 1 month | I40: KL4054WA*MG | W40: 481250 | X40: 360503 | Y40: 302753 | Z40: 293997 | AA40: 288750 | AB40: 283503
H41: 1 year | I41: KL4054WA*FG | W41: 5293750 | X41: 3965500 | Y41: 3330250 | Z41: 3234000 | AA41: 3176250 | AB41: 3118500
H42: 2 year | I42: KL4054WA*DG | W42: 7911750 | X42: 5967500 | Y42: 4985750 | Z42: 4851000 | AA42: 4793250 | AB42: 4677750
H43: 3 year | I43: KL4054WA*TG | W43: 9759750 | X43: 7353500 | Y43: 6179250 | Z43: 5967500 | AA43: 5871250 | AB43: 5775000
G44: Successive Plus | H44: 1 month | I44: KL4054WA*M4 | W44: 577500 | X44: 432597 | Y44: 363297 | Z44: 352803 | AA44: 346500 | AB44: 340197
H45: 1 year | I45: KL4054WA*F4 | W45: 6352500 | X45: 4758600 | Y45: 3996300 | Z45: 3880800 | AA45: 3811500 | AB45: 3742200
H46: 2 year | I46: KL4054WA*D4 | W46: 9494100 | X46: 7161000 | Y46: 5982900 | Z46: 5821200 | AA46: 5751900 | AB46: 5613300
H47: 3 year | I47: KL4054WA*T4 | W47: 11711700 | X47: 8824200 | Y47: 7415100 | Z47: 7161000 | AA47: 7045500 | AB47: 6930000
B48: 2007 | C48: Kaspersky Next XDR Core | D48: User | E48: License | F48: User | G48: Successive | H48: 1 month | I48: KL4056WA*MG | W48: 183755 | X48: 138424 | Y48: 115676 | Z48: 112178 | AA48: 109901 | AB48: 109197
H49: 1 year | I49: KL4056WA*FG | W49: 2021250 | X49: 1522675 | Y49: 1272425 | Z49: 1233925 | AA49: 1208900 | AB49: 1201200
H50: 2 year | I50: KL4056WA*DG | W50: 3234000 | X50: 2444750 | Y50: 2040500 | Z50: 1982750 | AA50: 1925000 | AB50: 1925000
H51: 3 year | I51: KL4056WA*TG | W51: 4639250 | X51: 3503500 | Y51: 2926000 | Z51: 2849000 | AA51: 2772000 | AB51: 2752750
G52: Successive Plus | H52: 1 month | I52: KL4056WA*M4 | W52: 220495 | X52: 166111 | Y52: 138809 | Z52: 134607 | AA52: 131879 | AB52: 131043
H53: 1 year | I53: KL4056WA*F4 | W53: 2425500 | X53: 1827210 | Y53: 1526910 | Z53: 1480710 | AA53: 1450680 | AB53: 1441440
H54: 2 year | I54: KL4056WA*D4 | W54: 3880800 | X54: 2933700 | Y54: 2448600 | Z54: 2379300 | AA54: 2310000 | AB54: 2310000
H55: 3 year | I55: KL4056WA*T4 | W55: 5567100 | X55: 4204200 | Y55: 3511200 | Z55: 3418800 | AA55: 3326400 | AB55: 3303300
B56: 2008 | C56: Kaspersky Next MXDR Optimum | D56: User | E56: License | F56: User | G56: Successive | H56: 1 month | I56: KL4086WA*MG | V56: 314160 | W56: 298914 | X56: 284130 | Y56: 269115 | Z56: 259875 | AA56: 251097 | AB56: 245322
H57: 1 year | I57: KL4086WA*FG | V57: 3141600 | W57: 2979900 | X57: 2841300 | Y57: 2679600 | Z57: 2610300 | AA57: 2517900 | AB57: 2448600
H58: 2 year | I58: KL4086WA*DG | V58: 5913600 | W58: 5636400 | X58: 5359200 | Y58: 5082000 | Z58: 4920300 | AA58: 4781700 | AB58: 4666200
H59: 3 year | I59: KL4086WA*TG | V59: 8547000 | W59: 8154300 | X59: 7761600 | Y59: 7392000 | Z59: 7161000 | AA59: 6953100 | AB59: 6814500
G60: Successive Plus | H60: 1 month | I60: KL4086WA*M4 | V60: 345576 | W60: 328944 | X60: 312312 | Y60: 295911 | Z60: 286209 | AA60: 276045 | AB60: 269808
H61: 1 year | I61: KL4086WA*F4 | V61: 3465000 | W61: 3280200 | X61: 3118500 | Y61: 2956800 | Z61: 2864400 | AA61: 2772000 | AB61: 2702700
H62: 2 year | I62: KL4086WA*D4 | V62: 6491100 | W62: 6190800 | X62: 5890500 | Y62: 5590200 | Z62: 5405400 | AA62: 5243700 | AB62: 5128200
H63: 3 year | I63: KL4086WA*T4 | V63: 9401700 | W63: 8985900 | X63: 8547000 | Y63: 8131200 | Z63: 7877100 | AA63: 7646100 | AB63: 7484400
B64: 3000 | C64: Small Office Security | D64: - | E64: - | F64: - | G64: - | H64: - | I64: -
B65: 3001 | C65: Kaspersky Small Office Security for Desktops, Mobiles and File Servers (fixed-date) | D65: MD+Dt+FS+User | E65: License | G65: Successive | H65: 1 month | I65: KL4542WA*MG | O65: 190575 | P65: 114345 | Q65: 114345 | R65: 114345 | S65: 101640
H66: 1 year | I66: KL4542WA*FG | O66: 2122890 | P66: 1233540 | Q66: 1233540 | R66: 1233540 | S66: 1106490
H67: 2 year | I67: KL4542WA*DG | O67: 2887500 | P67: 1677060 | Q67: 1677060 | R67: 1677060 | S67: 1513050
H68: 3 year | I68: KL4542WA*TG | O68: 3580500 | P68: 2072070 | Q68: 2072070 | R68: 2072070 | S68: 1868790
B69: 4010 | C69: Endpoint Security | D69: - | E69: - | F69: - | G69: - | H69: - | I69: - | P69: 0
B70: 4021 | C70: Kaspersky Endpoint Detection and Response Expert Telemetry Retention 60 days | D70: Node | E70: Certificate. | G70: Successive | H70: 1 month | I70: KL4714W1*MG | W70: 48279 | X70: 45738 | Y70: 43197 | Z70: 38115 | AA70: 35574 | AB70: 33033
H71: 1 year | I71: KL4714W1*FG | W71: 482790 | X71: 448140 | Y71: 429660 | Z71: 385770 | AA71: 351120 | AB71: 334950
B72: 4022 | C72: Kaspersky Endpoint Detection and Response Expert Telemetry Retention 90 days | D72: Node | E72: Certificate. | G72: Successive | H72: 1 month | I72: KL4715W1*MG | W72: 68607 | X72: 60984 | Y72: 58443 | Z72: 55902 | AA72: 48279 | AB72: 45738
H73: 1 year | I73: KL4715W1*FG | W73: 681450 | X73: 619080 | Y73: 593670 | Z73: 559020 | AA73: 496650 | AB73: 471240
B74: 4510 | C74: Targeted Security | E74: - | F74: - | G74: - | H74: - | I74: - | P74: 0
B75: 4511 | C75: Kaspersky Security for Microsoft Office 365 | D75: Mx | E75: License | G75: Successive | H75: 1 month | I75: KL4312WA*MG | O75: 88935 | P75: 88935 | Q75: 88935 | R75: 88935 | S75: 88935 | T75: 77616 | U75: 77616 | V75: 63525 | W75: 63525 | X75: 63525 | Y75: 53361 | Z75: 48279 | AA75: 44583 | AB75: 40656
H76: 1 year | I76: KL4312WA*FG | O76: 979440 | P76: 979440 | Q76: 979440 | R76: 979440 | S76: 979440 | T76: 852390 | U76: 852390 | V76: 699930 | W76: 699930 | X76: 699930 | Y76: 586740 | Z76: 531300 | AA76: 489720 | AB76: 448140
H77: 2 year | I77: KL4312WA*DG | P77: 1335180 | Q77: 1335180 | R77: 1335180 | S77: 1335180 | T77: 1161930 | U77: 1161930 | V77: 954030 | W77: 954030 | X77: 954030 | Y77: 801570 | Z77: 725340 | AA77: 667590 | AB77: 609840
H78: 3 year | I78: KL4312WA*TG | P78: 1644720 | Q78: 1644720 | R78: 1644720 | S78: 1644720 | T78: 1434510 | U78: 1434510 | V78: 1175790 | W78: 1175790 | X78: 1175790 | Y78: 986370 | Z78: 893970 | AA78: 822360 | AB78: 753060
G79: Successive Plus | H79: 1 month | I79: KL4312WA*M4 | O79: 97944 | P79: 97944 | Q79: 97944 | R79: 97944 | S79: 97944 | T79: 85470 | U79: 85470 | V79: 69993 | W79: 69993 | X79: 69993 | Y79: 58674 | Z79: 53130 | AA79: 48741 | AB79: 44814
H80: 1 year | I80: KL4312WA*F4 | O80: 1076460 | P80: 1076460 | Q80: 1076460 | R80: 1076460 | S80: 1076460 | T80: 937860 | U80: 937860 | V80: 769230 | W80: 769230 | X80: 769230 | Y80: 646800 | Z80: 584430 | AA80: 538230 | AB80: 492030
H81: 2 year | I81: KL4312WA*D4 | P81: 1466850 | Q81: 1466850 | R81: 1466850 | S81: 1466850 | T81: 1279740 | U81: 1279740 | V81: 1048740 | W81: 1048740 | X81: 1048740 | Y81: 880110 | Z81: 796950 | AA81: 734580 | AB81: 669900
H82: 3 year | I82: KL4312WA*T4 | P82: 1811040 | Q82: 1811040 | R82: 1811040 | S82: 1811040 | T82: 1577730 | U82: 1577730 | V82: 1293600 | W82: 1293600 | X82: 1293600 | Y82: 1085700 | Z82: 981750 | AA82: 905520 | AB82: 826980
B83: 4512 | C83: Kaspersky Security for Mail Server | D83: Em | E83: License | F83: User | G83: Successive | H83: 1 month | I83: KL4313WA*MG | P83: 89448 | Q83: 89448 | R83: 89448 | S83: 80771 | T83: 72094.4 | U83: 65153.2 | V83: 65153.2 | W83: 58212 | X83: 52059.5 | Y83: 46853.5 | Z83: 42594.1 | AA83: 38176.9 | AB83: 34706.3
H84: 1 year | I84: KL4313WA*FG | P84: 982328 | Q84: 982328 | R84: 982328 | S84: 887040 | T84: 791753 | U84: 715523 | V84: 715523 | W84: 639293 | X84: 571725 | Y84: 514553 | Z84: 467775 | AA84: 419265 | AB84: 381150
H85: 2 year | I85: KL4313WA*DG | P85: 1339053.4 | Q85: 1339053.4 | R85: 1339053.4 | S85: 1209163 | T85: 1079272.4 | U85: 975359.9 | V85: 975359.9 | W85: 871448 | X85: 779343.3 | Y85: 701409 | Z85: 637644.5 | AA85: 571518.3 | AB85: 519562.1
H86: 3 year | I86: KL4313WA*TG | P86: 1653185.3 | Q86: 1653185.3 | R86: 1653185.3 | S86: 1492823.3 | T86: 1332461.5 | U86: 1204172 | V86: 1204172 | W86: 1075883 | X86: 962171.3 | Y86: 865954 | Z86: 787231.1 | AA86: 705592.3 | AB86: 641447.5
G87: Successive Plus | H87: 1 month | I87: KL4313WA*M4 | P87: 98499 | Q87: 98499 | R87: 98499 | S87: 88944.4 | T87: 79389.8 | U87: 71746.1 | V87: 71746.1 | W87: 64103 | X87: 57327.4 | Y87: 51594.6 | Z87: 46904.2 | AA87: 42040 | AB87: 38218.3
H88: 1 year | I88: KL4313WA*F4 | P88: 1080826.5 | Q88: 1080826.5 | R88: 1080826.5 | S88: 975984.4 | T88: 871142.3 | U88: 787268.6 | V88: 787268.6 | W88: 703395 | X88: 629052.4 | Y88: 566147.1 | Z88: 514679.2 | AA88: 461305 | AB88: 419368.3
H89: 2 year | I89: KL4313WA*D4 | P89: 1474822.3 | Q89: 1474822.3 | R89: 1474822.3 | S89: 1331761.9 | T89: 1188701.6 | U89: 1074253.3 | V89: 1074253.3 | W89: 959805 | X89: 858362.1 | Y89: 772525.9 | Z89: 702296.3 | AA89: 629465.5 | AB89: 572241.5
H90: 3 year | I90: KL4313WA*T4 | P90: 1818237.5 | Q90: 1818237.5 | R90: 1818237.5 | S90: 1641865.3 | T90: 1465493 | U90: 1324395.3 | V90: 1324395.3 | W90: 1183298 | X90: 1058233.4 | Y90: 952410.1 | Z90: 865827.4 | AA90: 776038 | AB90: 705489
B91: 4513 | C91: Kaspersky Security for Mail Server Plus | D91: Em | E91: License | F91: Em | G91: Successive | H91: 1 month | I91: KL4319WA*MG | P91: 116411 | Q91: 116411 | R91: 116411 | S91: 105118 | T91: 93827 | U91: 84792 | V91: 84792 | W91: 75759 | X91: 67752 | Y91: 60977 | Z91: 55433 | AA91: 49685 | AB91: 45168
H92: 1 year | I92: KL4319WA*FG | P92: 1279079 | Q92: 1279079 | R92: 1279079 | S92: 1155006 | T92: 1030933 | U92: 931675 | V92: 931675 | W92: 832416 | X92: 744437 | Y92: 669994 | Z92: 609085 | AA92: 545921 | AB92: 496291
H93: 2 year | I93: KL4319WA*DG | P93: 1745131 | Q93: 1745131 | R93: 1745131 | S93: 1575851 | T93: 1406570 | U93: 1271146 | V93: 1271146 | W93: 1135720 | X93: 1015685 | Y93: 914117 | Z93: 831015 | AA93: 744835 | AB93: 677124
H94: 3 year | I94: KL4319WA*TG | P94: 2155751 | Q94: 2155751 | R94: 2155751 | S94: 1946639 | T94: 1737528 | U94: 1570238 | V94: 1570238 | W94: 1402949 | X94: 1254670 | Y94: 1129203 | Z94: 1026548 | AA94: 920092 | AB94: 836447
G95: Successive Plus | H95: 1 month | I95: KL4319WA*M4 | P95: 127908 | Q95: 127908 | R95: 127908 | S95: 115501 | T95: 103093 | U95: 93168 | V95: 93168 | W95: 83241 | X95: 74444 | Y95: 67000 | Z95: 60908 | AA95: 54592 | AB95: 49629
H96: 1 year | I96: KL4319WA*F4 | P96: 1408424 | Q96: 1408424 | R96: 1408424 | S96: 1271805 | T96: 1135185 | U96: 1025889 | V96: 1025889 | W96: 916594 | X96: 819718 | Y96: 737746 | Z96: 670678 | AA96: 601126 | AB96: 546479
H97: 2 year | I97: KL4319WA*D4 | P97: 1919645 | Q97: 1919645 | R97: 1919645 | S97: 1733436 | T97: 1547227 | U97: 1398260 | V97: 1398260 | W97: 1249293 | X97: 1117254 | Y97: 1005529 | Z97: 914117 | AA97: 819320 | AB97: 744835
H98: 3 year | I98: KL4319WA*T4 | P98: 2361061 | Q98: 2361061 | R98: 2361061 | S98: 2132033 | T98: 1903007 | U98: 1719785 | V98: 1719785 | W98: 1536564 | X98: 1374162 | Y98: 1236747 | Z98: 1124314 | AA98: 1007719 | AB98: 916109
B99: 4523 | C99: Kaspersky Security for Internet Gateway | D99: Node | E99: License | F99: User | G99: Successive | H99: 1 month | I99: KL4413WA*MG | P99: 58443 | Q99: 58443 | R99: 58443 | S99: 55902 | T99: 53361 | U99: 48279 | V99: 48279 | W99: 43197 | X99: 36960 | Y99: 34419 | Z99: 30492 | AA99: 29337 | AB99: 26796
H100: 1 year | I100: KL4413WA*FG | P100: 642180 | Q100: 642180 | R100: 642180 | S100: 614460 | T100: 586740 | U100: 531300 | V100: 531300 | W100: 475860 | X100: 404250 | Y100: 376530 | Z100: 334950 | AA100: 321090 | AB100: 293370
H101: 2 year | I101: KL4413WA*DG | P101: 877800 | Q101: 877800 | R101: 877800 | S101: 838530 | T101: 801570 | U101: 725340 | V101: 725340 | W101: 649110 | X101: 552090 | Y101: 515130 | Z101: 457380 | AA101: 438900 | AB101: 399630
H102: 3 year | I102: KL4413WA*TG | P102: 1081080 | Q102: 1081080 | R102: 1081080 | S102: 1034880 | T102: 986370 | U102: 893970 | V102: 893970 | W102: 799260 | X102: 681450 | Y102: 635250 | Z102: 563640 | AA102: 540540 | AB102: 494340
G103: Successive Plus | H103: 1 month | I103: KL4413WA*M4 | P103: 64218 | Q103: 64218 | R103: 64218 | S103: 61446 | T103: 58674 | U103: 53130 | V103: 53130 | W103: 47586 | X103: 40656 | Y103: 37653 | Z103: 33495 | AA103: 32109 | AB103: 29568
H104: 1 year | I104: KL4413WA*F4 | P104: 706860 | Q104: 706860 | R104: 706860 | S104: 676830 | T104: 646800 | U104: 584430 | V104: 584430 | W104: 522060 | X104: 445830 | Y104: 415800 | Z104: 369600 | AA104: 353430 | AB104: 323400
H105: 2 year | I105: KL4413WA*D4 | P105: 963270 | Q105: 963270 | R105: 963270 | S105: 921690 | T105: 880110 | U105: 796950 | V105: 796950 | W105: 713790 | X105: 607530 | Y105: 565950 | Z105: 503580 | AA105: 482790 | AB105: 441210
H106: 3 year | I106: KL4413WA*T4 | P106: 1189650 | Q106: 1189650 | R106: 1189650 | S106: 1136520 | T106: 1085700 | U106: 981750 | V106: 981750 | W106: 880110 | X106: 750750 | Y106: 697620 | Z106: 621390 | AA106: 593670 | AB106: 542850
...

Sheet xSP
C7: =CONCATENATE("Price List applicable for ",Data!A9,". Effective from ",Data!A11,". ") -> Price List applicable for Vietnam. Effective from July 1, 2026.
C8: =CONCATENATE(Data!A5,". ",Data!A7) -> Kaspersky Lab. 39A/3 Leningradskoe Shosse Moscow, 125212. 0
B9: Max of Price | J9: Band
B10: Code | C10: Product | D10: LicenceDescription | E10: Package | F10: LicenceObject | G10: Type | H10: Term | I10: SKU | J10: Band P: 250-499 | K10: Band Q: 500-999 | L10: Band R: 1000-1499 | M10: Band S: 1500-2499 | N10: Band T: 2500-4999 | O10: Band U: 5000-9999 | P10: Band V: 10000+
B11: 5111 | C11: Kaspersky Anti-Virus for xSP | D11: TrafficD | E11: Traffic Licence | F11: Mb of traffic per day | G11: Base | H11: 1 year | I11: KL5111NQ*FS | J11: 8 | K11: 5.5 | L11: 5 | M11: 4.5 | N11: 4 | O11: 3.5 | P11: 3
B12: 5811 | C12: Kaspersky Security for xSP | D12: TrafficD | E12: Traffic Licence | F12: Mb of traffic per day | G12: Base | H12: 1 year | I12: KL5811NQ*FS | J12: 15 | K12: 10.5 | L12: 9.5 | M12: 8.5 | N12: 7.5 | O12: 6.5 | P12: 5.5

Sheet Traffic
C7: =CONCATENATE("Price List applicable for ",Data!A9,". Effective from ",Data!A11,". ") -> Price List applicable for Vietnam. Effective from July 1, 2026.
C8: =CONCATENATE(Data!A5,". ",Data!A7) -> Kaspersky Lab. 39A/3 Leningradskoe Shosse Moscow, 125212. 0
B9: Max of Price | J9: Band
B10: Code | C10: Product | D10: LicenceDescription | E10: Package | F10: LicenceObject | G10: Type | H10: Term | I10: SKU | J10: Band P: 250-499 | K10: Band Q: 500-999 | L10: Band R: 1000-1499 | M10: Band S: 1500-2499 | N10: Band T: 2500-4999 | O10: Band U: 5000-9999 | P10: Band V: 10000+
B11: 5111 | C11: Kaspersky Anti-Virus for xSP | D11: TrafficD | E11: Traffic Licence | F11: Mb of traffic per day | G11: Base | H11: 1 year | I11: KL5111NQ*FS | J11: 8 | K11: 5.5 | L11: 5 | M11: 4.5 | N11: 4 | O11: 3.5 | P11: 3
B12: 5811 | C12: Kaspersky Security for xSP | D12: TrafficD | E12: Traffic Licence | F12: Mb of traffic per day | G12: Base | H12: 1 year | I12: KL5811NQ*FS | J12: 15 | K12: 10.5 | L12: 9.5 | M12: 8.5 | N12: 7.5 | O12: 6.5 | P12: 5.5

Sheet ProfessionalServices
C7: =CONCATENATE("Price List applicable for ",Data!A9,". Effective from ",Data!A11,". ") -> Price List applicable for Vietnam. Effective from July 1, 2026. | T7: * For additional details please see
C8: =CONCATENATE(Data!A5,". ",Data!A7) -> Kaspersky Lab. 39A/3 Leningradskoe Shosse Moscow, 125212. 0 | T8: specifications in Comment section
B9: Max of Price | J9: Band
B10: Code | C10: Product | D10: LicenceDescription | E10: Package | F10: LicenceObject | G10: Type | H10: Term | I10: SKU | K10: Band A: 1-1 | L10: Band B: 2-2 | M10: Band C: 3-3 | N10: Band D: 4-4 | O10: Band E: 5-9 | P10: Band K: 10-14 | Q10: Band M: 15-19 | R10: Band N: 20-24 | S10: Band P: 25-49 | T10: Band Q: 50-99 | U10: Band R: 100-149 | V10: Band S: 150-249
B11: 3000 | C11: Premium Support | D11: (blank) | E11: - | F11: - | G11: - | H11: - | I11: -
B12: 3001 | C12: Kaspersky Enhanced Support | D12: Case | E12: Certificate | H12: 1 year | I12: KL7122WL*FZ | J12: 377338500
H13: 2 year | I13: KL7122WL*DZ | J13: 754677000
H14: 3 year | I14: KL7122WL*TZ | J14: 1132015500
B15: 3002 | C15: Kaspersky Enhanced Support with TAM | D15: Case | E15: Certificate | H15: 1 year | I15: KL7124WL*FZ | J15: 754677000
H16: 2 year | I16: KL7124WL*DZ | J16: 1509354000
H17: 3 year | I17: KL7124WL*TZ | J17: 2264031000
B18: 3003 | C18: Kaspersky Enhanced Support Pro | D18: Case | E18: Certificate | F18: Case | H18: 1 year | I18: KL7129WL*FZ | J18: 1837578600
H19: 2 year | I19: KL7129WL*DZ | J19: 3675157200
H20: 3 year | I20: KL7129WL*TZ | J20: 5512735800
B21: 3004 | C21: Kaspersky Maintenance Service Agreement for MSP | D21: Case | E21: Certificate. | H21: 1 year | I21: KL7133W1*FZ | K21: 12912900 | L21: 11342100 | M21: 11342100 | N21: 11342100 | O21: 9725100 | P21: 8154300 | Q21: 8154300 | R21: 8154300 | S21: 8154300
B22: 3007 | C22: Kaspersky Maintenance Service Agreement for Partners | D22: Incident | E22: Certificate. | F22: Incident | H22: 1 year | I22: KL7227W1*FZ | O22: 16863000 | P22: 16863000 | Q22: 16863000
B23: 6050 | C23: Professional Services | D23: - | E23: - | F23: - | G23: - | H23: - | I23: -
B24: 6051 | C24: Kaspersky Professional Services - 4 Hours, Remote | D24: Day | E24: Certificate. | H24: 1 year | I24: KL7221W1*FZ | K24: 25155900
B25: 6052 | C25: Kaspersky Professional Services - 8 Hours, On-site | D25: Day | E25: Certificate. | H25: 1 year | I25: KL7224W1*FZ | K25: 92238300 | L25: 92238300 | M25: 92238300 | N25: 92238300 | O25: 92238300 | P25: 92238300 | Q25: 92238300 | R25: 92238300 | S25: 92238300 | T25: 92238300 | U25: 92238300 | V25: 92238300
B26: 6053 | C26: Kaspersky Professional Services - 8 Hours, Remote | D26: Day | E26: Certificate. | H26: 1 year | I26: KL7222W1*FZ | K26: 47516700 | L26: 47516700 | M26: 47516700 | N26: 47516700 | O26: 47516700 | P26: 47516700 | Q26: 47516700 | R26: 47516700 | S26: 47516700 | T26: 47516700 | U26: 47516700 | V26: 47516700
B27: 6054 | C27: Kaspersky Deployment service - 8 hours | D27: Case | E27: Certificate | H27: 1 year | I27: KL7231WL*FZ | J27: 47516700
B28: 6055 | C28: Kaspersky Disk Encryption service - 8 hours | D28: Case | E28: Certificate | H28: 1 year | I28: KL7232WL*FZ | J28: 47516700
B29: 6056 | C29: Kaspersky Upgrade service - 8 hours | D29: Case | E29: Certificate | H29: 1 year | I29: KL7234WL*FZ | J29: 47516700
B30: 6057 | C30: Kaspersky Health Check service - 2 hours | D30: Case | E30: Certificate | H30: 1 year | I30: KL7267WL*FZ | J30: 11896500
B31: 6058 | C31: Kaspersky Health Check service - 4 hours | D31: Case | E31: Certificate | H31: 1 year | I31: KL7268WL*FZ | J31: 23769900
B32: 6059 | C32: Kaspersky Health Check service - 8 hours | D32: Case | E32: Certificate | H32: 1 year | I32: KL7269WL*FZ | J32: 47516700
B33: 6061 | C33: Kaspersky Vulnerability and Patch management service - 8 hours | D33: Case | E33: Certificate | H33: 1 year | I33: KL7299WL*FZ | J33: 47516700
B34: 6062 | C34: Kaspersky Essential Installation service for Kaspersky Unified Monitoring and Analysis Platform | D34: Case | E34: Certificate | F34: Case | H34: 1 year | I34: KL7106WL*FZ | J34: 403891950
B35: 6063 | C35: Kaspersky Essential Installation service for Kaspersky XDR | D35: Case | E35: Certificate | F35: Case | H35: 1 year | I35: KL7107WL*FZ | J35: 605837925

Sheet SecurityServices
C7: =CONCATENATE("Price List applicable for ",Data!A9,". Effective from ",Data!A11,". ") -> Price List applicable for Vietnam. Effective from July 1, 2026. | W7: * For additional details please see
C8: =CONCATENATE(Data!A5,". ",Data!A7) -> Kaspersky Lab. 39A/3 Leningradskoe Shosse Moscow, 125212. 0 | W8: specifications in Comment section
B9: Max of Price | J9: Band
B10: Code | C10: Product | D10: LicenceDescription | E10: Package | F10: LicenceObject | G10: Type | H10: Term | I10: SKU | J10: Band Z: 1 | K10: Band A: 1 | L10: Band A: 1-1 | M10: Band B: 3 | N10: Band C: 5 | O10: Band D: 10 | P10: Band F: 20 | Q10: Band Q: 50-99 | R10: Band R: 100-149 | S10: Band S: 150-249 | T10: Band T: 250-499 | U10: Band U: 400 | V10: Band U: 500-999 | W10: Band W: 1000 | X10: Band 2: 2000 | Y10: Band X: 5000 | Z10: Band Y: 10000
B11: 5000 | C11: Security Awareness | D11: (blank) | E11: - | F11: - | G11: - | H11: - | I11: -
B12: 5001 | C12: Kaspersky Interactive Protection Simulation Training | D12: Case | E12: Certificate | G12: Base | H12: 1 year | I12: KL7556WL*FS | K12: 270015900 | M12: 665395500 | N12: 964309500
G13: Renewal | H13: 1 year | I13: KL7556WL*FR | K13: 270015900 | M13: 665395500 | N13: 964309500
B14: 8000 | C14: Threat Intelligence | D14: (blank) | E14: - | F14: - | G14: - | H14: - | I14: -
B15: 8001 | C15: Kaspersky Ask the Analyst | D15: Case | E15: Certificate | G15: Base | H15: 1 year | I15: KL7798WL*FS | N15: 566019300 | O15: 1132015500 | P15: 2264031000
H16: 3 year | I16: KL7798WL*TS | N16: 1443311100 | O16: 2886622200 | P16: 5773290600
H17: 2 year | I17: KL7798WL*DS | N17: 1018825500 | O17: 2037627900 | P17: 4075255800
B18: 8002 | C18: Kaspersky Takedown Service | D18: Queries per month | E18: Certificate | G18: Base | H18: 1 year | I18: KL7937WL*FS | O18: 594801900
B19: 8003 | C19: Kaspersky Incident Response Retainer Remote | D19: Hour | E19: Certificate. | H19: 1 year | I19: KL7056W1*FZ | Q19: 11665500 | R19: 10302600 | S19: 9609600 | T19: 9124500 | V19: 8662500
H20: 3 year | I20: KL7056W1*TZ | T20: 10493175 | V20: 9961875
H21: 2 year | I21: KL7056W1*DZ | S21: 10570560 | T21: 10036950 | V21: 9528750
B22: 8004 | C22: Kaspersky Incident Response Retainer On-site | D22: Hour | E22: Certificate. | H22: 1 year | I22: KL7057W1*FZ | Q22: 14414400 | R22: 13721400 | S22: 11845064 | T22: 11235389 | V22: 10712812
H23: 3 year | I23: KL7057W1*TZ | T23: 12920699 | V23: 12319736
H24: 2 year | I24: KL7057W1*DZ | S24: 13029577 | T24: 12358929 | V24: 11784102
B25: 8005 | C25: Kaspersky Incident Response Emergency (Remote) | D25: Incident | E25: Certificate. | F25: Incident | H25: 1 year | I25: KL7858W1*FZ | L25: 820000000
B26: 8006 | C26: Kaspersky Incident Response Emergency (On-site) | D26: Incident | E26: Certificate. | F26: Incident | H26: 1 year | I26: KL7859W1*FZ | L26: 1020000000
B27: 8007 | C27: Kaspersky Adversary Attack Emulation | D27: Case | E27: Certificate | F27: Case | H27: 1 year | I27: KL7881WL*FZ | J27: 787500000
B28: 8008 | C28: Kaspersky Incident Response Plan Development | D28: Case | E28: Certificate | F28: Case | H28: 1 year | I28: KL7882WL*FZ | J28: 1022500000
B29: 8009 | C29: Kaspersky SOC Maturity Assessment by SOC-CMM methodology | D29: Case | E29: Certificate | F29: Case | H29: 1 year | I29: KL7883WL*FZ | J29: 762500000
B30: 8011 | C30: Kaspersky Remote Compromise Assessment* | D30: Node | E30: Certificate | F30: Node | H30: 1 year | I30: KL7884WL*FZ | U30: 1102500000 | W30: 1102500000 | X30: 1190000000 | Y30: 1312499999 | Z30: 1592500000

Sheet SIEM
C7: =CONCATENATE("Price List applicable for ",Data!A9,". Effective from ",Data!A11,". ") -> Price List applicable for Vietnam. Effective from July 1, 2026. | U7: * For additional details please see
C8: =CONCATENATE(Data!A5,". ",Data!A7) -> Kaspersky Lab. 39A/3 Leningradskoe Shosse Moscow, 125212. 0 | U8: specifications in Comment section
B9: Max of Price | J9: Band
B10: Code | C10: Product | D10: LicenceDescription | E10: Package | F10: LicenceObject | G10: Type | H10: Term | I10: SKU | J10: Band E: 5-9 | K10: Band K: 10-14 | L10: Band M: 15-19 | M10: Band N: 20-24 | N10: Band P: 25-49 | O10: Band Q: 50-99 | P10: Band R: 100-149 | Q10: Band S: 150-249 | R10: Band T: 250-499 | S10: Band U: 500-999 | T10: Band V: 1000-1499 | U10: Band W: 1500-2499 | V10: Band X: 2500-4999 | W10: Band Y: 5000+
B11: 4000 | C11: Kaspersky Anti Targeted Attack Platform | D11: - | E11: - | F11: - | G11: - | H11: - | I11: -
B12: 4032 | C12: Kaspersky Unified Monitoring and Analysis Platform | D12: * 100 events per second | E12: License | G12: Base Premium | H12: 1 year | I12: KL4032WA*FA | J12: 175329000 | K12: 132501600 | L12: 110695200 | M12: 107461200 | N12: 105058800 | O12: 104250300 | P12: 103441800 | Q12: 93116100 | R12: 88449900 | S12: 84037800 | T12: 79833600 | U12: 79833600 | V12: 79833600 | W12: 79833600
H13: 2 year | I13: KL4032WA*DA | J13: 280526400 | K13: 212011800 | L13: 177107700 | M13: 171956400 | N13: 168098700 | O13: 166805100 | P13: 165511500 | Q13: 148971900 | R13: 141510600 | S13: 134442000 | T13: 127719900 | U13: 127719900 | V13: 127719900 | W13: 127719900
H14: 3 year | I14: KL4032WA*TA | J14: 403256700 | K14: 304758300 | L14: 254585100 | M14: 247193100 | N14: 241626000 | O14: 239778000 | P14: 237930000 | Q14: 214137000 | R14: 203441700 | S14: 193254600 | T14: 183598800 | U14: 183598800 | V14: 183598800 | W14: 183598800
G15: Renewal Premium Plus | H15: 1 year | I15: KL4032WA*F6 | J15: 132963600 | K15: 100485000 | L15: 83945400 | M15: 81496800 | N15: 79671900 | O15: 79071300 | P15: 78447600 | Q15: 70616700 | R15: 67082400 | S15: 63709800 | T15: 60545100 | U15: 60545100 | V15: 60545100 | W15: 60545100
H16: 2 year | I16: KL4032WA*D6 | J16: 252621600 | K16: 190921500 | L16: 159482400 | M16: 154839300 | N16: 151374300 | O16: 150219300 | P16: 149064300 | Q16: 134141700 | R16: 127442700 | S16: 121067100 | T16: 115014900 | U16: 115014900 | V16: 115014900 | W16: 115014900
H17: 3 year | I17: KL4032WA*T6 | J17: 372279600 | K17: 281334900 | L17: 235019400 | M17: 228204900 | N17: 223076700 | O17: 221367300 | P17: 219657900 | Q17: 197689800 | R17: 187803000 | S17: 178424400 | T17: 169507800 | U17: 169507800 | V17: 169507800 | W17: 169507800
G18: Renewal Premium | H18: 1 year | I18: KL4032WA*FL | J18: 122730300 | K18: 92746500 | L18: 77477400 | M18: 75236700 | N18: 73550400 | O18: 72972900 | P18: 72418500 | Q18: 65165100 | R18: 61908000 | S18: 58812600 | T18: 55878900 | U18: 55878900 | V18: 55878900 | W18: 55878900
H19: 2 year | I19: KL4032WA*DL | J19: 233194500 | K19: 176229900 | L19: 147216300 | M19: 142942800 | N19: 139731900 | O19: 138669300 | P19: 137583600 | Q19: 123839100 | R19: 117648300 | S19: 111757800 | T19: 106167600 | U19: 106167600 | V19: 106167600 | W19: 106167600
H20: 3 year | I20: KL4032WA*TL | J20: 343635600 | K20: 259713300 | L20: 216955200 | M20: 210648900 | N20: 205913400 | O20: 204342600 | P20: 202771800 | Q20: 182490000 | R20: 173365500 | S20: 164703000 | T20: 156456300 | U20: 156456300 | V20: 156456300 | W20: 156456300
G21: Base Premium Plus | H21: 1 year | I21: KL4032WA*F5 | J21: 189951300 | K21: 143543400 | L21: 119912100 | M21: 116424000 | N21: 113813700 | O21: 112935900 | P21: 112081200 | Q21: 100854600 | R21: 95818800 | S21: 91037100 | T21: 86486400 | U21: 86486400 | V21: 86486400 | W21: 86486400
H22: 2 year | I22: KL4032WA*D5 | J22: 303903600 | K22: 229660200 | L22: 191845500 | M22: 186278400 | N22: 182097300 | O22: 180711300 | P22: 179325300 | Q22: 161376600 | R22: 153314700 | S22: 145645500 | T22: 138369000 | U22: 138369000 | V22: 138369000 | W22: 138369000
H23: 3 year | I23: KL4032WA*T5 | J23: 436867200 | K23: 330145200 | L23: 275790900 | M23: 267775200 | N23: 261769200 | O23: 259759500 | P23: 257772900 | Q23: 231993300 | R23: 220397100 | S23: 209378400 | T23: 198891000 | U23: 198891000 | V23: 198891000 | W23: 198891000
B24: 4034 | C24: Kaspersky Unified Monitoring and Analysis Platform with Netflow support | D24: * 100 events per second | E24: License | G24: Base Premium | H24: 1 year | I24: KL4034WA*FA | J24: 201639900 | K24: 152367600 | L24: 127281000 | M24: 123585000 | N24: 120813000 | O24: 119889000 | P24: 118941900 | Q24: 107045400 | R24: 101709300 | S24: 96604200 | T24: 91776300 | U24: 91776300 | V24: 91776300 | W24: 91776300
H25: 2 year | I25: KL4034WA*DA | J25: 322614600 | K25: 243797400 | L25: 203672700 | M25: 197712900 | N25: 193277700 | O25: 191822400 | P25: 190320900 | Q25: 171286500 | R25: 162716400 | S25: 154585200 | T25: 146846700 | U25: 146846700 | V25: 146846700 | W25: 146846700
H26: 3 year | I26: KL4034WA*TA | J26: 463755600 | K26: 350473200 | L26: 292769400 | M26: 284222400 | N26: 277846800 | O26: 275744700 | P26: 273573300 | Q26: 246222900 | R26: 233910600 | S26: 222222000 | T26: 211110900 | U26: 211110900 | V26: 211110900 | W26: 211110900
G27: Renewal Premium Plus | H27: 1 year | I27: KL4034WA*F6 | J27: 152898900 | K27: 115546200 | L27: 96534900 | M27: 93716700 | N27: 91614600 | O27: 90921600 | P27: 90205500 | Q27: 81173400 | R27: 77130900 | S27: 73273200 | T27: 69600300 | U27: 69600300 | V27: 69600300 | W27: 69600300
H28: 2 year | I28: KL4034WA*D6 | J28: 290528700 | K28: 219542400 | L28: 183414000 | M28: 178054800 | N28: 174058500 | O28: 172741800 | P28: 171378900 | Q28: 154238700 | R28: 146523300 | S28: 139200600 | T28: 132247500 | U28: 132247500 | V28: 132247500 | W28: 132247500
H29: 3 year | I29: KL4034WA*T6 | J29: 428135400 | K29: 323538600 | L29: 270270000 | M29: 262392900 | N29: 256502400 | O29: 254562000 | P29: 252552300 | Q29: 227304000 | R29: 215938800 | S29: 205151100 | T29: 194894700 | U29: 194894700 | V29: 194894700 | W29: 194894700
G30: Renewal Premium | H30: 1 year | I30: KL4034WA*FL | J30: 141141000 | K30: 106652700 | L30: 89096700 | M30: 86509500 | N30: 84569100 | O30: 83922300 | P30: 83252400 | Q30: 74936400 | R30: 71194200 | S30: 67636800 | T30: 64241100 | U30: 64241100 | V30: 64241100 | W30: 64241100
H31: 2 year | I31: KL4034WA*DL | J31: 268167900 | K31: 202656300 | L31: 169299900 | M31: 164356500 | N31: 160660500 | O31: 159459300 | P31: 158188800 | Q31: 142388400 | R31: 135250500 | S31: 128505300 | T31: 122083500 | U31: 122083500 | V31: 122083500 | W31: 122083500
H32: 3 year | I32: KL4034WA*TL | J32: 395194800 | K32: 298659900 | L32: 249480000 | M32: 242203500 | N32: 236775000 | O32: 234973200 | P32: 233125200 | Q32: 209817300 | R32: 199329900 | S32: 189373800 | T32: 179902800 | U32: 179902800 | V32: 179902800 | W32: 179902800
G33: Base Premium Plus | H33: 1 year | I33: KL4034WA*F5 | J33: 218433600 | K33: 165072600 | L33: 137907000 | M33: 133864500 | N33: 130861500 | O33: 129868200 | P33: 128851800 | Q33: 115962000 | R33: 110163900 | S33: 104666100 | T33: 99422400 | U33: 99422400 | V33: 99422400 | W33: 99422400
H34: 2 year | I34: KL4034WA*D5 | J34: 349503000 | K34: 264125400 | L34: 220628100 | M34: 214206300 | N34: 209401500 | O34: 207807600 | P34: 206167500 | Q34: 185562300 | R34: 176276100 | S34: 167475000 | T34: 159089700 | U34: 159089700 | V34: 159089700 | W34: 159089700
H35: 3 year | I35: KL4034WA*T5 | J35: 502401900 | K35: 379671600 | L35: 317163000 | M35: 307899900 | N35: 300993000 | O35: 298729200 | P35: 296373000 | Q35: 266735700 | R35: 253407000 | S35: 240725100 | T35: 228690000 | U35: 228690000 | V35: 228690000 | W35: 228690000
B36: 4047 | C36: Kaspersky Unified Monitoring and Analysis Platform with Netflow support and TI | D36: * 100 events per second | E36: License | G36: Base Premium | H36: 1 year | I36: KL4047WA*FA | J36: 302425200 | K36: 228551400 | L36: 190944600 | M36: 185400600 | N36: 181196400 | O36: 179810400 | P36: 178424400 | Q36: 160591200 | R36: 152552400 | S36: 144929400 | T36: 137676000 | U36: 137676000 | V36: 137676000 | W36: 137676000
H37: 2 year | I37: KL4047WA*DA | J37: 483875700 | K37: 365673000 | L37: 305497500 | M37: 296627100 | N37: 289928100 | O37: 287710500 | P37: 285492900 | Q37: 256941300 | R37: 244097700 | S37: 231900900 | T37: 220304700 | U37: 220304700 | V37: 220304700 | W37: 220304700
H38: 3 year | I38: KL4047WA*TA | J38: 695587200 | K38: 525663600 | L38: 439154100 | M38: 426402900 | N38: 416770200 | O38: 413582400 | P38: 410394600 | Q38: 369369000 | R38: 350889000 | S38: 333356100 | T38: 316677900 | U38: 316677900 | V38: 316677900 | W38: 316677900
G39: Renewal Premium Plus | H39: 1 year | I39: KL4047WA*F6 | J39: 229336800 | K39: 173319300 | L39: 144790800 | M39: 140586600 | N39: 137421900 | O39: 136359300 | P39: 135319800 | Q39: 121783200 | R39: 115684800 | S39: 109909800 | T39: 104412000 | U39: 104412000 | V39: 104412000 | W39: 104412000
H40: 2 year | I40: KL4047WA*D6 | J40: 435735300 | K40: 329313600 | L40: 275097900 | M40: 267128400 | N40: 261076200 | O40: 259089600 | P40: 257103000 | Q40: 231392700 | R40: 219819600 | S40: 208824000 | T40: 198382800 | U40: 198382800 | V40: 198382800 | W40: 198382800
H41: 3 year | I41: KL4047WA*T6 | J41: 642156900 | K41: 485284800 | L41: 405428100 | M41: 393647100 | N41: 384753600 | O41: 381819900 | P41: 378863100 | Q41: 340979100 | R41: 323931300 | S41: 307738200 | T41: 292353600 | U41: 292353600 | V41: 292353600 | W41: 292353600
G42: Renewal Premium | H42: 1 year | I42: KL4047WA*FL | J42: 211688400 | K42: 159990600 | L42: 133656600 | M42: 129775800 | N42: 126842100 | O42: 125871900 | P42: 124901700 | Q42: 112404600 | R42: 106791300 | S42: 101455200 | T42: 96373200 | U42: 96373200 | V42: 96373200 | W42: 96373200
H43: 2 year | I43: KL4047WA*DL | J43: 402217200 | K43: 303972900 | L43: 253938300 | M43: 246569400 | N43: 241002300 | O43: 239154300 | P43: 237306300 | Q43: 213582600 | R43: 202910400 | S43: 192769500 | T43: 183113700 | U43: 183113700 | V43: 183113700 | W43: 183113700
H44: 3 year | I44: KL4047WA*TL | J44: 592746000 | K44: 447955200 | L44: 374243100 | M44: 363363000 | N44: 355162500 | O44: 352436700 | P44: 349734000 | Q44: 314760600 | R44: 299029500 | S44: 284060700 | T44: 269854200 | U44: 269854200 | V44: 269854200 | W44: 269854200
G45: Base Premium Plus | H45: 1 year | I45: KL4047WA*F5 | J45: 327627300 | K45: 247585800 | L45: 206837400 | M45: 200831400 | N45: 196303800 | O45: 194802300 | P45: 193300800 | Q45: 173966100 | R45: 165280500 | S45: 157010700 | T45: 149156700 | U45: 149156700 | V45: 149156700 | W45: 149156700
H46: 2 year | I46: KL4047WA*D5 | J46: 524208300 | K46: 396165000 | L46: 330953700 | M46: 321344100 | N46: 314090700 | O46: 311688300 | P46: 309285900 | Q46: 278355000 | R46: 264448800 | S46: 251212500 | T46: 238646100 | U46: 238646100 | V46: 238646100 | W46: 238646100
H47: 3 year | I47: KL4047WA*T5 | J47: 753545100 | K47: 569484300 | L47: 475744500 | M47: 461930700 | N47: 451512600 | O47: 448047600 | P47: 444605700 | Q47: 400138200 | R47: 380133600 | S47: 361122300 | T47: 343058100 | U47: 343058100 | V47: 343058100 | W47: 343058100
B48: 4048 | C48: Kaspersky Unified Monitoring and Analysis Platform with TI | D48: * 100 events per second | E48: License | G48: Base Premium | H48: 1 year | I48: KL4048WA*FA | J48: 262970400 | K48: 198752400 | L48: 166042800 | M48: 161191800 | N48: 157588200 | O48: 156363900 | P48: 155139600 | Q48: 139639500 | R48: 132663300 | S48: 126010500 | T48: 119727300 | U48: 119727300 | V48: 119727300 | W48: 119727300
H49: 2 year | I49: KL4048WA*DA | J49: 420766500 | K49: 317994600 | L49: 265673100 | M49: 257911500 | N49: 252136500 | O49: 250196100 | P49: 248232600 | Q49: 223423200 | R49: 212242800 | S49: 201639900 | T49: 191545200 | U49: 191545200 | V49: 191545200 | W49: 191545200
H50: 3 year | I50: KL4048WA*TA | J50: 604850400 | K50: 457125900 | L50: 381889200 | M50: 370731900 | N50: 362462100 | O50: 359643900 | P50: 356848800 | Q50: 321159300 | R50: 305104800 | S50: 289835700 | T50: 275352000 | U50: 275352000 | V50: 275352000 | W50: 275352000
G51: Renewal Premium Plus | H51: 1 year | I51: KL4048WA*F6 | J51: 199422300 | K51: 150727500 | L51: 125918100 | M51: 122245200 | N51: 119496300 | O51: 118572300 | P51: 117648300 | Q51: 105890400 | R51: 100600500 | S51: 95564700 | T51: 90783000 | U51: 90783000 | V51: 90783000 | W51: 90783000
H52: 2 year | I52: KL4048WA*D6 | J52: 378909300 | K52: 286370700 | L52: 239246700 | M52: 232247400 | N52: 227049900 | O52: 225294300 | P52: 223538700 | Q52: 201177900 | R52: 191129400 | S52: 181566000 | T52: 172487700 | U52: 172487700 | V52: 172487700 | W52: 172487700
H53: 3 year | I53: KL4048WA*T6 | J53: 558396300 | K53: 422013900 | L53: 352575300 | M53: 342272700 | N53: 334603500 | O53: 332016300 | P53: 329429100 | Q53: 296488500 | R53: 281658300 | S53: 267590400 | T53: 254192400 | U53: 254192400 | V53: 254192400 | W53: 254192400
G54: Renewal Premium | H54: 1 year | I54: KL4048WA*FL | J54: 184083900 | K54: 139131300 | L54: 116239200 | M54: 112843500 | N54: 110302500 | O54: 109447800 | P54: 108593100 | Q54: 97736100 | R54: 92862000 | S54: 88218900 | T54: 83806800 | U54: 83806800 | V54: 83806800 | W54: 83806800
H55: 2 year | I55: KL4048WA*DL | J55: 349757100 | K55: 264333300 | L55: 220836000 | M55: 214391100 | N55: 209586300 | O55: 207969300 | P55: 206352300 | Q55: 185724000 | R55: 176437800 | S55: 167613600 | T55: 159228300 | U55: 159228300 | V55: 159228300 | W55: 159228300
H56: 3 year | I56: KL4048WA*TL | J56: 515430300 | K56: 389558400 | L56: 325432800 | M56: 315938700 | N56: 308870100 | O56: 306490800 | P56: 304088400 | Q56: 273688800 | R56: 259990500 | S56: 247008300 | T56: 234649800 | U56: 234649800 | V56: 234649800 | W56: 234649800
G57: Base Premium Plus | H57: 1 year | I57: KL4048WA*F5 | J57: 284892300 | K57: 215315100 | L57: 179879700 | M57: 174636000 | N57: 170732100 | O57: 169392300 | P57: 168075600 | Q57: 151258800 | R57: 143705100 | S57: 136521000 | T57: 129706500 | U57: 129706500 | V57: 129706500 | W57: 129706500
H58: 2 year | I58: KL4048WA*D5 | J58: 455832300 | K58: 344513400 | L58: 287802900 | M58: 279394500 | N58: 273157500 | O58: 271032300 | P58: 268930200 | Q58: 242041800 | R58: 229937400 | S58: 218433600 | T58: 207507300 | U58: 207507300 | V58: 207507300 | W58: 207507300
H59: 3 year | I59: KL4048WA*T5 | J59: 655254600 | K59: 495217800 | L59: 413721000 | M59: 401639700 | N59: 392653800 | O59: 389627700 | P59: 386578500 | Q59: 347932200 | R59: 330514800 | S59: 313998300 | T59: 298290300 | U59: 298290300 | V59: 298290300 | W59: 298290300

Sheet ScanEngine
C7: =CONCATENATE("Price List applicable for ",Data!A9,". Effective from ",Data!A11,". ") -> Price List applicable for Vietnam. Effective from July 1, 2026. | K7: * For additional details please see
C8: =CONCATENATE(Data!A5,". ",Data!A7) -> Kaspersky Lab. 39A/3 Leningradskoe Shosse Moscow, 125212. 0 | K8: specifications in Comment section
B9: Max of Price | J9: Band
B10: Code | C10: Product | D10: LicenceDescription | E10: Package | F10: LicenceObject | G10: Type | H10: Term | I10: SKU | J10: Band 1: 250+ | K10: Band Y: 1-10000
B11: 4000 | C11: Threat Intelligence | D11: - | E11: - | F11: - | G11: - | H11: - | I11: -
B12: 4001 | C12: Kaspersky Scan Engine | D12: Node | E12: Technology Licence | G12: Base | H12: 1 year | I12: KL6910WH*FS | J12: 304920
H13: 2 year | I13: KL6910WH*DS | J13: 457380
H14: 3 year | I14: KL6910WH*TS | J14: 593670
B15: 4002 | C15: Kaspersky Scan Engine, Server | D15: Svr | E15: Technology Licence | G15: Base | H15: 1 year | I15: KL6916WH*FS | K15: 293393100
H16: 2 year | I16: KL6916WH*DS | K16: 440055000
H17: 3 year | I17: KL6916WH*TS | K17: 572071500

Sheet SD-WAN
C7: =CONCATENATE("Price List applicable for ",Data!A9,". Effective from ",Data!A11,". ") -> Price List applicable for Vietnam. Effective from July 1, 2026. | AB7: * For additional details please see
C8: =CONCATENATE(Data!A5,". ",Data!A7) -> Kaspersky Lab. 39A/3 Leningradskoe Shosse Moscow, 125212. 0 | AB8: specifications in Comment section
B9: Max of Price | J9: Band
B10: Code | C10: Product | D10: LicenceDescription | E10: Package | F10: LicenceObject | G10: Type | H10: Term | I10: SKU | J10: Band A: 1 | K10: Band A: 1-1 | L10: Band B: 2-2 | M10: Band C: 3-3 | N10: Band D: 4-4 | O10: Band E: 5-9 | P10: Band K: 10-14 | Q10: Band M: 15-19 | R10: Band N: 20-24 | S10: Band P: 25-49 | T10: Band Q: 50-99 | U10: Band R: 100-149 | V10: Band S: 150-249 | W10: Band T: 250-499 | X10: Band U: 500-999 | Y10: Band V: 1000-1499 | Z10: Band W: 1500-2499 | AA10: Band X: 2500-4999 | AB10: Band Y: 5000+
B11: 4000 | C11: Kaspersky Anti Targeted Attack Platform* | D11: - | E11: - | F11: - | G11: - | H11: - | I11: -
B12: 4001 | C12: Kaspersky SD-WAN Advanced CPE 1 Gbps | D12: Dvc | E12: License | G12: Base Premium Plus | H12: 1 year | I12: KL4245WA*F5 | K12: 591544800 | L12: 591544800 | M12: 591544800 | N12: 591544800 | O12: 591544800 | P12: 591544800 | Q12: 591544800 | R12: 591544800 | S12: 591544800 | T12: 591544800 | U12: 502817700 | V12: 502817700 | W12: 473226600 | X12: 473226600 | Y12: 410140500 | Z12: 410140500 | AA12: 410140500 | AB12: 410140500
H13: 2 year | I13: KL4245WA*D5 | K13: 1025339700 | L13: 1025339700 | M13: 1025339700 | N13: 1025339700 | O13: 1025339700 | P13: 1025339700 | Q13: 1025339700 | R13: 1025339700 | S13: 1025339700 | T13: 1025339700 | U13: 871539900 | V13: 871539900 | W13: 820257900 | X13: 820257900 | Y13: 757171800 | Z13: 757171800 | AA13: 757171800 | AB13: 757171800
H14: 3 year | I14: KL4245WA*T5 | K14: 1538021100 | L14: 1538021100 | M14: 1538021100 | N14: 1538021100 | O14: 1538021100 | P14: 1538021100 | Q14: 1538021100 | R14: 1538021100 | S14: 1538021100 | T14: 1538021100 | U14: 1307298300 | V14: 1307298300 | W14: 1230398400 | X14: 1230398400 | Y14: 1167312300 | Z14: 1167312300 | AA14: 1167312300 | AB14: 1167312300
G15: Renewal Premium Plus | H15: 1 year | I15: KL4245WA*F6 | K15: 512681400 | L15: 512681400 | M15: 512681400 | N15: 512681400 | O15: 512681400 | P15: 512681400 | Q15: 512681400 | R15: 512681400 | S15: 512681400 | T15: 512681400 | U15: 435758400 | V15: 435758400 | W15: 410140500 | X15: 410140500 | Y15: 347054400 | Z15: 347054400 | AA15: 347054400 | AB15: 347054400
H16: 2 year | I16: KL4245WA*D6 | K16: 899144400 | L16: 899144400 | M16: 899144400 | N16: 899144400 | O16: 899144400 | P16: 899144400 | Q16: 899144400 | R16: 899144400 | S16: 899144400 | T16: 899144400 | U16: 764286600 | V16: 764286600 | W16: 719310900 | X16: 719310900 | Y16: 656224800 | Z16: 656224800 | AA16: 656224800 | AB16: 656224800
H17: 3 year | I17: KL4245WA*T6 | K17: 1348716600 | L17: 1348716600 | M17: 1348716600 | N17: 1348716600 | O17: 1348716600 | P17: 1348716600 | Q17: 1348716600 | R17: 1348716600 | S17: 1348716600 | T17: 1348716600 | U17: 1146406800 | V17: 1146406800 | W17: 1078954800 | X17: 1078954800 | Y17: 1015868700 | Z17: 1015868700 | AA17: 1015868700 | AB17: 1015868700
G18: Base Premium | H18: 1 year | I18: KL4245WA*FA | K18: 512681400 | L18: 512681400 | M18: 512681400 | N18: 512681400 | O18: 512681400 | P18: 512681400 | Q18: 512681400 | R18: 512681400 | S18: 512681400 | T18: 512681400 | U18: 435758400 | V18: 435758400 | W18: 410140500 | X18: 410140500 | Y18: 378585900 | Z18: 378585900 | AA18: 378585900 | AB18: 378585900
H19: 2 year | I19: KL4245WA*DA | K19: 867589800 | L19: 867589800 | M19: 867589800 | N19: 867589800 | O19: 867589800 | P19: 867589800 | Q19: 867589800 | R19: 867589800 | S19: 867589800 | T19: 867589800 | U19: 737444400 | V19: 737444400 | W19: 694085700 | X19: 694085700 | Y19: 662508000 | Z19: 662508000 | AA19: 662508000 | AB19: 662508000
H20: 3 year | I20: KL4245WA*TA | K20: 1301407800 | L20: 1301407800 | M20: 1301407800 | N20: 1301407800 | O20: 1301407800 | P20: 1301407800 | Q20: 1301407800 | R20: 1301407800 | S20: 1301407800 | T20: 1301407800 | U20: 1106166600 | V20: 1106166600 | W20: 1041117000 | X20: 1041117000 | Y20: 1009562400 | Z20: 1009562400 | AA20: 1009562400 | AB20: 1009562400
G21: Renewal Premium | H21: 1 year | I21: KL4245WA*FL | K21: 433794900 | L21: 433794900 | M21: 433794900 | N21: 433794900 | O21: 433794900 | P21: 433794900 | Q21: 433794900 | R21: 433794900 | S21: 433794900 | T21: 433794900 | U21: 368722200 | V21: 368722200 | W21: 347054400 | X21: 347054400 | Y21: 315499800 | Z21: 315499800 | AA21: 315499800 | AB21: 315499800
H22: 2 year | I22: KL4245WA*DL | K22: 741394500 | L22: 741394500 | M22: 741394500 | N22: 741394500 | O22: 741394500 | P22: 741394500 | Q22: 741394500 | R22: 741394500 | S22: 741394500 | T22: 741394500 | U22: 630191100 | V22: 630191100 | W22: 593115600 | X22: 593115600 | Y22: 561561000 | Z22: 561561000 | AA22: 561561000 | AB22: 561561000
H23: 3 year | I23: KL4245WA*TL | K23: 1112103300 | L23: 1112103300 | M23: 1112103300 | N23: 1112103300 | O23: 1112103300 | P23: 1112103300 | Q23: 1112103300 | R23: 1112103300 | S23: 1112103300 | T23: 1112103300 | U23: 945275100 | V23: 945275100 | W23: 889673400 | X23: 889673400 | Y23: 858118800 | Z23: 858118800 | AA23: 858118800 | AB23: 858118800
B24: 4002 | C24: Kaspersky SD-WAN Advanced CPE 10 Gbps | D24: Dvc | E24: License | G24: Base Premium Plus | H24: 1 year | I24: KL4246WA*F5 | K24: 2253081600 | L24: 2253081600 | M24: 2253081600 | N24: 2253081600 | O24: 2253081600 | P24: 2253081600 | Q24: 2253081600 | R24: 2253081600 | S24: 2253081600 | T24: 2253081600 | U24: 1915128600 | V24: 1915128600 | W24: 1802469900 | X24: 1802469900 | Y24: 1562137500 | Z24: 1562137500 | AA24: 1562137500 | AB24: 1562137500
H25: 2 year | I25: KL4246WA*D5 | K25: 3905355300 | L25: 3905355300 | M25: 3905355300 | N25: 3905355300 | O25: 3905355300 | P25: 3905355300 | Q25: 3905355300 | R25: 3905355300 | S25: 3905355300 | T25: 3905355300 | U25: 3319562400 | V25: 3319562400 | W25: 3124298100 | X25: 3124298100 | Y25: 2883965700 | Z25: 2883965700 | AA25: 2883965700 | AB25: 2883965700
H26: 3 year | I26: KL4246WA*T5 | K26: 5858021400 | L26: 5858021400 | M26: 5858021400 | N26: 5858021400 | O26: 5858021400 | P26: 5858021400 | Q26: 5858021400 | R26: 5858021400 | S26: 5858021400 | T26: 5858021400 | U26: 4979320500 | V26: 4979320500 | W26: 4686412500 | X26: 4686412500 | Y26: 4446080100 | Z26: 4446080100 | AA26: 4446080100 | AB26: 4446080100
G27: Renewal Premium Plus | H27: 1 year | I27: KL4246WA*F6 | K27: 1952689200 | L27: 1952689200 | M27: 1952689200 | N27: 1952689200 | O27: 1952689200 | P27: 1952689200 | Q27: 1952689200 | R27: 1952689200 | S27: 1952689200 | T27: 1952689200 | U27: 1659781200 | V27: 1659781200 | W27: 1562137500 | X27: 1562137500 | Y27: 1321805100 | Z27: 1321805100 | AA27: 1321805100 | AB27: 1321805100
H28: 2 year | I28: KL4246WA*D6 | K28: 3424690500 | L28: 3424690500 | M28: 3424690500 | N28: 3424690500 | O28: 3424690500 | P28: 3424690500 | Q28: 3424690500 | R28: 3424690500 | S28: 3424690500 | T28: 3424690500 | U28: 2910992700 | V28: 2910992700 | W28: 2739752400 | X28: 2739752400 | Y28: 2499420000 | Z28: 2499420000 | AA28: 2499420000 | AB28: 2499420000
H29: 3 year | I29: KL4246WA*T6 | K29: 5137047300 | L29: 5137047300 | M29: 5137047300 | N29: 5137047300 | O29: 5137047300 | P29: 5137047300 | Q29: 5137047300 | R29: 5137047300 | S29: 5137047300 | T29: 5137047300 | U29: 4366477500 | V29: 4366477500 | W29: 4109628600 | X29: 4109628600 | Y29: 3869319300 | Z29: 3869319300 | AA29: 3869319300 | AB29: 3869319300
G30: Base Premium | H30: 1 year | I30: KL4246WA*FA | K30: 1952689200 | L30: 1952689200 | M30: 1952689200 | N30: 1952689200 | O30: 1952689200 | P30: 1952689200 | Q30: 1952689200 | R30: 1952689200 | S30: 1952689200 | T30: 1952689200 | U30: 1659781200 | V30: 1659781200 | W30: 1562137500 | X30: 1562137500 | Y30: 1441971300 | Z30: 1441971300 | AA30: 1441971300 | AB30: 1441971300
H31: 2 year | I31: KL4246WA*DA | K31: 3304524300 | L31: 3304524300 | M31: 3304524300 | N31: 3304524300 | O31: 3304524300 | P31: 3304524300 | Q31: 3304524300 | R31: 3304524300 | S31: 3304524300 | T31: 3304524300 | U31: 2808844500 | V31: 2808844500 | W31: 2643633300 | X31: 2643633300 | Y31: 2523467100 | Z31: 2523467100 | AA31: 2523467100 | AB31: 2523467100
H32: 3 year | I32: KL4246WA*TA | K32: 4956798000 | L32: 4956798000 | M32: 4956798000 | N32: 4956798000 | O32: 4956798000 | P32: 4956798000 | Q32: 4956798000 | R32: 4956798000 | S32: 4956798000 | T32: 4956798000 | U32: 4213278300 | V32: 4213278300 | W32: 3965438400 | X32: 3965438400 | Y32: 3845272200 | Z32: 3845272200 | AA32: 3845272200 | AB32: 3845272200
G33: Renewal Premium | H33: 1 year | I33: KL4246WA*FL | K33: 1652250600 | L33: 1652250600 | M33: 1652250600 | N33: 1652250600 | O33: 1652250600 | P33: 1652250600 | Q33: 1652250600 | R33: 1652250600 | S33: 1652250600 | T33: 1652250600 | U33: 1404433800 | V33: 1404433800 | W33: 1321805100 | X33: 1321805100 | Y33: 1201638900 | Z33: 1201638900 | AA33: 1201638900 | AB33: 1201638900
H34: 2 year | I34: KL4246WA*DL | K34: 2823859500 | L34: 2823859500 | M34: 2823859500 | N34: 2823859500 | O34: 2823859500 | P34: 2823859500 | Q34: 2823859500 | R34: 2823859500 | S34: 2823859500 | T34: 2823859500 | U34: 2400274800 | V34: 2400274800 | W34: 2259110700 | X34: 2259110700 | Y34: 2138944500 | Z34: 2138944500 | AA34: 2138944500 | AB34: 2138944500
H35: 3 year | I35: KL4246WA*TL | K35: 4235800800 | L35: 4235800800 | M35: 4235800800 | N35: 4235800800 | O35: 4235800800 | P35: 4235800800 | Q35: 4235800800 | R35: 4235800800 | S35: 4235800800 | T35: 4235800800 | U35: 3600435300 | V35: 3600435300 | W35: 3388654500 | X35: 3388654500 | Y35: 3268488300 | Z35: 3268488300 | AA35: 3268488300 | AB35: 3268488300
B36: 4003 | C36: Kaspersky SD-WAN Advanced CPE 100 Mbps | D36: Dvc | E36: License | G36: Base Premium Plus | H36: 1 year | I36: KL4242WA*F5 | K36: 134626800 | L36: 134626800 | M36: 134626800 | N36: 134626800 | O36: 134626800 | P36: 134626800 | Q36: 134626800 | R36: 134626800 | S36: 134626800 | T36: 134626800 | U36: 114414300 | V36: 114414300 | W36: 107715300 | X36: 107715300 | Y36: 93324000 | Z36: 93324000 | AA36: 93324000 | AB36: 93324000
H37: 2 year | I37: KL4242WA*D5 | K37: 233333100 | L37: 233333100 | M37: 233333100 | N37: 233333100 | O37: 233333100 | P37: 233333100 | Q37: 233333100 | R37: 233333100 | S37: 233333100 | T37: 233333100 | U37: 198359700 | V37: 198359700 | W37: 186694200 | X37: 186694200 | Y37: 172326000 | Z37: 172326000 | AA37: 172326000 | AB37: 172326000
H38: 3 year | I38: KL4242WA*T5 | K38: 350034300 | L38: 350034300 | M38: 350034300 | N38: 350034300 | O38: 350034300 | P38: 350034300 | Q38: 350034300 | R38: 350034300 | S38: 350034300 | T38: 350034300 | U38: 297528000 | V38: 297528000 | W38: 280018200 | X38: 280018200 | Y38: 265673100 | Z38: 265673100 | AA38: 265673100 | AB38: 265673100
G39: Renewal Premium Plus | H39: 1 year | I39: KL4242WA*F6 | K39: 116678100 | L39: 116678100 | M39: 116678100 | N39: 116678100 | O39: 116678100 | P39: 116678100 | Q39: 116678100 | R39: 116678100 | S39: 116678100 | T39: 116678100 | U39: 99168300 | V39: 99168300 | W39: 93324000 | X39: 93324000 | Y39: 78978900 | Z39: 78978900 | AA39: 78978900 | AB39: 78978900
H40: 2 year | I40: KL4242WA*D6 | K40: 204619800 | L40: 204619800 | M40: 204619800 | N40: 204619800 | O40: 204619800 | P40: 204619800 | Q40: 204619800 | R40: 204619800 | S40: 204619800 | T40: 204619800 | U40: 173943000 | V40: 173943000 | W40: 163709700 | X40: 163709700 | Y40: 149341500 | Z40: 149341500 | AA40: 149341500 | AB40: 149341500
H41: 3 year | I41: KL4242WA*T6 | K41: 306952800 | L41: 306952800 | M41: 306952800 | N41: 306952800 | O41: 306952800 | P41: 306952800 | Q41: 306952800 | R41: 306952800 | S41: 306952800 | T41: 306952800 | U41: 260914500 | V41: 260914500 | W41: 245553000 | X41: 245553000 | Y41: 231207900 | Z41: 231207900 | AA41: 231207900 | AB41: 231207900
G42: Base Premium | H42: 1 year | I42: KL4242WA*FA | K42: 116678100 | L42: 116678100 | M42: 116678100 | N42: 116678100 | O42: 116678100 | P42: 116678100 | Q42: 116678100 | R42: 116678100 | S42: 116678100 | T42: 116678100 | U42: 99168300 | V42: 99168300 | W42: 93324000 | X42: 93324000 | Y42: 86163000 | Z42: 86163000 | AA42: 86163000 | AB42: 86163000
H43: 2 year | I43: KL4242WA*DA | K43: 197458800 | L43: 197458800 | M43: 197458800 | N43: 197458800 | O43: 197458800 | P43: 197458800 | Q43: 197458800 | R43: 197458800 | S43: 197458800 | T43: 197458800 | U43: 167844600 | V43: 167844600 | W43: 157957800 | X43: 157957800 | Y43: 150773700 | Z43: 150773700 | AA43: 150773700 | AB43: 150773700
H44: 3 year | I44: KL4242WA*TA | K44: 296188200 | L44: 296188200 | M44: 296188200 | N44: 296188200 | O44: 296188200 | P44: 296188200 | Q44: 296188200 | R44: 296188200 | S44: 296188200 | T44: 296188200 | U44: 251766900 | V44: 251766900 | W44: 236959800 | X44: 236959800 | Y44: 229752600 | Z44: 229752600 | AA44: 229752600 | AB44: 229752600
G45: Renewal Premium | H45: 1 year | I45: KL4242WA*FL | K45: 98729400 | L45: 98729400 | M45: 98729400 | N45: 98729400 | O45: 98729400 | P45: 98729400 | Q45: 98729400 | R45: 98729400 | S45: 98729400 | T45: 98729400 | U45: 83922300 | V45: 83922300 | W45: 78978900 | X45: 78978900 | Y45: 71817900 | Z45: 71817900 | AA45: 71817900 | AB45: 71817900
H46: 2 year | I46: KL4242WA*DL | K46: 168722400 | L46: 168722400 | M46: 168722400 | N46: 168722400 | O46: 168722400 | P46: 168722400 | Q46: 168722400 | R46: 168722400 | S46: 168722400 | T46: 168722400 | U46: 143404800 | V46: 143404800 | W46: 134973300 | X46: 134973300 | Y46: 127812300 | Z46: 127812300 | AA46: 127812300 | AB46: 127812300
H47: 3 year | I47: KL4242WA*TL | K47: 253106700 | L47: 253106700 | M47: 253106700 | N47: 253106700 | O47: 253106700 | P47: 253106700 | Q47: 253106700 | R47: 253106700 | S47: 253106700 | T47: 253106700 | U47: 215130300 | V47: 215130300 | W47: 202471500 | X47: 202471500 | Y47: 195310500 | Z47: 195310500 | AA47: 195310500 | AB47: 195310500
B48: 4004 | C48: Kaspersky SD-WAN Advanced CPE 30 Mbps | D48: Dvc | E48: License | G48: Base Premium Plus | H48: 1 year | I48: KL4240WA*F5 | K48: 45206700 | L48: 45206700 | M48: 45206700 | N48: 45206700 | O48: 45206700 | P48: 45206700 | Q48: 45206700 | R48: 45206700 | S48: 45206700 | T48: 45206700 | U48: 38415300 | V48: 38415300 | W48: 36151500 | X48: 36151500 | Y48: 31323600 | Z48: 31323600 | AA48: 31323600 | AB48: 31323600
H49: 2 year | I49: KL4240WA*D5 | K49: 78332100 | L49: 78332100 | M49: 78332100 | N49: 78332100 | O49: 78332100 | P49: 78332100 | Q49: 78332100 | R49: 78332100 | S49: 78332100 | T49: 78332100 | U49: 66597300 | V49: 66597300 | W49: 62670300 | X49: 62670300 | Y49: 57865500 | Z49: 57865500 | AA49: 57865500 | AB49: 57865500
H50: 3 year | I50: KL4240WA*T5 | K50: 117532800 | L50: 117532800 | M50: 117532800 | N50: 117532800 | O50: 117532800 | P50: 117532800 | Q50: 117532800 | R50: 117532800 | S50: 117532800 | T50: 117532800 | U50: 99884400 | V50: 99884400 | W50: 94017000 | X50: 94017000 | Y50: 89189100 | Z50: 89189100 | AA50: 89189100 | AB50: 89189100
G51: Renewal Premium Plus | H51: 1 year | I51: KL4240WA*F6 | K51: 39177600 | L51: 39177600 | M51: 39177600 | N51: 39177600 | O51: 39177600 | P51: 39177600 | Q51: 39177600 | R51: 39177600 | S51: 39177600 | T51: 39177600 | U51: 33287100 | V51: 33287100 | W51: 31323600 | X51: 31323600 | Y51: 26518800 | Z51: 26518800 | AA51: 26518800 | AB51: 26518800
H52: 2 year | I52: KL4240WA*D6 | K52: 68699400 | L52: 68699400 | M52: 68699400 | N52: 68699400 | O52: 68699400 | P52: 68699400 | Q52: 68699400 | R52: 68699400 | S52: 68699400 | T52: 68699400 | U52: 58396800 | V52: 58396800 | W52: 54954900 | X52: 54954900 | Y52: 50127000 | Z52: 50127000 | AA52: 50127000 | AB52: 50127000
H53: 3 year | I53: KL4240WA*T6 | K53: 103049100 | L53: 103049100 | M53: 103049100 | N53: 103049100 | O53: 103049100 | P53: 103049100 | Q53: 103049100 | R53: 103049100 | S53: 103049100 | T53: 103049100 | U53: 87595200 | V53: 87595200 | W53: 82420800 | X53: 82420800 | Y53: 77639100 | Z53: 77639100 | AA53: 77639100 | AB53: 77639100
G54: Base Premium | H54: 1 year | I54: KL4240WA*FA | K54: 39177600 | L54: 39177600 | M54: 39177600 | N54: 39177600 | O54: 39177600 | P54: 39177600 | Q54: 39177600 | R54: 39177600 | S54: 39177600 | T54: 39177600 | U54: 33287100 | V54: 33287100 | W54: 31323600 | X54: 31323600 | Y54: 28921200 | Z54: 28921200 | AA54: 28921200 | AB54: 28921200
H55: 2 year | I55: KL4240WA*DA | K55: 66297000 | L55: 66297000 | M55: 66297000 | N55: 66297000 | O55: 66297000 | P55: 66297000 | Q55: 66297000 | R55: 66297000 | S55: 66297000 | T55: 66297000 | U55: 56340900 | V55: 56340900 | W55: 53037600 | X55: 53037600 | Y55: 50612100 | Z55: 50612100 | AA55: 50612100 | AB55: 50612100
H56: 3 year | I56: KL4240WA*TA | K56: 99422400 | L56: 99422400 | M56: 99422400 | N56: 99422400 | O56: 99422400 | P56: 99422400 | Q56: 99422400 | R56: 99422400 | S56: 99422400 | T56: 99422400 | U56: 84522900 | V56: 84522900 | W56: 79556400 | X56: 79556400 | Y56: 77154000 | Z56: 77154000 | AA56: 77154000 | AB56: 77154000
G57: Renewal Premium | H57: 1 year | I57: KL4240WA*FL | K57: 33125400 | L57: 33125400 | M57: 33125400 | N57: 33125400 | O57: 33125400 | P57: 33125400 | Q57: 33125400 | R57: 33125400 | S57: 33125400 | T57: 33125400 | U57: 28182000 | V57: 28182000 | W57: 26518800 | X57: 26518800 | Y57: 24116400 | Z57: 24116400 | AA57: 24116400 | AB57: 24116400
H58: 2 year | I58: KL4240WA*DL | K58: 56641200 | L58: 56641200 | M58: 56641200 | N58: 56641200 | O58: 56641200 | P58: 56641200 | Q58: 56641200 | R58: 56641200 | S58: 56641200 | T58: 56641200 | U58: 48163500 | V58: 48163500 | W58: 45299100 | X58: 45299100 | Y58: 42919800 | Z58: 42919800 | AA58: 42919800 | AB58: 42919800
H59: 3 year | I59: KL4240WA*TL | K59: 84961800 | L59: 84961800 | M59: 84961800 | N59: 84961800 | O59: 84961800 | P59: 84961800 | Q59: 84961800 | R59: 84961800 | S59: 84961800 | T59: 84961800 | U59: 72210600 | V59: 72210600 | W59: 67983300 | X59: 67983300 | Y59: 65557800 | Z59: 65557800 | AA59: 65557800 | AB59: 65557800
B60: 4005 | C60: Kaspersky SD-WAN Advanced CPE 300 Mbps | D60: Dvc | E60: License | G60: Base Premium Plus | H60: 1 year | I60: KL4243WA*F5 | K60: 241833900 | L60: 241833900 | M60: 241833900 | N60: 241833900 | O60: 241833900 | P60: 241833900 | Q60: 241833900 | R60: 241833900 | S60: 241833900 | T60: 241833900 | U60: 205566900 | V60: 205566900 | W60: 193462500 | X60: 193462500 | Y60: 167682900 | Z60: 167682900 | AA60: 167682900 | AB60: 167682900
H61: 2 year | I61: KL4243WA*D5 | K61: 419172600 | L61: 419172600 | M61: 419172600 | N61: 419172600 | O61: 419172600 | P61: 419172600 | Q61: 419172600 | R61: 419172600 | S61: 419172600 | T61: 419172600 | U61: 356294400 | V61: 356294400 | W61: 335342700 | X61: 335342700 | Y61: 309540000 | Z61: 309540000 | AA61: 309540000 | AB61: 309540000
H62: 3 year | I62: KL4243WA*T5 | K62: 628782000 | L62: 628782000 | M62: 628782000 | N62: 628782000 | O62: 628782000 | P62: 628782000 | Q62: 628782000 | R62: 628782000 | S62: 628782000 | T62: 628782000 | U62: 534441600 | V62: 534441600 | W62: 503025600 | X62: 503025600 | Y62: 477222900 | Z62: 477222900 | AA62: 477222900 | AB62: 477222900
G63: Renewal Premium Plus | H63: 1 year | I63: KL4243WA*F6 | K63: 209586300 | L63: 209586300 | M63: 209586300 | N63: 209586300 | O63: 209586300 | P63: 209586300 | Q63: 209586300 | R63: 209586300 | S63: 209586300 | T63: 209586300 | U63: 178147200 | V63: 178147200 | W63: 167682900 | X63: 167682900 | Y63: 141857100 | Z63: 141857100 | AA63: 141857100 | AB63: 141857100
H64: 2 year | I64: KL4243WA*D6 | K64: 367590300 | L64: 367590300 | M64: 367590300 | N64: 367590300 | O64: 367590300 | P64: 367590300 | Q64: 367590300 | R64: 367590300 | S64: 367590300 | T64: 367590300 | U64: 312450600 | V64: 312450600 | W64: 294063000 | X64: 294063000 | Y64: 268283400 | Z64: 268283400 | AA64: 268283400 | AB64: 268283400
H65: 3 year | I65: KL4243WA*T6 | K65: 551373900 | L65: 551373900 | M65: 551373900 | N65: 551373900 | O65: 551373900 | P65: 551373900 | Q65: 551373900 | R65: 551373900 | S65: 551373900 | T65: 551373900 | U65: 468652800 | V65: 468652800 | W65: 441094500 | X65: 441094500 | Y65: 415291800 | Z65: 415291800 | AA65: 415291800 | AB65: 415291800
G66: Base Premium | H66: 1 year | I66: KL4243WA*FA | K66: 209586300 | L66: 209586300 | M66: 209586300 | N66: 209586300 | O66: 209586300 | P66: 209586300 | Q66: 209586300 | R66: 209586300 | S66: 209586300 | T66: 209586300 | U66: 178147200 | V66: 178147200 | W66: 167682900 | X66: 167682900 | Y66: 154770000 | Z66: 154770000 | AA66: 154770000 | AB66: 154770000
H67: 2 year | I67: KL4243WA*DA | K67: 354700500 | L67: 354700500 | M67: 354700500 | N67: 354700500 | O67: 354700500 | P67: 354700500 | Q67: 354700500 | R67: 354700500 | S67: 354700500 | T67: 354700500 | U67: 301501200 | V67: 301501200 | W67: 283760400 | X67: 283760400 | Y67: 270847500 | Z67: 270847500 | AA67: 270847500 | AB67: 270847500
H68: 3 year | I68: KL4243WA*TA | K68: 532039200 | L68: 532039200 | M68: 532039200 | N68: 532039200 | O68: 532039200 | P68: 532039200 | Q68: 532039200 | R68: 532039200 | S68: 532039200 | T68: 532039200 | U68: 452228700 | V68: 452228700 | W68: 425617500 | X68: 425617500 | Y68: 412727700 | Z68: 412727700 | AA68: 412727700 | AB68: 412727700
G69: Renewal Premium | H69: 1 year | I69: KL4243WA*FL | K69: 177338700 | L69: 177338700 | M69: 177338700 | N69: 177338700 | O69: 177338700 | P69: 177338700 | Q69: 177338700 | R69: 177338700 | S69: 177338700 | T69: 177338700 | U69: 150727500 | V69: 150727500 | W69: 141857100 | X69: 141857100 | Y69: 128990400 | Z69: 128990400 | AA69: 128990400 | AB69: 128990400
H70: 2 year | I70: KL4243WA*DL | K70: 303095100 | L70: 303095100 | M70: 303095100 | N70: 303095100 | O70: 303095100 | P70: 303095100 | Q70: 303095100 | R70: 303095100 | S70: 303095100 | T70: 303095100 | U70: 257634300 | V70: 257634300 | W70: 242480700 | X70: 242480700 | Y70: 229590900 | Z70: 229590900 | AA70: 229590900 | AB70: 229590900
H71: 3 year | I71: KL4243WA*TL | K71: 454631100 | L71: 454631100 | M71: 454631100 | N71: 454631100 | O71: 454631100 | P71: 454631100 | Q71: 454631100 | R71: 454631100 | S71: 454631100 | T71: 454631100 | U71: 386439900 | V71: 386439900 | W71: 363709500 | X71: 363709500 | Y71: 350819700 | Z71: 350819700 | AA71: 350819700 | AB71: 350819700
B72: 4006 | C72: Kaspersky SD-WAN Advanced CPE 50 Mbps | D72: Dvc | E72: License | G72: Base Premium Plus | H72: 1 year | I72: KL4241WA*F5 | K72: 66712800 | L72: 66712800 | M72: 66712800 | N72: 66712800 | O72: 66712800 | P72: 66712800 | Q72: 66712800 | R72: 66712800 | S72: 66712800 | T72: 66712800 | U72: 56687400 | V72: 56687400 | W72: 53361000 | X72: 53361000 | Y72: 46246200 | Z72: 46246200 | AA72: 46246200 | AB72: 46246200
H73: 2 year | I73: KL4241WA*D5 | K73: 115615500 | L73: 115615500 | M73: 115615500 | N73: 115615500 | O73: 115615500 | P73: 115615500 | Q73: 115615500 | R73: 115615500 | S73: 115615500 | T73: 115615500 | U73: 98290500 | V73: 98290500 | W73: 92492400 | X73: 92492400 | Y73: 85377600 | Z73: 85377600 | AA73: 85377600 | AB73: 85377600
H74: 3 year | I74: KL4241WA*T5 | K74: 173434800 | L74: 173434800 | M74: 173434800 | N74: 173434800 | O74: 173434800 | P74: 173434800 | Q74: 173434800 | R74: 173434800 | S74: 173434800 | T74: 173434800 | U74: 147424200 | V74: 147424200 | W74: 138738600 | X74: 138738600 | Y74: 131623800 | Z74: 131623800 | AA74: 131623800 | AB74: 131623800
G75: Renewal Premium Plus | H75: 1 year | I75: KL4241WA*F6 | K75: 57819300 | L75: 57819300 | M75: 57819300 | N75: 57819300 | O75: 57819300 | P75: 57819300 | Q75: 57819300 | R75: 57819300 | S75: 57819300 | T75: 57819300 | U75: 49133700 | V75: 49133700 | W75: 46246200 | X75: 46246200 | Y75: 39131400 | Z75: 39131400 | AA75: 39131400 | AB75: 39131400
H76: 2 year | I76: KL4241WA*D6 | K76: 101385900 | L76: 101385900 | M76: 101385900 | N76: 101385900 | O76: 101385900 | P76: 101385900 | Q76: 101385900 | R76: 101385900 | S76: 101385900 | T76: 101385900 | U76: 86186100 | V76: 86186100 | W76: 81104100 | X76: 81104100 | Y76: 73989300 | Z76: 73989300 | AA76: 73989300 | AB76: 73989300
H77: 3 year | I77: KL4241WA*T6 | K77: 152090400 | L77: 152090400 | M77: 152090400 | N77: 152090400 | O77: 152090400 | P77: 152090400 | Q77: 152090400 | R77: 152090400 | S77: 152090400 | T77: 152090400 | U77: 129290700 | V77: 129290700 | W77: 121667700 | X77: 121667700 | Y77: 114552900 | Z77: 114552900 | AA77: 114552900 | AB77: 114552900
G78: Base Premium | H78: 1 year | I78: KL4241WA*FA | K78: 57819300 | L78: 57819300 | M78: 57819300 | N78: 57819300 | O78: 57819300 | P78: 57819300 | Q78: 57819300 | R78: 57819300 | S78: 57819300 | T78: 57819300 | U78: 49133700 | V78: 49133700 | W78: 46246200 | X78: 46246200 | Y78: 42688800 | Z78: 42688800 | AA78: 42688800 | AB78: 42688800
H79: 2 year | I79: KL4241WA*DA | K79: 97828500 | L79: 97828500 | M79: 97828500 | N79: 97828500 | O79: 97828500 | P79: 97828500 | Q79: 97828500 | R79: 97828500 | S79: 97828500 | T79: 97828500 | U79: 83160000 | V79: 83160000 | W79: 78262800 | X79: 78262800 | Y79: 74705400 | Z79: 74705400 | AA79: 74705400 | AB79: 74705400
H80: 3 year | I80: KL4241WA*TA | K80: 146754300 | L80: 146754300 | M80: 146754300 | N80: 146754300 | O80: 146754300 | P80: 146754300 | Q80: 146754300 | R80: 146754300 | S80: 146754300 | T80: 146754300 | U80: 124740000 | V80: 124740000 | W80: 117394200 | X80: 117394200 | Y80: 113836800 | Z80: 113836800 | AA80: 113836800 | AB80: 113836800
G81: Renewal Premium | H81: 1 year | I81: KL4241WA*FL | K81: 48925800 | L81: 48925800 | M81: 48925800 | N81: 48925800 | O81: 48925800 | P81: 48925800 | Q81: 48925800 | R81: 48925800 | S81: 48925800 | T81: 48925800 | U81: 41580000 | V81: 41580000 | W81: 39131400 | X81: 39131400 | Y81: 35574000 | Z81: 35574000 | AA81: 35574000 | AB81: 35574000
H82: 2 year | I82: KL4241WA*DL | K82: 83598900 | L82: 83598900 | M82: 83598900 | N82: 83598900 | O82: 83598900 | P82: 83598900 | Q82: 83598900 | R82: 83598900 | S82: 83598900 | T82: 83598900 | U82: 71078700 | V82: 71078700 | W82: 66874500 | X82: 66874500 | Y82: 63317100 | Z82: 63317100 | AA82: 63317100 | AB82: 63317100
H83: 3 year | I83: KL4241WA*TL | K83: 125409900 | L83: 125409900 | M83: 125409900 | N83: 125409900 | O83: 125409900 | P83: 125409900 | Q83: 125409900 | R83: 125409900 | S83: 125409900 | T83: 125409900 | U83: 106606500 | V83: 106606500 | W83: 100323300 | X83: 100323300 | Y83: 96765900 | Z83: 96765900 | AA83: 96765900 | AB83: 96765900
B84: 4007 | C84: Kaspersky SD-WAN Advanced CPE 500 Mbps | D84: Dvc | E84: License | G84: Base Premium Plus | H84: 1 year | I84: KL4244WA*F5 | K84: 353106600 | L84: 353106600 | M84: 353106600 | N84: 353106600 | O84: 353106600 | P84: 353106600 | Q84: 353106600 | R84: 353106600 | S84: 353106600 | T84: 353106600 | U84: 300138300 | V84: 300138300 | W84: 282489900 | X84: 282489900 | Y84: 244836900 | Z84: 244836900 | AA84: 244836900 | AB84: 244836900
H85: 2 year | I85: KL4244WA*D5 | K85: 612057600 | L85: 612057600 | M85: 612057600 | N85: 612057600 | O85: 612057600 | P85: 612057600 | Q85: 612057600 | R85: 612057600 | S85: 612057600 | T85: 612057600 | U85: 520235100 | V85: 520235100 | W85: 489650700 | X85: 489650700 | Y85: 451974600 | Z85: 451974600 | AA85: 451974600 | AB85: 451974600
H86: 3 year | I86: KL4244WA*T5 | K86: 918063300 | L86: 918063300 | M86: 918063300 | N86: 918063300 | O86: 918063300 | P86: 918063300 | Q86: 918063300 | R86: 918063300 | S86: 918063300 | T86: 918063300 | U86: 780364200 | V86: 780364200 | W86: 734441400 | X86: 734441400 | Y86: 696788400 | Z86: 696788400 | AA86: 696788400 | AB86: 696788400
G87: Renewal Premium Plus | H87: 1 year | I87: KL4244WA*F6 | K87: 306005700 | L87: 306005700 | M87: 306005700 | N87: 306005700 | O87: 306005700 | P87: 306005700 | Q87: 306005700 | R87: 306005700 | S87: 306005700 | T87: 306005700 | U87: 260129100 | V87: 260129100 | W87: 244836900 | X87: 244836900 | Y87: 207137700 | Z87: 207137700 | AA87: 207137700 | AB87: 207137700
H88: 2 year | I88: KL4244WA*D6 | K88: 536705400 | L88: 536705400 | M88: 536705400 | N88: 536705400 | O88: 536705400 | P88: 536705400 | Q88: 536705400 | R88: 536705400 | S88: 536705400 | T88: 536705400 | U88: 456201900 | V88: 456201900 | W88: 429382800 | X88: 429382800 | Y88: 391729800 | Z88: 391729800 | AA88: 391729800 | AB88: 391729800
H89: 3 year | I89: KL4244WA*T6 | K89: 805081200 | L89: 805081200 | M89: 805081200 | N89: 805081200 | O89: 805081200 | P89: 805081200 | Q89: 805081200 | R89: 805081200 | S89: 805081200 | T89: 805081200 | U89: 684314400 | V89: 684314400 | W89: 644074200 | X89: 644074200 | Y89: 606421200 | Z89: 606421200 | AA89: 606421200 | AB89: 606421200
G90: Base Premium | H90: 1 year | I90: KL4244WA*FA | K90: 306005700 | L90: 306005700 | M90: 306005700 | N90: 306005700 | O90: 306005700 | P90: 306005700 | Q90: 306005700 | R90: 306005700 | S90: 306005700 | T90: 306005700 | U90: 260129100 | V90: 260129100 | W90: 244836900 | X90: 244836900 | Y90: 225987300 | Z90: 225987300 | AA90: 225987300 | AB90: 225987300
H91: 2 year | I91: KL4244WA*DA | K91: 517878900 | L91: 517878900 | M91: 517878900 | N91: 517878900 | O91: 517878900 | P91: 517878900 | Q91: 517878900 | R91: 517878900 | S91: 517878900 | T91: 517878900 | U91: 440193600 | V91: 440193600 | W91: 414321600 | X91: 414321600 | Y91: 395472000 | Z91: 395472000 | AA91: 395472000 | AB91: 395472000
H92: 3 year | I92: KL4244WA*TA | K92: 776829900 | L92: 776829900 | M92: 776829900 | N92: 776829900 | O92: 776829900 | P92: 776829900 | Q92: 776829900 | R92: 776829900 | S92: 776829900 | T92: 776829900 | U92: 660313500 | V92: 660313500 | W92: 621459300 | X92: 621459300 | Y92: 602632800 | Z92: 602632800 | AA92: 602632800 | AB92: 602632800
G93: Renewal Premium | H93: 1 year | I93: KL4244WA*FL | K93: 258951000 | L93: 258951000 | M93: 258951000 | N93: 258951000 | O93: 258951000 | P93: 258951000 | Q93: 258951000 | R93: 258951000 | S93: 258951000 | T93: 258951000 | U93: 220096800 | V93: 220096800 | W93: 207137700 | X93: 207137700 | Y93: 188311200 | Z93: 188311200 | AA93: 188311200 | AB93: 188311200
H94: 2 year | I94: KL4244WA*DL | K94: 442572900 | L94: 442572900 | M94: 442572900 | N94: 442572900 | O94: 442572900 | P94: 442572900 | Q94: 442572900 | R94: 442572900 | S94: 442572900 | T94: 442572900 | U94: 376160400 | V94: 376160400 | W94: 354030600 | X94: 354030600 | Y94: 335204100 | Z94: 335204100 | AA94: 335204100 | AB94: 335204100
H95: 3 year | I95: KL4244WA*TL | K95: 663847800 | L95: 663847800 | M95: 663847800 | N95: 663847800 | O95: 663847800 | P95: 663847800 | Q95: 663847800 | R95: 663847800 | S95: 663847800 | T95: 663847800 | U95: 564263700 | V95: 564263700 | W95: 531069000 | X95: 531069000 | Y95: 512242500 | Z95: 512242500 | AA95: 512242500 | AB95: 512242500
B96: 4012 | C96: Kaspersky SD-WAN Standard CPE 1 Gbps | D96: Dvc | E96: License | G96: Base Premium Plus | H96: 1 year | I96: KL4238WA*F5 | K96: 389165700 | L96: 389165700 | M96: 389165700 | N96: 389165700 | O96: 389165700 | P96: 389165700 | Q96: 389165700 | R96: 389165700 | S96: 389165700 | T96: 389165700 | U96: 330792000 | V96: 330792000 | W96: 311318700 | X96: 311318700 | Y96: 269831100 | Z96: 269831100 | AA96: 269831100 | AB96: 269831100
H97: 2 year | I97: KL4238WA*D5 | K97: 674566200 | L97: 674566200 | M97: 674566200 | N97: 674566200 | O97: 674566200 | P97: 674566200 | Q97: 674566200 | R97: 674566200 | S97: 674566200 | T97: 674566200 | U97: 573388200 | V97: 573388200 | W97: 539639100 | X97: 539639100 | Y97: 498128400 | Z97: 498128400 | AA97: 498128400 | AB97: 498128400
H98: 3 year | I98: KL4238WA*T5 | K98: 1011826200 | L98: 1011826200 | M98: 1011826200 | N98: 1011826200 | O98: 1011826200 | P98: 1011826200 | Q98: 1011826200 | R98: 1011826200 | S98: 1011826200 | T98: 1011826200 | U98: 860059200 | V98: 860059200 | W98: 809470200 | X98: 809470200 | Y98: 767936400 | Z98: 767936400 | AA98: 767936400 | AB98: 767936400
G99: Renewal Premium Plus | H99: 1 year | I99: KL4238WA*F6 | K99: 337260000 | L99: 337260000 | M99: 337260000 | N99: 337260000 | O99: 337260000 | P99: 337260000 | Q99: 337260000 | R99: 337260000 | S99: 337260000 | T99: 337260000 | U99: 286671000 | V99: 286671000 | W99: 269831100 | X99: 269831100 | Y99: 228320400 | Z99: 228320400 | AA99: 228320400 | AB99: 228320400
H100: 2 year | I100: KL4238WA*D6 | K100: 591521700 | L100: 591521700 | M100: 591521700 | N100: 591521700 | O100: 591521700 | P100: 591521700 | Q100: 591521700 | R100: 591521700 | S100: 591521700 | T100: 591521700 | U100: 502794600 | V100: 502794600 | W100: 473203500 | X100: 473203500 | Y100: 431715900 | Z100: 431715900 | AA100: 431715900 | AB100: 431715900
H101: 3 year | I101: KL4238WA*T6 | K101: 887294100 | L101: 887294100 | M101: 887294100 | N101: 887294100 | O101: 887294100 | P101: 887294100 | Q101: 887294100 | R101: 887294100 | S101: 887294100 | T101: 887294100 | U101: 754191900 | V101: 754191900 | W101: 709839900 | X101: 709839900 | Y101: 668306100 | Z101: 668306100 | AA101: 668306100 | AB101: 668306100
G102: Base Premium | H102: 1 year | I102: KL4238WA*FA | K102: 337260000 | L102: 337260000 | M102: 337260000 | N102: 337260000 | O102: 337260000 | P102: 337260000 | Q102: 337260000 | R102: 337260000 | S102: 337260000 | T102: 337260000 | U102: 286671000 | V102: 286671000 | W102: 269831100 | X102: 269831100 | Y102: 249064200 | Z102: 249064200 | AA102: 249064200 | AB102: 249064200
H103: 2 year | I103: KL4238WA*DA | K103: 570754800 | L103: 570754800 | M103: 570754800 | N103: 570754800 | O103: 570754800 | P103: 570754800 | Q103: 570754800 | R103: 570754800 | S103: 570754800 | T103: 570754800 | U103: 485146200 | V103: 485146200 | W103: 456617700 | X103: 456617700 | Y103: 435850800 | Z103: 435850800 | AA103: 435850800 | AB103: 435850800
H104: 3 year | I104: KL4238WA*TA | K104: 856155300 | L104: 856155300 | M104: 856155300 | N104: 856155300 | O104: 856155300 | P104: 856155300 | Q104: 856155300 | R104: 856155300 | S104: 856155300 | T104: 856155300 | U104: 727742400 | V104: 727742400 | W104: 684938100 | X104: 684938100 | Y104: 664171200 | Z104: 664171200 | AA104: 664171200 | AB104: 664171200
G105: Renewal Premium | H105: 1 year | I105: KL4238WA*FL | K105: 285377400 | L105: 285377400 | M105: 285377400 | N105: 285377400 | O105: 285377400 | P105: 285377400 | Q105: 285377400 | R105: 285377400 | S105: 285377400 | T105: 285377400 | U105: 242596200 | V105: 242596200 | W105: 228320400 | X105: 228320400 | Y105: 207553500 | Z105: 207553500 | AA105: 207553500 | AB105: 207553500
H106: 2 year | I106: KL4238WA*DL | K106: 487756500 | L106: 487756500 | M106: 487756500 | N106: 487756500 | O106: 487756500 | P106: 487756500 | Q106: 487756500 | R106: 487756500 | S106: 487756500 | T106: 487756500 | U106: 414598800 | V106: 414598800 | W106: 390205200 | X106: 390205200 | Y106: 369438300 | Z106: 369438300 | AA106: 369438300 | AB106: 369438300
...

Sheet ATC
C7: =CONCATENATE("Price List applicable for ",Data!A9,". Effective from ",Data!A11,". ") -> Price List applicable for Vietnam. Effective from July 1, 2026. | J7: * For additional details please see
C8: =CONCATENATE(Data!A5,". ",Data!A7) -> Kaspersky Lab. 39A/3 Leningradskoe Shosse Moscow, 125212. 0 | J8: specifications in Comment section
J9: For the avoidance of doubt, it is hereby confirmed that the prices listed in the ‘ATC’ tab of this Price List
J10: are not recommended retail prices (MSRP), but represent the amount of license fees (royalties) payable to the Vendor (Manufacturer).
B11: Max of Price | J11: Band
B12: Code | C12: Product | D12: LicenceDescription | E12: Package | F12: LicenceObject | G12: Type | H12: Term | I12: SKU | J12: Band A: 1
B13: 4000 | C13: ATC* | D13: - | E13: - | F13: - | G13: - | H13: - | I13: -
B14: 4001 | C14: KL 034. Kaspersky Unified Monitoring and Analysis Platform Course | D14: Trainee | E14: License Pack | G14: Base | I14: KL7522WC*ZS | J14: 24381000
B15: 4002 | C15: KL 036. Kaspersky Secure Mail Gateway Course | D15: Trainee | E15: License Pack | G15: Base | I15: KL7523WC*ZS | J15: 3276000
B16: 4004 | C16: KL 302. Kaspersky Endpoint Security for Windows. Advanced Course | D16: Trainee | E16: License Pack | G16: Base | I16: KL7541WC*ZS | J16: 5187000
B17: 4005 | C17: KL 008. Endpoint Security and Management. Encryption Course | D17: Trainee | E17: License Pack | G17: Base | I17: KL7542WC*ZS | J17: 3171000
B18: 4006 | C18: KL 009. Kaspersky Endpoint Security for Windows. Systems Management Course | D18: Trainee | E18: License Pack | G18: Base | I18: KL7543WC*ZS | J18: 3171000
B19: 4007 | C19: KL 014. Kaspersky Endpoint Security for Virtualization. Agentless Course | D19: Trainee | E19: License Pack | G19: Base | I19: KL7545WC*ZS | J19: 3171000
B20: 4008 | C20: KL 031. Kaspersky Endpoint Security for Virtualization. Light Agent Course | D20: Trainee | E20: License Pack | G20: Base | I20: KL7547WC*ZS | J20: 3171000
B21: 4009 | C21: KL 005. Kaspersky Security for Windows Server Course | D21: Trainee | E21: License Pack | G21: Base | I21: KL7548WC*ZS | J21: 5187000
B22: 4011 | C22: KL 025. Kaspersky Anti Targeted Attack Platform & Endpoint Detection and Response Course | D22: Trainee | E22: License Pack | G22: Base | I22: KL7572WC*ZS | J22: 23688000
B23: 4012 | C23: KL 038. Kaspersky Industrial CyberSecurity Course | D23: Trainee | E23: License Pack | G23: Base | I23: KL7617WC*ZS | J23: 20307000
B24: 4015 | C24: KL 004. Kaspersky SD-WAN Course | D24: Trainee | E24: License Pack | G24: Base | I24: KL7527WC*ZS | J24: 20307000
B25: 4017 | C25: KL 044. Kaspersky Container Security Course | D25: Trainee | E25: License Pack | G25: Base | I25: KL7524WC*ZS | J25: 7749000
B26: 4018 | C26: KL 047. Kaspersky Next EDR Optimum Course | E26: License Pack | G26: Base | I26: KL7517WC*ZS | J26: 5922000
B27: 4019 | C27: KL 046. Kaspersky Next EDR Foundations Course | E27: License Pack | G27: Base | I27: KL7515WC*ZS | J27: 8211000
B28: 4021 | C28: KL 047. Kaspersky Next EDR Optimum Course + virtual labs | E28: License Pack | G28: Base | I28: KL7516WC*ZS | J28: 6930000
B29: 4022 | C29: KL 048. Kaspersky Next XDR Expert Course + virtual labs | E29: License Pack | G29: Base | I29: KL7627WC*ZS | J29: 31479000
B30: 4023 | C30: KL 048. Kaspersky Next XDR Expert Course | E30: License Pack | G30: Base | I30: KL7626WC*ZS | J30: 27237000
B31: 4024 | C31: KL 057. Kaspersky Anti Targeted Attack. Investigation + virtual labs | D31: Trainee | E31: License Pack | F31: Trainee | G31: Base | I31: KL7629WC*ZS | J31: 23835000
B32: 4025 | C32: KL 057. Kaspersky Anti Targeted Attack. Investigation | D32: Trainee | E32: License Pack | F32: Trainee | G32: Base | I32: KL7630WC*ZS | J32: 20790000
B33: 4026 | C33: KL 051. Kaspersky Unified Monitoring and Analysis Platform. Investigation | D33: Trainee | E33: License Pack | F33: Trainee | G33: Base | I33: KL7633WC*ZS | J33: 15939000
B34: 4027 | C34: KL 051. Kaspersky Unified Monitoring and Analysis Platform. Investigation + virtual labs | D34: Trainee | E34: License Pack | F34: Trainee | G34: Base | I34: KL7634WC*ZS | J34: 19677000
B35: 4028 | C35: KL 025. Kaspersky Anti Targeted Attack. Kaspersky EDR. Administration | D35: Trainee | E35: License Pack | F35: Trainee | G35: Base | I35: KL7635WC*ZS | J35: 15792000
B36: 4029 | C36: KL 025. Kaspersky Anti Targeted Attack. Kaspersky EDR. Administration + virtual labs | D36: Trainee | E36: License Pack | F36: Trainee | G36: Base | I36: KL7636WC*ZS | J36: 20244000
B37: 4031 | C37: KL 034. Kaspersky Unified Monitoring and Analysis Platform. Administration | D37: Trainee | E37: License Pack | F37: Trainee | G37: Base | I37: KL7637WC*ZS | J37: 13860000
B38: 4032 | C38: KL 034. Kaspersky Unified Monitoring and Analysis Platform. Administration + virtual labs | D38: Trainee | E38: License Pack | F38: Trainee | G38: Base | I38: KL7638WC*ZS | J38: 17598000
B39: 4033 | C39: KL 034. Kaspersky Unified Monitoring and Analysis Platform Course + virtual labs | D39: Trainee | E39: License Pack | F39: Trainee | G39: Base | I39: KL7504WC*ZS | J39: 21475000
B40: 4034 | C40: KL 036. Kaspersky Secure Mail Gateway Course + virtual labs | D40: Trainee | E40: License Pack | F40: Trainee | G40: Base | I40: KL7505WC*ZS | J40: 3400000
B41: 4035 | C41: KL 044. Kaspersky Container Security Course + virtual labs | D41: Trainee | E41: License Pack | F41: Trainee | G41: Base | I41: KL7506WC*ZS | J41: 7425000
B42: 4036 | C42: KL 025. Kaspersky Anti Targeted Attack Platform, Kaspersky Endpoint Detection Course + virtual labs | D42: Trainee | E42: License Pack | F42: Trainee | G42: Base | I42: KL7507WC*ZS | J42: 21600000
... B50: 4045 | C50: KL 059. Kaspersky XDR Expert. Investigation Course + virtual labs | D50: Trainee | E50: License Pack | F50: Trainee | G50: Base | I50: KL7651WC*ZS | J50: 24750000

Sheet ProductSelector
R3: Local Currency Rate: | S3: 1
C9: Describe customer IT infrastructure | H9: Product | I9: SKU | J9: Quantity | K9: Price 1Y | L9: Price 2Y | M9: Price 3Y | N9: Discount | O9: Amount 1Y | P9: Amount 2Y | Q9: Amount 3Y | R9: Rslr Margin | S9: Distri Margin
C11: System/Platform | D11: Quantity | H11: Option 1
C12: Total number of Endpoints | D12: =SUM(D13:D15) -> 0 | G12: 1 | H12: =IF(I12<>"",VLOOKUP(U12,$G$54:$H$66,2,0),"") | I12: =IF(ISERROR(U12),"",CONCATENATE("KL",U12,Data!$D$4,V12,Data!$B$100,Data!$B$107)) | J12: =IF(ISERROR(U12),"",IF(U12=$I$64,$D$23,IF(U12=$I$65,$D$24,MAX(IF(U12=$I$54,$D$13,MAX(IF(U12=$I$58,$D$14,IF(U12=$I$59,$D$18,IF(U12=$I$56,MAX($D$12,$D$18),IF(U12=$I$60,$D$19,IF(U12=$I$61,$D$20,IF(U12=$I$62,$D$21,IF(U12=$I$63,$D$22,IF(U12=$I$66,$D$25,$D$12)))))))),10)),$I$68)))) | K12: =IF(ISERROR(VLOOKUP(W12,'SaleListSMB+Enterprise'!$A:$M,13,FALSE)),"-",$S$3*VLOOKUP(W12,'SaleListSMB+Enterprise'!$A:$M,13,FALSE)) -> - | L12: =IF($J12="-","-",IF(ISERROR(VLOOKUP(X12,'SaleListSMB+Enterprise'!$A:$M,13,FALSE)),"-",$S$3*VLOOKUP(X12,'SaleListSMB+Enterprise'!$A:$M,13,FALSE))) -> - | M12: =IF($J12="-","-",IF(ISERROR(VLOOKUP(Y12,'SaleListSMB+Enterprise'!$A:$M,13,FALSE)),"-",$S$3*VLOOKUP(Y12,'SaleListSMB+Enterprise'!$A:$M,13,FALSE))) -> - | O12: =IF(OR($J12="-",K12="-"),"-",J12*K12*(1-$N12)*IF($D$31="Incl.VAT",1+$D$30,1)) -> - | P12: =IF(OR($J12="-",L12="-"),"-",J12*L12*(1-$N12)*IF($D$31="Incl.VAT",1+$D$30,1)) -> - | Q12: =IF(OR($J12="-",M12="-"),"-",J12*M12*(1-$N12)*IF($D$31="Incl.VAT",1+$D$30,1)) -> - | R12: =IF($J12="-",0,IF(AND($D$29="1 Year",K12<>"-"),O12,IF(AND($D$29="2 Years",L12<>"-"),P12,IF(AND($D$29="3 Years",M12<>"-"),Q12,0)))*IF($D$32>0,$D$32,0)) -> 0 | S12: =IF($J12="-",0,IF(AND($D$29="1 Year",K12<>"-"),O12,IF(AND($D$29="2 Years",L12<>"-"),P12,IF(AND($D$29="3 Years",M12<>"-"),Q12,0)))*IF($D$33>0,$D$33-$D$32,0)) -> 0 | U12: =VLOOKUP(G12,$O$54:$P$66,2,0) -> #N/A | V12: =VLOOKUP(J12,Data!$A$120:$B$137,2) -> #N/A | W12: =CONCATENATE(LEFT($I12,9),"F",Data!$B$107) -> #N/A | X12: =CONCATENATE(LEFT($I12,9),"D",Data!$B$107) -> #N/A | Y12: =CONCATENATE(LEFT($I12,9),"T",Data!$B$107) -> #N/A
C13: Workstations | G13: 2 | H13: =IF(I13<>"",VLOOKUP(U13,$G$54:$H$66,2,0),"") | I13: =IF(ISERROR(U13),"",CONCATENATE("KL",U13,Data!$D$4,V13,Data!$B$100,Data!$B$107)) | J13: =IF(ISERROR(U13),"",IF(U13=$I$64,$D$23,IF(U13=$I$65,$D$24,MAX(IF(U13=$I$54,$D$13,MAX(IF(U13=$I$58,$D$14,IF(U13=$I$59,$D$18,IF(U13=$I$56,MAX($D$12,$D$18),IF(U13=$I$60,$D$19,IF(U13=$I$61,$D$20,IF(U13=$I$62,$D$21,IF(U13=$I$63,$D$22,IF(U13=$I$66,$D$25,$D$12)))))))),10)),$I$68)))) | K13: =IF($J13="-","-",IF(ISERROR(VLOOKUP(W13,'SaleListSMB+Enterprise'!$A:$M,13,FALSE)),"-",S3*VLOOKUP(W13,'SaleListSMB+Enterprise'!$A:$M,13,FALSE))) -> - | L13: =IF($J13="-","-",IF(ISERROR(VLOOKUP(X13,'SaleListSMB+Enterprise'!$A:$M,13,FALSE)),"-",S3*VLOOKUP(X13,'SaleListSMB+Enterprise'!$A:$M,13,FALSE))) -> - | M13: =IF($J13="-","-",IF(ISERROR(VLOOKUP(Y13,'SaleListSMB+Enterprise'!$A:$M,13,FALSE)),"-",S3*VLOOKUP(Y13,'SaleListSMB+Enterprise'!$A:$M,13,FALSE))) -> - | O13: =IF(OR($J13="-",K13="-"),"-",J13*K13*(1-$N13)*IF($D$31="Incl.VAT",1+$D$30,1)) -> - | P13: =IF(OR($J13="-",L13="-"),"-",J13*L13*(1-$N13)*IF($D$31="Incl.VAT",1+$D$30,1)) -> - | Q13: =IF(OR($J13="-",M13="-"),"-",J13*M13*(1-$N13)*IF($D$31="Incl.VAT",1+$D$30,1)) -> - | R13: =IF($J13="-",0,IF(AND($D$29="1 Year",K13<>"-"),O13,IF(AND($D$29="2 Years",L13<>"-"),P13,IF(AND($D$29="3 Years",M13<>"-"),Q13,0)))*IF($D$32>0,$D$32,0)) -> 0 | S13: =IF($J13="-",0,IF(AND($D$29="1 Year",K13<>"-"),O13,IF(AND($D$29="2 Years",L13<>"-"),P13,IF(AND($D$29="3 Years",M13<>"-"),Q13,0)))*IF($D$33>0,$D$33-$D$32,0)) -> 0 | U13: =VLOOKUP(G13,$O$54:$P$66,2,0) -> #N/A | V13: =VLOOKUP(J13,Data!$A$120:$B$137,2) -> #N/A | W13: =CONCATENATE(LEFT($I13,9),"F",Data!$B$107) -> #N/A | X13: =CONCATENATE(LEFT($I13,9),"D",Data!$B$107) -> #N/A | Y13: =CONCATENATE(LEFT($I13,9),"T",Data!$B$107) -> #N/A
C14: Mobile devices | G14: 3 | H14: =IF(I14<>"",VLOOKUP(U14,$G$54:$H$66,2,0),"") | I14: =IF(ISERROR(U14),"",CONCATENATE("KL",U14,Data!$D$4,V14,Data!$B$100,Data!$B$107)) | J14: =IF(ISERROR(U14),"",IF(U14=$I$64,$D$23,IF(U14=$I$65,$D$24,MAX(IF(U14=$I$54,$D$13,MAX(IF(U14=$I$58,$D$14,IF(U14=$I$59,$D$18,IF(U14=$I$56,MAX($D$12,$D$18),IF(U14=$I$60,$D$19,IF(U14=$I$61,$D$20,IF(U14=$I$62,$D$21,IF(U14=$I$63,$D$22,IF(U14=$I$66,$D$25,$D$12)))))))),10)),$I$68)))) | K14: =IF($J14="-","-",IF(ISERROR(VLOOKUP(W14,'SaleListSMB+Enterprise'!$A:$M,13,FALSE)),"-",S3*VLOOKUP(W14,'SaleListSMB+Enterprise'!$A:$M,13,FALSE))) -> - | L14: =IF($J14="-","-",IF(ISERROR(VLOOKUP(X14,'SaleListSMB+Enterprise'!$A:$M,13,FALSE)),"-",S3*VLOOKUP(X14,'SaleListSMB+Enterprise'!$A:$M,13,FALSE))) -> - | M14: =IF($J14="-","-",IF(ISERROR(VLOOKUP(Y14,'SaleListSMB+Enterprise'!$A:$M,13,FALSE)),"-",S3*VLOOKUP(Y14,'SaleListSMB+Enterprise'!$A:$M,13,FALSE))) -> - | O14: =IF(OR($J14="-",K14="-"),"-",J14*K14*(1-$N14)*IF($D$31="Incl.VAT",1+$D$30,1)) -> - | P14: =IF(OR($J14="-",L14="-"),"-",J14*L14*(1-$N14)*IF($D$31="Incl.VAT",1+$D$30,1)) -> - | Q14: =IF(OR($J14="-",M14="-"),"-",J14*M14*(1-$N14)*IF($D$31="Incl.VAT",1+$D$30,1)) -> - | R14: =IF($J14="-",0,IF(AND($D$29="1 Year",K14<>"-"),O14,IF(AND($D$29="2 Years",L14<>"-"),P14,IF(AND($D$29="3 Years",M14<>"-"),Q14,0)))*IF($D$32>0,$D$32,0)) -> 0 | S14: =IF($J14="-",0,IF(AND($D$29="1 Year",K14<>"-"),O14,IF(AND($D$29="2 Years",L14<>"-"),P14,IF(AND($D$29="3 Years",M14<>"-"),Q14,0)))*IF($D$33>0,$D$33-$D$32,0)) -> 0 | U14: =VLOOKUP(G14,$O$54:$P$66,2,0) -> #N/A | V14: =VLOOKUP(J14,Data!$A$120:$B$137,2) -> #N/A | W14: =CONCATENATE(LEFT($I14,9),"F",Data!$B$107) -> #N/A | X14: =CONCATENATE(LEFT($I14,9),"D",Data!$B$107) -> #N/A | Y14: =CONCATENATE(LEFT($I14,9),"T",Data!$B$107) -> #N/A
C15: File servers | G15: 4 | H15: =IF(I15<>"",VLOOKUP(U15,$G$54:$H$66,2,0),"") | I15: =IF(ISERROR(U15),"",CONCATENATE("KL",U15,Data!$D$4,V15,Data!$B$100,Data!$B$107)) | J15: =IF(ISERROR(U15),"",IF(U15=$I$64,$D$23,IF(U15=$I$65,$D$24,MAX(IF(U15=$I$54,$D$13,MAX(IF(U15=$I$58,$D$14,IF(U15=$I$59,$D$18,IF(U15=$I$56,MAX($D$12,$D$18),IF(U15=$I$60,$D$19,IF(U15=$I$61,$D$20,IF(U15=$I$62,$D$21,IF(U15=$I$63,$D$22,IF(U15=$I$66,$D$25,$D$12)))))))),10)),$I$68)))) | K15: =IF(ISERROR(VLOOKUP(W15,'SaleListSMB+Enterprise'!$A:$M,13,FALSE)),"-",$S$3*VLOOKUP(W15,'SaleListSMB+Enterprise'!$A:$M,13,FALSE)) -> - | L15: =IF($J15="-","-",IF(ISERROR(VLOOKUP(X15,'SaleListSMB+Enterprise'!$A:$M,13,FALSE)),"-",$S$3*VLOOKUP(X15,'SaleListSMB+Enterprise'!$A:$M,13,FALSE))) -> - | M15: =IF($J15="-","-",IF(ISERROR(VLOOKUP(Y15,'SaleListSMB+Enterprise'!$A:$M,13,FALSE)),"-",$S$3*VLOOKUP(Y15,'SaleListSMB+Enterprise'!$A:$M,13,FALSE))) -> - | O15: =IF(OR($J15="-",K15="-"),"-",J15*K15*(1-$N15)*IF($D$31="Incl.VAT",1+$D$30,1)) -> - | P15: =IF(OR($J15="-",L15="-"),"-",J15*L15*(1-$N15)*IF($D$31="Incl.VAT",1+$D$30,1)) -> - | Q15: =IF(OR($J15="-",M15="-"),"-",J15*M15*(1-$N15)*IF($D$31="Incl.VAT",1+$D$30,1)) -> - | R15: =IF($J15="-",0,IF(AND($D$29="1 Year",K15<>"-"),O15,IF(AND($D$29="2 Years",L15<>"-"),P15,IF(AND($D$29="3 Years",M15<>"-"),Q15,0)))*IF($D$32>0,$D$32,0)) -> 0 | S15: =IF($J15="-",0,IF(AND($D$29="1 Year",K15<>"-"),O15,IF(AND($D$29="2 Years",L15<>"-"),P15,IF(AND($D$29="3 Years",M15<>"-"),Q15,0)))*IF($D$33>0,$D$33-$D$32,0)) -> 0 | U15: =VLOOKUP(G15,$O$54:$P$66,2,0) -> #N/A | V15: =VLOOKUP(J15,Data!$A$120:$B$137,2) -> #N/A | W15: =CONCATENATE(LEFT($I15,9),"F",Data!$B$107) -> #N/A | X15: =CONCATENATE(LEFT($I15,9),"D",Data!$B$107) -> #N/A | Y15: =CONCATENATE(LEFT($I15,9),"T",Data!$B$107) -> #N/A
C16: App/Device/Web Control | D16: - | G16: 5 | H16: =IF(I16<>"",VLOOKUP(U16,$G$54:$H$66,2,0),"") | I16: =IF(ISERROR(U16),"",CONCATENATE("KL",U16,Data!$D$4,V16,Data!$B$100,Data!$B$107)) | J16: =IF(ISERROR(U16),"",IF(U16=$I$64,$D$23,IF(U16=$I$65,$D$24,MAX(IF(U16=$I$54,$D$13,MAX(IF(U16=$I$58,$D$14,IF(U16=$I$59,$D$18,IF(U16=$I$56,MAX($D$12,$D$18),IF(U16=$I$60,$D$19,IF(U16=$I$61,$D$20,IF(U16=$I$62,$D$21,IF(U16=$I$63,$D$22,IF(U16=$I$66,$D$25,$D$12)))))))),10)),$I$68)))) | K16: =IF(ISERROR(VLOOKUP(W16,'SaleListSMB+Enterprise'!$A:$M,13,FALSE)),"-",$S$3*VLOOKUP(W16,'SaleListSMB+Enterprise'!$A:$M,13,FALSE)) -> - | L16: =IF($J16="-","-",IF(ISERROR(VLOOKUP(X16,'SaleListSMB+Enterprise'!$A:$M,13,FALSE)),"-",$S$3*VLOOKUP(X16,'SaleListSMB+Enterprise'!$A:$M,13,FALSE))) -> - | M16: =IF($J16="-","-",IF(ISERROR(VLOOKUP(Y16,'SaleListSMB+Enterprise'!$A:$M,13,FALSE)),"-",$S$3*VLOOKUP(Y16,'SaleListSMB+Enterprise'!$A:$M,13,FALSE))) -> - | O16: =IF(OR($J16="-",K16="-"),"-",J16*K16*(1-$N16)*IF($D$31="Incl.VAT",1+$D$30,1)) -> - | P16: =IF(OR($J16="-",L16="-"),"-",J16*L16*(1-$N16)*IF($D$31="Incl.VAT",1+$D$30,1)) -> - | Q16: =IF(OR($J16="-",M16="-"),"-",J16*M16*(1-$N16)*IF($D$31="Incl.VAT",1+$D$30,1)) -> - | R16: =IF($J16="-",0,IF(AND($D$29="1 Year",K16<>"-"),O16,IF(AND($D$29="2 Years",L16<>"-"),P16,IF(AND($D$29="3 Years",M16<>"-"),Q16,0)))*IF($D$32>0,$D$32,0)) -> 0 | S16: =IF($J16="-",0,IF(AND($D$29="1 Year",K16<>"-"),O16,IF(AND($D$29="2 Years",L16<>"-"),P16,IF(AND($D$29="3 Years",M16<>"-"),Q16,0)))*IF($D$33>0,$D$33-$D$32,0)) -> 0 | U16: =VLOOKUP(G16,$O$54:$P$66,2,0) -> #N/A | V16: =VLOOKUP(J16,Data!$A$120:$B$137,2) -> #N/A | W16: =CONCATENATE(LEFT($I16,9),"F",Data!$B$107) -> #N/A | X16: =CONCATENATE(LEFT($I16,9),"D",Data!$B$107) -> #N/A | Y16: =CONCATENATE(LEFT($I16,9),"T",Data!$B$107) -> #N/A
C17: Encryption | D17: - | G17: 6 | H17: =IF(I17<>"",VLOOKUP(U17,$G$54:$H$66,2,0),"") | I17: =IF(ISERROR(U17),"",CONCATENATE("KL",U17,Data!$D$4,V17,Data!$B$100,Data!$B$107)) | J17: =IF(ISERROR(U17),"",IF(U17=$I$64,$D$23,IF(U17=$I$65,$D$24,MAX(IF(U17=$I$54,$D$13,MAX(IF(U17=$I$58,$D$14,IF(U17=$I$59,$D$18,IF(U17=$I$56,MAX($D$12,$D$18),IF(U17=$I$60,$D$19,IF(U17=$I$61,$D$20,IF(U17=$I$62,$D$21,IF(U17=$I$63,$D$22,IF(U17=$I$66,$D$25,$D$12)))))))),10)),$I$68)))) | K17: =IF(ISERROR(VLOOKUP(W17,'SaleListSMB+Enterprise'!$A:$M,13,FALSE)),"-",$S$3*VLOOKUP(W17,'SaleListSMB+Enterprise'!$A:$M,13,FALSE)) -> - | L17: =IF($J17="-","-",IF(ISERROR(VLOOKUP(X17,'SaleListSMB+Enterprise'!$A:$M,13,FALSE)),"-",$S$3*VLOOKUP(X17,'SaleListSMB+Enterprise'!$A:$M,13,FALSE))) -> - | M17: =IF($J17="-","-",IF(ISERROR(VLOOKUP(Y17,'SaleListSMB+Enterprise'!$A:$M,13,FALSE)),"-",$S$3*VLOOKUP(Y17,'SaleListSMB+Enterprise'!$A:$M,13,FALSE))) -> - | O17: =IF(OR($J17="-",K17="-"),"-",J17*K17*(1-$N17)*IF($D$31="Incl.VAT",1+$D$30,1)) -> - | P17: =IF(OR($J17="-",L17="-"),"-",J17*L17*(1-$N17)*IF($D$31="Incl.VAT",1+$D$30,1)) -> - | Q17: =IF(OR($J17="-",M17="-"),"-",J17*M17*(1-$N17)*IF($D$31="Incl.VAT",1+$D$30,1)) -> - | R17: =IF($J17="-",0,IF(AND($D$29="1 Year",K17<>"-"),O17,IF(AND($D$29="2 Years",L17<>"-"),P17,IF(AND($D$29="3 Years",M17<>"-"),Q17,0)))*IF($D$32>0,$D$32,0)) -> 0 | S17: =IF($J17="-",0,IF(AND($D$29="1 Year",K17<>"-"),O17,IF(AND($D$29="2 Years",L17<>"-"),P17,IF(AND($D$29="3 Years",M17<>"-"),Q17,0)))*IF($D$33>0,$D$33-$D$32,0)) -> 0 | U17: =VLOOKUP(G17,$O$54:$P$66,2,0) -> #N/A | V17: =VLOOKUP(J17,Data!$A$120:$B$137,2) -> #N/A | W17: =CONCATENATE(LEFT($I17,9),"F",Data!$B$107) -> #N/A | X17: =CONCATENATE(LEFT($I17,9),"D",Data!$B$107) -> #N/A | Y17: =CONCATENATE(LEFT($I17,9),"T",Data!$B$107) -> #N/A
C18: Systems management nodes | G18: 7 | H18: =IF(I18<>"",VLOOKUP(U18,$G$54:$H$66,2,0),"") | I18: =IF(ISERROR(U18),"",CONCATENATE("KL",U18,Data!$D$4,V18,Data!$B$100,Data!$B$107)) | J18: =IF(ISERROR(U18),"",IF(U18=$I$64,$D$23,IF(U18=$I$65,$D$24,MAX(IF(U18=$I$54,$D$13,MAX(IF(U18=$I$58,$D$14,IF(U18=$I$59,$D$18,IF(U18=$I$56,MAX($D$12,$D$18),IF(U18=$I$60,$D$19,IF(U18=$I$61,$D$20,IF(U18=$I$62,$D$21,IF(U18=$I$63,$D$22,IF(U18=$I$66,$D$25,$D$12)))))))),10)),$I$68)))) | K18: =IF(ISERROR(VLOOKUP(W18,'SaleListSMB+Enterprise'!$A:$M,13,FALSE)),"-",$S$3*VLOOKUP(W18,'SaleListSMB+Enterprise'!$A:$M,13,FALSE)) -> - | L18: =IF($J18="-","-",IF(ISERROR(VLOOKUP(X18,'SaleListSMB+Enterprise'!$A:$M,13,FALSE)),"-",$S$3*VLOOKUP(X18,'SaleListSMB+Enterprise'!$A:$M,13,FALSE))) -> - | M18: =IF($J18="-","-",IF(ISERROR(VLOOKUP(Y18,'SaleListSMB+Enterprise'!$A:$M,13,FALSE)),"-",$S$3*VLOOKUP(Y18,'SaleListSMB+Enterprise'!$A:$M,13,FALSE))) -> - | O18: =IF(OR($J18="-",K18="-"),"-",J18*K18*(1-$N18)*IF($D$31="Incl.VAT",1+$D$30,1)) -> - | P18: =IF(OR($J18="-",L18="-"),"-",J18*L18*(1-$N18)*IF($D$31="Incl.VAT",1+$D$30,1)) -> - | Q18: =IF(OR($J18="-",M18="-"),"-",J18*M18*(1-$N18)*IF($D$31="Incl.VAT",1+$D$30,1)) -> - | R18: =IF($J18="-",0,IF(AND($D$29="1 Year",K18<>"-"),O18,IF(AND($D$29="2 Years",L18<>"-"),P18,IF(AND($D$29="3 Years",M18<>"-"),Q18,0)))*IF($D$32>0,$D$32,0)) -> 0 | S18: =IF($J18="-",0,IF(AND($D$29="1 Year",K18<>"-"),O18,IF(AND($D$29="2 Years",L18<>"-"),P18,IF(AND($D$29="3 Years",M18<>"-"),Q18,0)))*IF($D$33>0,$D$33-$D$32,0)) -> 0 | U18: =VLOOKUP(G18,$O$54:$P$66,2,0) -> #N/A | V18: =VLOOKUP(J18,Data!$A$120:$B$137,2) -> #N/A | W18: =CONCATENATE(LEFT($I18,9),"F",Data!$B$107) -> #N/A | X18: =CONCATENATE(LEFT($I18,9),"D",Data!$B$107) -> #N/A | Y18: =CONCATENATE(LEFT($I18,9),"T",Data!$B$107) -> #N/A
C19: Mail boxes/ addresses | G19: 8 | H19: =IF(I19<>"",VLOOKUP(U19,$G$54:$H$66,2,0),"") | I19: =IF(ISERROR(U19),"",CONCATENATE("KL",U19,Data!$D$4,V19,Data!$B$100,Data!$B$107)) | J19: =IF(ISERROR(U19),"",IF(U19=$I$64,$D$23,IF(U19=$I$65,$D$24,MAX(IF(U19=$I$54,$D$13,MAX(IF(U19=$I$58,$D$14,IF(U19=$I$59,$D$18,IF(U19=$I$56,MAX($D$12,$D$18),IF(U19=$I$60,$D$19,IF(U19=$I$61,$D$20,IF(U19=$I$62,$D$21,IF(U19=$I$63,$D$22,IF(U19=$I$66,$D$25,$D$12)))))))),10)),$I$68)))) | K19: =IF(ISERROR(VLOOKUP(W19,'SaleListSMB+Enterprise'!$A:$M,13,FALSE)),"-",$S$3*VLOOKUP(W19,'SaleListSMB+Enterprise'!$A:$M,13,FALSE)) -> - | L19: =IF($J19="-","-",IF(ISERROR(VLOOKUP(X19,'SaleListSMB+Enterprise'!$A:$M,13,FALSE)),"-",$S$3*VLOOKUP(X19,'SaleListSMB+Enterprise'!$A:$M,13,FALSE))) -> - | M19: =IF($J19="-","-",IF(ISERROR(VLOOKUP(Y19,'SaleListSMB+Enterprise'!$A:$M,13,FALSE)),"-",$S$3*VLOOKUP(Y19,'SaleListSMB+Enterprise'!$A:$M,13,FALSE))) -> - | O19: =IF(OR($J19="-",K19="-"),"-",J19*K19*(1-$N19)*IF($D$31="Incl.VAT",1+$D$30,1)) -> - | P19: =IF(OR($J19="-",L19="-"),"-",J19*L19*(1-$N19)*IF($D$31="Incl.VAT",1+$D$30,1)) -> - | Q19: =IF(OR($J19="-",M19="-"),"-",J19*M19*(1-$N19)*IF($D$31="Incl.VAT",1+$D$30,1)) -> - | R19: =IF($J19="-",0,IF(AND($D$29="1 Year",K19<>"-"),O19,IF(AND($D$29="2 Years",L19<>"-"),P19,IF(AND($D$29="3 Years",M19<>"-"),Q19,0)))*IF($D$32>0,$D$32,0)) -> 0 | S19: =IF($J19="-",0,IF(AND($D$29="1 Year",K19<>"-"),O19,IF(AND($D$29="2 Years",L19<>"-"),P19,IF(AND($D$29="3 Years",M19<>"-"),Q19,0)))*IF($D$33>0,$D$33-$D$32,0)) -> 0 | U19: =VLOOKUP(G19,$O$54:$P$66,2,0) -> #N/A | V19: =VLOOKUP(J19,Data!$A$120:$B$137,2) -> #N/A | W19: =CONCATENATE(LEFT($I19,9),"F",Data!$B$107) -> #N/A | X19: =CONCATENATE(LEFT($I19,9),"D",Data!$B$107) -> #N/A | Y19: =CONCATENATE(LEFT($I19,9),"T",Data!$B$107) -> #N/A
C20: Internet gateway nodes | G20: 9 | H20: =IF(I20<>"",VLOOKUP(U20,$G$54:$H$66,2,0),"") | I20: =IF(ISERROR(U20),"",CONCATENATE("KL",U20,Data!$D$4,V20,Data!$B$100,Data!$B$107)) | J20: =IF(ISERROR(U20),"",IF(U20=$I$64,$D$23,IF(U20=$I$65,$D$24,MAX(IF(U20=$I$54,$D$13,MAX(IF(U20=$I$58,$D$14,IF(U20=$I$59,$D$18,IF(U20=$I$56,MAX($D$12,$D$18),IF(U20=$I$60,$D$19,IF(U20=$I$61,$D$20,IF(U20=$I$62,$D$21,IF(U20=$I$63,$D$22,IF(U20=$I$66,$D$25,$D$12)))))))),10)),$I$68)))) | K20: =IF(ISERROR(VLOOKUP(W20,'SaleListSMB+Enterprise'!$A:$M,13,FALSE)),"-",$S$3*VLOOKUP(W20,'SaleListSMB+Enterprise'!$A:$M,13,FALSE)) -> - | L20: =IF($J20="-","-",IF(ISERROR(VLOOKUP(X20,'SaleListSMB+Enterprise'!$A:$M,13,FALSE)),"-",$S$3*VLOOKUP(X20,'SaleListSMB+Enterprise'!$A:$M,13,FALSE))) -> - | M20: =IF($J20="-","-",IF(ISERROR(VLOOKUP(Y20,'SaleListSMB+Enterprise'!$A:$M,13,FALSE)),"-",$S$3*VLOOKUP(Y20,'SaleListSMB+Enterprise'!$A:$M,13,FALSE))) -> - | O20: =IF(OR($J20="-",K20="-"),"-",J20*K20*(1-$N20)*IF($D$31="Incl.VAT",1+$D$30,1)) -> - | P20: =IF(OR($J20="-",L20="-"),"-",J20*L20*(1-$N20)*IF($D$31="Incl.VAT",1+$D$30,1)) -> - | Q20: =IF(OR($J20="-",M20="-"),"-",J20*M20*(1-$N20)*IF($D$31="Incl.VAT",1+$D$30,1)) -> - | R20: =IF($J20="-",0,IF(AND($D$29="1 Year",K20<>"-"),O20,IF(AND($D$29="2 Years",L20<>"-"),P20,IF(AND($D$29="3 Years",M20<>"-"),Q20,0)))*IF($D$32>0,$D$32,0)) -> 0 | S20: =IF($J20="-",0,IF(AND($D$29="1 Year",K20<>"-"),O20,IF(AND($D$29="2 Years",L20<>"-"),P20,IF(AND($D$29="3 Years",M20<>"-"),Q20,0)))*IF($D$33>0,$D$33-$D$32,0)) -> 0 | U20: =VLOOKUP(G20,$O$54:$P$66,2,0) -> #N/A | V20: =VLOOKUP(J20,Data!$A$120:$B$137,2) -> #N/A | W20: =CONCATENATE(LEFT($I20,9),"F",Data!$B$107) -> #N/A | X20: =CONCATENATE(LEFT($I20,9),"D",Data!$B$107) -> #N/A | Y20: =CONCATENATE(LEFT($I20,9),"T",Data!$B$107) -> #N/A
C21: Collaboration nodes | G21: 10 | H21: =IF(I21<>"",VLOOKUP(U21,$G$54:$H$66,2,0),"") | I21: =IF(ISERROR(U21),"",CONCATENATE("KL",U21,Data!$D$4,V21,Data!$B$100,Data!$B$107)) | J21: =IF(ISERROR(U21),"",IF(U21=$I$64,$D$23,IF(U21=$I$65,$D$24,MAX(IF(U21=$I$54,$D$13,MAX(IF(U21=$I$58,$D$14,IF(U21=$I$59,$D$18,IF(U21=$I$56,MAX($D$12,$D$18),IF(U21=$I$60,$D$19,IF(U21=$I$61,$D$20,IF(U21=$I$62,$D$21,IF(U21=$I$63,$D$22,IF(U21=$I$66,$D$25,$D$12)))))))),10)),$I$68)))) | K21: =IF(ISERROR(VLOOKUP(W21,'SaleListSMB+Enterprise'!$A:$M,13,FALSE)),"-",$S$3*VLOOKUP(W21,'SaleListSMB+Enterprise'!$A:$M,13,FALSE)) -> - | L21: =IF($J21="-","-",IF(ISERROR(VLOOKUP(X21,'SaleListSMB+Enterprise'!$A:$M,13,FALSE)),"-",$S$3*VLOOKUP(X21,'SaleListSMB+Enterprise'!$A:$M,13,FALSE))) -> - | M21: =IF($J21="-","-",IF(ISERROR(VLOOKUP(Y21,'SaleListSMB+Enterprise'!$A:$M,13,FALSE)),"-",$S$3*VLOOKUP(Y21,'SaleListSMB+Enterprise'!$A:$M,13,FALSE))) -> - | O21: =IF(OR($J21="-",K21="-"),"-",J21*K21*(1-$N21)*IF($D$31="Incl.VAT",1+$D$30,1)) -> - | P21: =IF(OR($J21="-",L21="-"),"-",J21*L21*(1-$N21)*IF($D$31="Incl.VAT",1+$D$30,1)) -> - | Q21: =IF(OR($J21="-",M21="-"),"-",J21*M21*(1-$N21)*IF($D$31="Incl.VAT",1+$D$30,1)) -> - | R21: =IF($J21="-",0,IF(AND($D$29="1 Year",K21<>"-"),O21,IF(AND($D$29="2 Years",L21<>"-"),P21,IF(AND($D$29="3 Years",M21<>"-"),Q21,0)))*IF($D$32>0,$D$32,0)) -> 0 | S21: =IF($J21="-",0,IF(AND($D$29="1 Year",K21<>"-"),O21,IF(AND($D$29="2 Years",L21<>"-"),P21,IF(AND($D$29="3 Years",M21<>"-"),Q21,0)))*IF($D$33>0,$D$33-$D$32,0)) -> 0 | U21: =VLOOKUP(G21,$O$54:$P$66,2,0) -> #N/A | V21: =VLOOKUP(J21,Data!$A$120:$B$137,2) -> #N/A | W21: =CONCATENATE(LEFT($I21,9),"F",Data!$B$107) -> #N/A | X21: =CONCATENATE(LEFT($I21,9),"D",Data!$B$107) -> #N/A | Y21: =CONCATENATE(LEFT($I21,9),"T",Data!$B$107) -> #N/A
C22: Virtual desktops | G22: 1 | H22: Total Option 1: | O22: =SUM(O12:O21) -> 0 | P22: =SUM(P12:P21) -> 0 | Q22: =SUM(Q12:Q21) -> 0 | R22: =SUM(R12:R21) -> 0 | S22: =SUM(S12:S21) -> 0
C23: Virtual servers | G23: 2 | H23: Option 2
C24: Cores | G24: 1 | H24: =IF(I24<>"",VLOOKUP(U24,$G$54:$H$66,2,0),"") | I24: =IF(ISERROR(U24),"",CONCATENATE("KL",U24,Data!$D$4,V24,Data!$B$100,IF(OR(U24=$I$60,U24=$I$61,U24=$I$62),"H",Data!$B$107))) | J24: =IF(ISERROR(U24),"",IF(U24=$I$64,$D$23,IF(U24=$I$65,$D$24,IF(U24=$I$54,$D$13,IF(U24=$I$55,MAX($D$12,$I$68),MAX(IF(U24=$I$58,$D$14,IF(U24=$I$59,$D$18,IF(U24=$I$56,MAX($D$12,$D$18),IF(U24=$I$60,ROUNDUP($D$19/1.5,0),IF(U24=$I$61,ROUNDUP($D$20/1.1,0),IF(U24=$I$62,$D$21,IF(U24=$I$63,$D$22,IF(U24=$I$66,$D$25,$D$12)))))))),10)))))) | K24: =IF(ISERROR(VLOOKUP(W24,'SaleListSMB+Enterprise'!$A:$M,13,FALSE)),"-",$S$3*VLOOKUP(W24,'SaleListSMB+Enterprise'!$A:$M,13,FALSE)) -> - | L24: =IF($J24="-","-",IF(ISERROR(VLOOKUP(X24,'SaleListSMB+Enterprise'!$A:$M,13,FALSE)),"-",$S$3*VLOOKUP(X24,'SaleListSMB+Enterprise'!$A:$M,13,FALSE))) -> - | M24: =IF($J24="-","-",IF(ISERROR(VLOOKUP(Y24,'SaleListSMB+Enterprise'!$A:$M,13,FALSE)),"-",$S$3*VLOOKUP(Y24,'SaleListSMB+Enterprise'!$A:$M,13,FALSE))) -> - | O24: =IF(OR($J24="-",K24="-"),"-",J24*K24*(1-$N24)*IF($D$31="Incl.VAT",1+$D$30,1)) -> - | P24: =IF(OR($J24="-",L24="-"),"-",J24*L24*(1-$N24)*IF($D$31="Incl.VAT",1+$D$30,1)) -> - | Q24: =IF(OR($J24="-",M24="-"),"-",J24*M24*(1-$N24)*IF($D$31="Incl.VAT",1+$D$30,1)) -> - | R24: =IF($J24="-",0,IF(AND($D$29="1 Year",K24<>"-"),O24,IF(AND($D$29="2 Years",L24<>"-"),P24,IF(AND($D$29="3 Years",M24<>"-"),Q24,0)))*IF($D$32>0,$D$32,0)) -> 0 | S24: =IF($J24="-",0,IF(AND($D$29="1 Year",K24<>"-"),O24,IF(AND($D$29="2 Years",L24<>"-"),P24,IF(AND($D$29="3 Years",M24<>"-"),Q24,0)))*IF($D$33>0,$D$33-$D$32,0)) -> 0 | U24: =VLOOKUP(G24,$R$54:$S$66,2,0) -> #N/A | V24: =VLOOKUP(J24,Data!$A$120:$B$137,2) -> #N/A | W24: =CONCATENATE(LEFT($I24,9),"F",IF(OR(U24=$I$60,U24=$I$61,U24=$I$62),"H",Data!$B$107)) -> #N/A | X24: =CONCATENATE(LEFT($I24,9),"D",IF(OR(U24=$I$60,U24=$I$61,U24=$I$62),"H",Data!$B$107)) -> #N/A | Y24: =CONCATENATE(LEFT($I24,9),"T",IF(OR(U24=$I$60,U24=$I$61,U24=$I$62),"H",Data!$B$107)) -> #N/A
C25: Storage users | G25: 2 | H25: =IF(I25<>"",VLOOKUP(U25,$G$54:$H$66,2,0),"") | I25: =IF(ISERROR(U25),"",CONCATENATE("KL",U25,Data!$D$4,V25,Data!$B$100,IF(OR(U25=$I$60,U25=$I$61,U25=$I$62),"H",Data!$B$107))) | J25: =IF(ISERROR(U25),"",IF(U25=$I$64,$D$23,IF(U25=$I$65,$D$24,IF(U25=$I$54,$D$13,IF(U25=$I$55,MAX($D$12,$I$68),MAX(IF(U25=$I$58,$D$14,IF(U25=$I$59,$D$18,IF(U25=$I$56,MAX($D$12,$D$18),IF(U25=$I$60,ROUNDUP($D$19/1.5,0),IF(U25=$I$61,ROUNDUP($D$20/1.1,0),IF(U25=$I$62,$D$21,IF(U25=$I$63,$D$22,IF(U25=$I$66,$D$25,$D$12)))))))),10)))))) | K25: =IF(ISERROR(VLOOKUP(W25,'SaleListSMB+Enterprise'!$A:$M,13,FALSE)),"-",$S$3*VLOOKUP(W25,'SaleListSMB+Enterprise'!$A:$M,13,FALSE)) -> - | L25: =IF($J25="-","-",IF(ISERROR(VLOOKUP(X25,'SaleListSMB+Enterprise'!$A:$M,13,FALSE)),"-",$S$3*VLOOKUP(X25,'SaleListSMB+Enterprise'!$A:$M,13,FALSE))) -> - | M25: =IF($J25="-","-",IF(ISERROR(VLOOKUP(Y25,'SaleListSMB+Enterprise'!$A:$M,13,FALSE)),"-",$S$3*VLOOKUP(Y25,'SaleListSMB+Enterprise'!$A:$M,13,FALSE))) -> - | O25: =IF(OR($J25="-",K25="-"),"-",J25*K25*(1-$N25)*IF($D$31="Incl.VAT",1+$D$30,1)) -> - | P25: =IF(OR($J25="-",L25="-"),"-",J25*L25*(1-$N25)*IF($D$31="Incl.VAT",1+$D$30,1)) -> - | Q25: =IF(OR($J25="-",M25="-"),"-",J25*M25*(1-$N25)*IF($D$31="Incl.VAT",1+$D$30,1)) -> - | R25: =IF($J25="-",0,IF(AND($D$29="1 Year",K25<>"-"),O25,IF(AND($D$29="2 Years",L25<>"-"),P25,IF(AND($D$29="3 Years",M25<>"-"),Q25,0)))*IF($D$32>0,$D$32,0)) -> 0 | S25: =IF($J25="-",0,IF(AND($D$29="1 Year",K25<>"-"),O25,IF(AND($D$29="2 Years",L25<>"-"),P25,IF(AND($D$29="3 Years",M25<>"-"),Q25,0)))*IF($D$33>0,$D$33-$D$32,0)) -> 0 | U25: =VLOOKUP(G25,$R$54:$S$66,2,0) -> #N/A | V25: =VLOOKUP(J25,Data!$A$120:$B$137,2) -> #N/A | W25: =CONCATENATE(LEFT($I25,9),"F",IF(OR(U25=$I$60,U25=$I$61,U25=$I$62),"H",Data!$B$107)) -> #N/A | X25: =CONCATENATE(LEFT($I25,9),"D",IF(OR(U25=$I$60,U25=$I$61,U25=$I$62),"H",Data!$B$107)) -> #N/A | Y25: =CONCATENATE(LEFT($I25,9),"T",IF(OR(U25=$I$60,U25=$I$61,U25=$I$62),"H",Data!$B$107)) -> #N/A
C26: Help | G26: 3 | H26: =IF(I26<>"",VLOOKUP(U26,$G$54:$H$66,2,0),"") | I26: =IF(ISERROR(U26),"",CONCATENATE("KL",U26,Data!$D$4,V26,Data!$B$100,IF(OR(U26=$I$60,U26=$I$61,U26=$I$62),"H",Data!$B$107))) | J26: =IF(ISERROR(U26),"",IF(U26=$I$64,$D$23,IF(U26=$I$65,$D$24,IF(U26=$I$54,$D$13,IF(U26=$I$55,MAX($D$12,$I$68),MAX(IF(U26=$I$58,$D$14,IF(U26=$I$59,$D$18,IF(U26=$I$56,MAX($D$12,$D$18),IF(U26=$I$60,ROUNDUP($D$19/1.5,0),IF(U26=$I$61,ROUNDUP($D$20/1.1,0),IF(U26=$I$62,$D$21,IF(U26=$I$63,$D$22,IF(U26=$I$66,$D$25,$D$12)))))))),10)))))) | K26: =IF(ISERROR(VLOOKUP(W26,'SaleListSMB+Enterprise'!$A:$M,13,FALSE)),"-",$S$3*VLOOKUP(W26,'SaleListSMB+Enterprise'!$A:$M,13,FALSE)) -> - | L26: =IF($J26="-","-",IF(ISERROR(VLOOKUP(X26,'SaleListSMB+Enterprise'!$A:$M,13,FALSE)),"-",$S$3*VLOOKUP(X26,'SaleListSMB+Enterprise'!$A:$M,13,FALSE))) -> - | M26: =IF($J26="-","-",IF(ISERROR(VLOOKUP(Y26,'SaleListSMB+Enterprise'!$A:$M,13,FALSE)),"-",$S$3*VLOOKUP(Y26,'SaleListSMB+Enterprise'!$A:$M,13,FALSE))) -> - | O26: =IF(OR($J26="-",K26="-"),"-",J26*K26*(1-$N26)*IF($D$31="Incl.VAT",1+$D$30,1)) -> - | P26: =IF(OR($J26="-",L26="-"),"-",J26*L26*(1-$N26)*IF($D$31="Incl.VAT",1+$D$30,1)) -> - | Q26: =IF(OR($J26="-",M26="-"),"-",J26*M26*(1-$N26)*IF($D$31="Incl.VAT",1+$D$30,1)) -> - | R26: =IF($J26="-",0,IF(AND($D$29="1 Year",K26<>"-"),O26,IF(AND($D$29="2 Years",L26<>"-"),P26,IF(AND($D$29="3 Years",M26<>"-"),Q26,0)))*IF($D$32>0,$D$32,0)) -> 0 | S26: =IF($J26="-",0,IF(AND($D$29="1 Year",K26<>"-"),O26,IF(AND($D$29="2 Years",L26<>"-"),P26,IF(AND($D$29="3 Years",M26<>"-"),Q26,0)))*IF($D$33>0,$D$33-$D$32,0)) -> 0 | U26: =VLOOKUP(G26,$R$54:$S$66,2,0) -> #N/A | V26: =VLOOKUP(J26,Data!$A$120:$B$137,2) -> #N/A | W26: =CONCATENATE(LEFT($I26,9),"F",IF(OR(U26=$I$60,U26=$I$61,U26=$I$62),"H",Data!$B$107)) -> #N/A | X26: =CONCATENATE(LEFT($I26,9),"D",IF(OR(U26=$I$60,U26=$I$61,U26=$I$62),"H",Data!$B$107)) -> #N/A | Y26: =CONCATENATE(LEFT($I26,9),"T",IF(OR(U26=$I$60,U26=$I$61,U26=$I$62),"H",Data!$B$107)) -> #N/A
G27: 4 | H27: =IF(I27<>"",VLOOKUP(U27,$G$54:$H$66,2,0),"") | I27: =IF(ISERROR(U27),"",CONCATENATE("KL",U27,Data!$D$4,V27,Data!$B$100,IF(OR(U27=$I$60,U27=$I$61,U27=$I$62),"H",Data!$B$107))) | J27: =IF(ISERROR(U27),"",IF(U27=$I$64,$D$23,IF(U27=$I$65,$D$24,IF(U27=$I$54,$D$13,IF(U27=$I$55,MAX($D$12,$I$68),MAX(IF(U27=$I$58,$D$14,IF(U27=$I$59,$D$18,IF(U27=$I$56,MAX($D$12,$D$18),IF(U27=$I$60,ROUNDUP($D$19/1.5,0),IF(U27=$I$61,ROUNDUP($D$20/1.1,0),IF(U27=$I$62,$D$21,IF(U27=$I$63,$D$22,IF(U27=$I$66,$D$25,$D$12)))))))),10)))))) | K27: =IF(ISERROR(VLOOKUP(W27,'SaleListSMB+Enterprise'!$A:$M,13,FALSE)),"-",$S$3*VLOOKUP(W27,'SaleListSMB+Enterprise'!$A:$M,13,FALSE)) -> - | L27: =IF($J27="-","-",IF(ISERROR(VLOOKUP(X27,'SaleListSMB+Enterprise'!$A:$M,13,FALSE)),"-",$S$3*VLOOKUP(X27,'SaleListSMB+Enterprise'!$A:$M,13,FALSE))) -> - | M27: =IF($J27="-","-",IF(ISERROR(VLOOKUP(Y27,'SaleListSMB+Enterprise'!$A:$M,13,FALSE)),"-",$S$3*VLOOKUP(Y27,'SaleListSMB+Enterprise'!$A:$M,13,FALSE))) -> - | O27: =IF(OR($J27="-",K27="-"),"-",J27*K27*(1-$N27)*IF($D$31="Incl.VAT",1+$D$30,1)) -> - | P27: =IF(OR($J27="-",L27="-"),"-",J27*L27*(1-$N27)*IF($D$31="Incl.VAT",1+$D$30,1)) -> - | Q27: =IF(OR($J27="-",M27="-"),"-",J27*M27*(1-$N27)*IF($D$31="Incl.VAT",1+$D$30,1)) -> - | R27: =IF($J27="-",0,IF(AND($D$29="1 Year",K27<>"-"),O27,IF(AND($D$29="2 Years",L27<>"-"),P27,IF(AND($D$29="3 Years",M27<>"-"),Q27,0)))*IF($D$32>0,$D$32,0)) -> 0 | S27: =IF($J27="-",0,IF(AND($D$29="1 Year",K27<>"-"),O27,IF(AND($D$29="2 Years",L27<>"-"),P27,IF(AND($D$29="3 Years",M27<>"-"),Q27,0)))*IF($D$33>0,$D$33-$D$32,0)) -> 0 | U27: =VLOOKUP(G27,$R$54:$S$66,2,0) -> #N/A | V27: =VLOOKUP(J27,Data!$A$120:$B$137,2) -> #N/A | W27: =CONCATENATE(LEFT($I27,9),"F",IF(OR(U27=$I$60,U27=$I$61,U27=$I$62),"H",Data!$B$107)) -> #N/A | X27: =CONCATENATE(LEFT($I27,9),"D",IF(OR(U27=$I$60,U27=$I$61,U27=$I$62),"H",Data!$B$107)) -> #N/A | Y27: =CONCATENATE(LEFT($I27,9),"T",IF(OR(U27=$I$60,U27=$I$61,U27=$I$62),"H",Data!$B$107)) -> #N/A
C28: Select license type * | D28: Base | G28: 5 | H28: =IF(I28<>"",VLOOKUP(U28,$G$54:$H$66,2,0),"") | I28: =IF(ISERROR(U28),"",CONCATENATE("KL",U28,Data!$D$4,V28,Data!$B$100,IF(OR(U28=$I$60,U28=$I$61,U28=$I$62),"H",Data!$B$107))) | J28: =IF(ISERROR(U28),"",IF(U28=$I$64,$D$23,IF(U28=$I$65,$D$24,IF(U28=$I$54,$D$13,IF(U28=$I$55,MAX($D$12,$I$68),MAX(IF(U28=$I$58,$D$14,IF(U28=$I$59,$D$18,IF(U28=$I$56,MAX($D$12,$D$18),IF(U28=$I$60,ROUNDUP($D$19/1.5,0),IF(U28=$I$61,ROUNDUP($D$20/1.1,0),IF(U28=$I$62,$D$21,IF(U28=$I$63,$D$22,IF(U28=$I$66,$D$25,$D$12)))))))),10)))))) | K28: =IF(ISERROR(VLOOKUP(W28,'SaleListSMB+Enterprise'!$A:$M,13,FALSE)),"-",$S$3*VLOOKUP(W28,'SaleListSMB+Enterprise'!$A:$M,13,FALSE)) -> - | L28: =IF($J28="-","-",IF(ISERROR(VLOOKUP(X28,'SaleListSMB+Enterprise'!$A:$M,13,FALSE)),"-",$S$3*VLOOKUP(X28,'SaleListSMB+Enterprise'!$A:$M,13,FALSE))) -> - | M28: =IF($J28="-","-",IF(ISERROR(VLOOKUP(Y28,'SaleListSMB+Enterprise'!$A:$M,13,FALSE)),"-",$S$3*VLOOKUP(Y28,'SaleListSMB+Enterprise'!$A:$M,13,FALSE))) -> - | O28: =IF(OR($J28="-",K28="-"),"-",J28*K28*(1-$N28)*IF($D$31="Incl.VAT",1+$D$30,1)) -> - | P28: =IF(OR($J28="-",L28="-"),"-",J28*L28*(1-$N28)*IF($D$31="Incl.VAT",1+$D$30,1)) -> - | Q28: =IF(OR($J28="-",M28="-"),"-",J28*M28*(1-$N28)*IF($D$31="Incl.VAT",1+$D$30,1)) -> - | R28: =IF($J28="-",0,IF(AND($D$29="1 Year",K28<>"-"),O28,IF(AND($D$29="2 Years",L28<>"-"),P28,IF(AND($D$29="3 Years",M28<>"-"),Q28,0)))*IF($D$32>0,$D$32,0)) -> 0 | S28: =IF($J28="-",0,IF(AND($D$29="1 Year",K28<>"-"),O28,IF(AND($D$29="2 Years",L28<>"-"),P28,IF(AND($D$29="3 Years",M28<>"-"),Q28,0)))*IF($D$33>0,$D$33-$D$32,0)) -> 0 | U28: =VLOOKUP(G28,$R$54:$S$66,2,0) -> #N/A | V28: =VLOOKUP(J28,Data!$A$120:$B$137,2) -> #N/A | W28: =CONCATENATE(LEFT($I28,9),"F",IF(OR(U28=$I$60,U28=$I$61,U28=$I$62),"H",Data!$B$107)) -> #N/A | X28: =CONCATENATE(LEFT($I28,9),"D",IF(OR(U28=$I$60,U28=$I$61,U28=$I$62),"H",Data!$B$107)) -> #N/A | Y28: =CONCATENATE(LEFT($I28,9),"T",IF(OR(U28=$I$60,U28=$I$61,U28=$I$62),"H",Data!$B$107)) -> #N/A
C29: Select subscription period * | D29: 1 Year | G29: 6 | H29: =IF(I29<>"",VLOOKUP(U29,$G$54:$H$66,2,0),"") | I29: =IF(ISERROR(U29),"",CONCATENATE("KL",U29,Data!$D$4,V29,Data!$B$100,IF(OR(U29=$I$60,U29=$I$61,U29=$I$62),"H",Data!$B$107))) | J29: =IF(ISERROR(U29),"",IF(U29=$I$64,$D$23,IF(U29=$I$65,$D$24,IF(U29=$I$54,$D$13,IF(U29=$I$55,MAX($D$12,$I$68),MAX(IF(U29=$I$58,$D$14,IF(U29=$I$59,$D$18,IF(U29=$I$56,MAX($D$12,$D$18),IF(U29=$I$60,ROUNDUP($D$19/1.5,0),IF(U29=$I$61,ROUNDUP($D$20/1.1,0),IF(U29=$I$62,$D$21,IF(U29=$I$63,$D$22,IF(U29=$I$66,$D$25,$D$12)))))))),10)))))) | K29: =IF(ISERROR(VLOOKUP(W29,'SaleListSMB+Enterprise'!$A:$M,13,FALSE)),"-",$S$3*VLOOKUP(W29,'SaleListSMB+Enterprise'!$A:$M,13,FALSE)) -> - | L29: =IF($J29="-","-",IF(ISERROR(VLOOKUP(X29,'SaleListSMB+Enterprise'!$A:$M,13,FALSE)),"-",$S$3*VLOOKUP(X29,'SaleListSMB+Enterprise'!$A:$M,13,FALSE))) -> - | M29: =IF($J29="-","-",IF(ISERROR(VLOOKUP(Y29,'SaleListSMB+Enterprise'!$A:$M,13,FALSE)),"-",$S$3*VLOOKUP(Y29,'SaleListSMB+Enterprise'!$A:$M,13,FALSE))) -> - | O29: =IF(OR($J29="-",K29="-"),"-",J29*K29*(1-$N29)*IF($D$31="Incl.VAT",1+$D$30,1)) -> - | P29: =IF(OR($J29="-",L29="-"),"-",J29*L29*(1-$N29)*IF($D$31="Incl.VAT",1+$D$30,1)) -> - | Q29: =IF(OR($J29="-",M29="-"),"-",J29*M29*(1-$N29)*IF($D$31="Incl.VAT",1+$D$30,1)) -> - | R29: =IF($J29="-",0,IF(AND($D$29="1 Year",K29<>"-"),O29,IF(AND($D$29="2 Years",L29<>"-"),P29,IF(AND($D$29="3 Years",M29<>"-"),Q29,0)))*IF($D$32>0,$D$32,0)) -> 0 | S29: =IF($J29="-",0,IF(AND($D$29="1 Year",K29<>"-"),O29,IF(AND($D$29="2 Years",L29<>"-"),P29,IF(AND($D$29="3 Years",M29<>"-"),Q29,0)))*IF($D$33>0,$D$33-$D$32,0)) -> 0 | U29: =VLOOKUP(G29,$R$54:$S$66,2,0) -> #N/A | V29: =VLOOKUP(J29,Data!$A$120:$B$137,2) -> #N/A | W29: =CONCATENATE(LEFT($I29,9),"F",IF(OR(U29=$I$60,U29=$I$61,U29=$I$62),"H",Data!$B$107)) -> #N/A | X29: =CONCATENATE(LEFT($I29,9),"D",IF(OR(U29=$I$60,U29=$I$61,U29=$I$62),"H",Data!$B$107)) -> #N/A | Y29: =CONCATENATE(LEFT($I29,9),"T",IF(OR(U29=$I$60,U29=$I$61,U29=$I$62),"H",Data!$B$107)) -> #N/A
C30: VAT Rate | G30: 7 | H30: =IF(I30<>"",VLOOKUP(U30,$G$54:$H$66,2,0),"") | I30: =IF(ISERROR(U30),"",CONCATENATE("KL",U30,Data!$D$4,V30,Data!$B$100,IF(OR(U30=$I$60,U30=$I$61,U30=$I$62),"H",Data!$B$107))) | J30: =IF(ISERROR(U30),"",IF(U30=$I$64,$D$23,IF(U30=$I$65,$D$24,IF(U30=$I$54,$D$13,IF(U30=$I$55,MAX($D$12,$I$68),MAX(IF(U30=$I$58,$D$14,IF(U30=$I$59,$D$18,IF(U30=$I$56,MAX($D$12,$D$18),IF(U30=$I$60,ROUNDUP($D$19/1.5,0),IF(U30=$I$61,ROUNDUP($D$20/1.1,0),IF(U30=$I$62,$D$21,IF(U30=$I$63,$D$22,IF(U30=$I$66,$D$25,$D$12)))))))),10)))))) | K30: =IF(ISERROR(VLOOKUP(W30,'SaleListSMB+Enterprise'!$A:$M,13,FALSE)),"-",$S$3*VLOOKUP(W30,'SaleListSMB+Enterprise'!$A:$M,13,FALSE)) -> - | L30: =IF($J30="-","-",IF(ISERROR(VLOOKUP(X30,'SaleListSMB+Enterprise'!$A:$M,13,FALSE)),"-",$S$3*VLOOKUP(X30,'SaleListSMB+Enterprise'!$A:$M,13,FALSE))) -> - | M30: =IF($J30="-","-",IF(ISERROR(VLOOKUP(Y30,'SaleListSMB+Enterprise'!$A:$M,13,FALSE)),"-",$S$3*VLOOKUP(Y30,'SaleListSMB+Enterprise'!$A:$M,13,FALSE))) -> - | O30: =IF(OR($J30="-",K30="-"),"-",J30*K30*(1-$N30)*IF($D$31="Incl.VAT",1+$D$30,1)) -> - | P30: =IF(OR($J30="-",L30="-"),"-",J30*L30*(1-$N30)*IF($D$31="Incl.VAT",1+$D$30,1)) -> - | Q30: =IF(OR($J30="-",M30="-"),"-",J30*M30*(1-$N30)*IF($D$31="Incl.VAT",1+$D$30,1)) -> - | R30: =IF($J30="-",0,IF(AND($D$29="1 Year",K30<>"-"),O30,IF(AND($D$29="2 Years",L30<>"-"),P30,IF(AND($D$29="3 Years",M30<>"-"),Q30,0)))*IF($D$32>0,$D$32,0)) -> 0 | S30: =IF($J30="-",0,IF(AND($D$29="1 Year",K30<>"-"),O30,IF(AND($D$29="2 Years",L30<>"-"),P30,IF(AND($D$29="3 Years",M30<>"-"),Q30,0)))*IF($D$33>0,$D$33-$D$32,0)) -> 0 | U30: =VLOOKUP(G30,$R$54:$S$66,2,0) -> #N/A | V30: =VLOOKUP(J30,Data!$A$120:$B$137,2) -> #N/A | W30: =CONCATENATE(LEFT($I30,9),"F",IF(OR(U30=$I$60,U30=$I$61,U30=$I$62),"H",Data!$B$107)) -> #N/A | X30: =CONCATENATE(LEFT($I30,9),"D",IF(OR(U30=$I$60,U30=$I$61,U30=$I$62),"H",Data!$B$107)) -> #N/A | Y30: =CONCATENATE(LEFT($I30,9),"T",IF(OR(U30=$I$60,U30=$I$61,U30=$I$62),"H",Data!$B$107)) -> #N/A
C31: Display amounts | D31: Excl.VAT | G31: 8 | H31: =IF(I31<>"",VLOOKUP(U31,$G$54:$H$66,2,0),"") | I31: =IF(ISERROR(U31),"",CONCATENATE("KL",U31,Data!$D$4,V31,Data!$B$100,IF(OR(U31=$I$60,U31=$I$61,U31=$I$62),"H",Data!$B$107))) | J31: =IF(ISERROR(U31),"",IF(U31=$I$64,$D$23,IF(U31=$I$65,$D$24,IF(U31=$I$54,$D$13,IF(U31=$I$55,MAX($D$12,$I$68),MAX(IF(U31=$I$58,$D$14,IF(U31=$I$59,$D$18,IF(U31=$I$56,MAX($D$12,$D$18),IF(U31=$I$60,ROUNDUP($D$19/1.5,0),IF(U31=$I$61,ROUNDUP($D$20/1.1,0),IF(U31=$I$62,$D$21,IF(U31=$I$63,$D$22,IF(U31=$I$66,$D$25,$D$12)))))))),10)))))) | K31: =IF(ISERROR(VLOOKUP(W31,'SaleListSMB+Enterprise'!$A:$M,13,FALSE)),"-",$S$3*VLOOKUP(W31,'SaleListSMB+Enterprise'!$A:$M,13,FALSE)) -> - | L31: =IF($J31="-","-",IF(ISERROR(VLOOKUP(X31,'SaleListSMB+Enterprise'!$A:$M,13,FALSE)),"-",$S$3*VLOOKUP(X31,'SaleListSMB+Enterprise'!$A:$M,13,FALSE))) -> - | M31: =IF($J31="-","-",IF(ISERROR(VLOOKUP(Y31,'SaleListSMB+Enterprise'!$A:$M,13,FALSE)),"-",$S$3*VLOOKUP(Y31,'SaleListSMB+Enterprise'!$A:$M,13,FALSE))) -> - | O31: =IF(OR($J31="-",K31="-"),"-",J31*K31*(1-$N31)*IF($D$31="Incl.VAT",1+$D$30,1)) -> - | P31: =IF(OR($J31="-",L31="-"),"-",J31*L31*(1-$N31)*IF($D$31="Incl.VAT",1+$D$30,1)) -> - | Q31: =IF(OR($J31="-",M31="-"),"-",J31*M31*(1-$N31)*IF($D$31="Incl.VAT",1+$D$30,1)) -> - | R31: =IF($J31="-",0,IF(AND($D$29="1 Year",K31<>"-"),O31,IF(AND($D$29="2 Years",L31<>"-"),P31,IF(AND($D$29="3 Years",M31<>"-"),Q31,0)))*IF($D$32>0,$D$32,0)) -> 0 | S31: =IF($J31="-",0,IF(AND($D$29="1 Year",K31<>"-"),O31,IF(AND($D$29="2 Years",L31<>"-"),P31,IF(AND($D$29="3 Years",M31<>"-"),Q31,0)))*IF($D$33>0,$D$33-$D$32,0)) -> 0 | U31: =VLOOKUP(G31,$R$54:$S$66,2,0) -> #N/A | V31: =VLOOKUP(J31,Data!$A$120:$B$137,2) -> #N/A | W31: =CONCATENATE(LEFT($I31,9),"F",IF(OR(U31=$I$60,U31=$I$61,U31=$I$62),"H",Data!$B$107)) -> #N/A | X31: =CONCATENATE(LEFT($I31,9),"D",IF(OR(U31=$I$60,U31=$I$61,U31=$I$62),"H",Data!$B$107)) -> #N/A | Y31: =CONCATENATE(LEFT($I31,9),"T",IF(OR(U31=$I$60,U31=$I$61,U31=$I$62),"H",Data!$B$107)) -> #N/A
C32: Reseller discount rate | G32: 9 | H32: =IF(I32<>"",VLOOKUP(U32,$G$54:$H$66,2,0),"") | I32: =IF(ISERROR(U32),"",CONCATENATE("KL",U32,Data!$D$4,V32,Data!$B$100,IF(OR(U32=$I$60,U32=$I$61,U32=$I$62),"H",Data!$B$107))) | J32: =IF(ISERROR(U32),"",IF(U32=$I$64,$D$23,IF(U32=$I$65,$D$24,IF(U32=$I$54,$D$13,IF(U32=$I$55,MAX($D$12,$I$68),MAX(IF(U32=$I$58,$D$14,IF(U32=$I$59,$D$18,IF(U32=$I$56,MAX($D$12,$D$18),IF(U32=$I$60,ROUNDUP($D$19/1.5,0),IF(U32=$I$61,ROUNDUP($D$20/1.1,0),IF(U32=$I$62,$D$21,IF(U32=$I$63,$D$22,IF(U32=$I$66,$D$25,$D$12)))))))),10)))))) | K32: =IF(ISERROR(VLOOKUP(W32,'SaleListSMB+Enterprise'!$A:$M,13,FALSE)),"-",$S$3*VLOOKUP(W32,'SaleListSMB+Enterprise'!$A:$M,13,FALSE)) -> - | L32: =IF($J32="-","-",IF(ISERROR(VLOOKUP(X32,'SaleListSMB+Enterprise'!$A:$M,13,FALSE)),"-",$S$3*VLOOKUP(X32,'SaleListSMB+Enterprise'!$A:$M,13,FALSE))) -> - | M32: =IF($J32="-","-",IF(ISERROR(VLOOKUP(Y32,'SaleListSMB+Enterprise'!$A:$M,13,FALSE)),"-",$S$3*VLOOKUP(Y32,'SaleListSMB+Enterprise'!$A:$M,13,FALSE))) -> - | O32: =IF(OR($J32="-",K32="-"),"-",J32*K32*(1-$N32)*IF($D$31="Incl.VAT",1+$D$30,1)) -> - | P32: =IF(OR($J32="-",L32="-"),"-",J32*L32*(1-$N32)*IF($D$31="Incl.VAT",1+$D$30,1)) -> - | Q32: =IF(OR($J32="-",M32="-"),"-",J32*M32*(1-$N32)*IF($D$31="Incl.VAT",1+$D$30,1)) -> - | R32: =IF($J32="-",0,IF(AND($D$29="1 Year",K32<>"-"),O32,IF(AND($D$29="2 Years",L32<>"-"),P32,IF(AND($D$29="3 Years",M32<>"-"),Q32,0)))*IF($D$32>0,$D$32,0)) -> 0 | S32: =IF($J32="-",0,IF(AND($D$29="1 Year",K32<>"-"),O32,IF(AND($D$29="2 Years",L32<>"-"),P32,IF(AND($D$29="3 Years",M32<>"-"),Q32,0)))*IF($D$33>0,$D$33-$D$32,0)) -> 0 | U32: =VLOOKUP(G32,$R$54:$S$66,2,0) -> #N/A | V32: =VLOOKUP(J32,Data!$A$120:$B$137,2) -> #N/A | W32: =CONCATENATE(LEFT($I32,9),"F",IF(OR(U32=$I$60,U32=$I$61,U32=$I$62),"H",Data!$B$107)) -> #N/A | X32: =CONCATENATE(LEFT($I32,9),"D",IF(OR(U32=$I$60,U32=$I$61,U32=$I$62),"H",Data!$B$107)) -> #N/A | Y32: =CONCATENATE(LEFT($I32,9),"T",IF(OR(U32=$I$60,U32=$I$61,U32=$I$62),"H",Data!$B$107)) -> #N/A
C33: Distributor discount rate | H33: Total Option 2: | O33: =SUM(O24:O32) -> 0 | P33: =SUM(P24:P32) -> 0 | Q33: =SUM(Q24:Q32) -> 0 | R33: =SUM(R24:R32) -> 0 | S33: =SUM(S24:S32) -> 0
G34: 12 | H34: Option 3
G35: 1 | H35: =IF(I35<>"",VLOOKUP(U35,$G$54:$H$66,2,0),"") | I35: =IF(ISERROR(U35),"",CONCATENATE("KL",U35,Data!$D$4,V35,Data!$B$100,IF(OR(U35=$I$60,U35=$I$61,U35=$I$62),"H",Data!$B$107))) | J35: =IF(ISERROR(U35),"",IF(U35=$I$64,$D$23,IF(U35=$I$65,$D$24,MAX(IF(U35=$I$54,$D$13,IF(U35=$I$58,$D$14,IF(U35=$I$59,$D$18,IF(U35=$I$56,MAX($D$12,$D$18),IF(U35=$I$60,ROUNDUP($D$19/1.5,0),IF(U35=$I$61,ROUNDUP($D$20/1.1,0),IF(U35=$I$62,$D$21,IF(U35=$I$63,$D$22,IF(U35=$I$66,$D$25,$D$12))))))))),10)))) | K35: =IF(ISERROR(VLOOKUP(W35,'SaleListSMB+Enterprise'!$A:$M,13,FALSE)),"-",$S$3*VLOOKUP(W35,'SaleListSMB+Enterprise'!$A:$M,13,FALSE)) -> - | L35: =IF($J35="-","-",IF(ISERROR(VLOOKUP(X35,'SaleListSMB+Enterprise'!$A:$M,13,FALSE)),"-",$S$3*VLOOKUP(X35,'SaleListSMB+Enterprise'!$A:$M,13,FALSE))) -> - | M35: =IF($J35="-","-",IF(ISERROR(VLOOKUP(Y35,'SaleListSMB+Enterprise'!$A:$M,13,FALSE)),"-",$S$3*VLOOKUP(Y35,'SaleListSMB+Enterprise'!$A:$M,13,FALSE))) -> - | O35: =IF(OR($J35="-",K35="-"),"-",J35*K35*(1-$N35)*IF($D$31="Incl.VAT",1+$D$30,1)) -> - | P35: =IF(OR($J35="-",L35="-"),"-",J35*L35*(1-$N35)*IF($D$31="Incl.VAT",1+$D$30,1)) -> - | Q35: =IF(OR($J35="-",M35="-"),"-",J35*M35*(1-$N35)*IF($D$31="Incl.VAT",1+$D$30,1)) -> - | R35: =IF($J35="-",0,IF(AND($D$29="1 Year",K35<>"-"),O35,IF(AND($D$29="2 Years",L35<>"-"),P35,IF(AND($D$29="3 Years",M35<>"-"),Q35,0)))*IF($D$32>0,$D$32,0)) -> 0 | S35: =IF($J35="-",0,IF(AND($D$29="1 Year",K35<>"-"),O35,IF(AND($D$29="2 Years",L35<>"-"),P35,IF(AND($D$29="3 Years",M35<>"-"),Q35,0)))*IF($D$33>0,$D$33-$D$32,0)) -> 0 | U35: =VLOOKUP(G35,$U$54:$V$66,2,0) -> #N/A | V35: =VLOOKUP(J35,Data!$A$120:$B$137,2) -> #N/A | W35: =CONCATENATE(LEFT($I35,9),"F",IF(OR(U35=$I$60,U35=$I$61,U35=$I$62),"H",Data!$B$107)) -> #N/A | X35: =CONCATENATE(LEFT($I35,9),"D",IF(OR(U35=$I$60,U35=$I$61,U35=$I$62),"H",Data!$B$107)) -> #N/A | Y35: =CONCATENATE(LEFT($I35,9),"T",IF(OR(U35=$I$60,U35=$I$61,U35=$I$62),"H",Data!$B$107)) -> #N/A
G36: 2 | H36: =IF(I36<>"",VLOOKUP(U36,$G$54:$H$66,2,0),"") | I36: =IF(ISERROR(U36),"",CONCATENATE("KL",U36,Data!$D$4,V36,Data!$B$100,IF(OR(U36=$I$60,U36=$I$61,U36=$I$62),"H",Data!$B$107))) | J36: =IF(ISERROR(U36),"",IF(U36=$I$64,$D$23,IF(U36=$I$65,$D$24,MAX(IF(U36=$I$54,$D$13,IF(U36=$I$58,$D$14,IF(U36=$I$59,$D$18,IF(U36=$I$56,MAX($D$12,$D$18),IF(U36=$I$60,ROUNDUP($D$19/1.5,0),IF(U36=$I$61,ROUNDUP($D$20/1.1,0),IF(U36=$I$62,$D$21,IF(U36=$I$63,$D$22,IF(U36=$I$66,$D$25,$D$12))))))))),10)))) | K36: =IF(ISERROR(VLOOKUP(W36,'SaleListSMB+Enterprise'!$A:$M,13,FALSE)),"-",$S$3*VLOOKUP(W36,'SaleListSMB+Enterprise'!$A:$M,13,FALSE)) -> - | L36: =IF($J36="-","-",IF(ISERROR(VLOOKUP(X36,'SaleListSMB+Enterprise'!$A:$M,13,FALSE)),"-",$S$3*VLOOKUP(X36,'SaleListSMB+Enterprise'!$A:$M,13,FALSE))) -> - | M36: =IF($J36="-","-",IF(ISERROR(VLOOKUP(Y36,'SaleListSMB+Enterprise'!$A:$M,13,FALSE)),"-",$S$3*VLOOKUP(Y36,'SaleListSMB+Enterprise'!$A:$M,13,FALSE))) -> - | O36: =IF(OR($J36="-",K36="-"),"-",J36*K36*(1-$N36)*IF($D$31="Incl.VAT",1+$D$30,1)) -> - | P36: =IF(OR($J36="-",L36="-"),"-",J36*L36*(1-$N36)*IF($D$31="Incl.VAT",1+$D$30,1)) -> - | Q36: =IF(OR($J36="-",M36="-"),"-",J36*M36*(1-$N36)*IF($D$31="Incl.VAT",1+$D$30,1)) -> - | R36: =IF($J36="-",0,IF(AND($D$29="1 Year",K36<>"-"),O36,IF(AND($D$29="2 Years",L36<>"-"),P36,IF(AND($D$29="3 Years",M36<>"-"),Q36,0)))*IF($D$32>0,$D$32,0)) -> 0 | S36: =IF($J36="-",0,IF(AND($D$29="1 Year",K36<>"-"),O36,IF(AND($D$29="2 Years",L36<>"-"),P36,IF(AND($D$29="3 Years",M36<>"-"),Q36,0)))*IF($D$33>0,$D$33-$D$32,0)) -> 0 | U36: =VLOOKUP(G36,$U$54:$V$66,2,0) -> #N/A | V36: =VLOOKUP(J36,Data!$A$120:$B$137,2) -> #N/A | W36: =CONCATENATE(LEFT($I36,9),"F",IF(OR(U36=$I$60,U36=$I$61,U36=$I$62),"H",Data!$B$107)) -> #N/A | X36: =CONCATENATE(LEFT($I36,9),"D",IF(OR(U36=$I$60,U36=$I$61,U36=$I$62),"H",Data!$B$107)) -> #N/A | Y36: =CONCATENATE(LEFT($I36,9),"T",IF(OR(U36=$I$60,U36=$I$61,U36=$I$62),"H",Data!$B$107)) -> #N/A
G37: 3 | H37: =IF(I37<>"",VLOOKUP(U37,$G$54:$H$66,2,0),"") | I37: =IF(ISERROR(U37),"",CONCATENATE("KL",U37,Data!$D$4,V37,Data!$B$100,IF(OR(U37=$I$60,U37=$I$61,U37=$I$62),"H",Data!$B$107))) | J37: =IF(ISERROR(U37),"",IF(U37=$I$64,$D$23,IF(U37=$I$65,$D$24,MAX(IF(U37=$I$54,$D$13,IF(U37=$I$58,$D$14,IF(U37=$I$59,$D$18,IF(U37=$I$56,MAX($D$12,$D$18),IF(U37=$I$60,ROUNDUP($D$19/1.5,0),IF(U37=$I$61,ROUNDUP($D$20/1.1,0),IF(U37=$I$62,$D$21,IF(U37=$I$63,$D$22,IF(U37=$I$66,$D$25,$D$12))))))))),10)))) | K37: =IF(ISERROR(VLOOKUP(W37,'SaleListSMB+Enterprise'!$A:$M,13,FALSE)),"-",$S$3*VLOOKUP(W37,'SaleListSMB+Enterprise'!$A:$M,13,FALSE)) -> - | L37: =IF($J37="-","-",IF(ISERROR(VLOOKUP(X37,'SaleListSMB+Enterprise'!$A:$M,13,FALSE)),"-",$S$3*VLOOKUP(X37,'SaleListSMB+Enterprise'!$A:$M,13,FALSE))) -> - | M37: =IF($J37="-","-",IF(ISERROR(VLOOKUP(Y37,'SaleListSMB+Enterprise'!$A:$M,13,FALSE)),"-",$S$3*VLOOKUP(Y37,'SaleListSMB+Enterprise'!$A:$M,13,FALSE))) -> - | O37: =IF(OR($J37="-",K37="-"),"-",J37*K37*(1-$N37)*IF($D$31="Incl.VAT",1+$D$30,1)) -> - | P37: =IF(OR($J37="-",L37="-"),"-",J37*L37*(1-$N37)*IF($D$31="Incl.VAT",1+$D$30,1)) -> - | Q37: =IF(OR($J37="-",M37="-"),"-",J37*M37*(1-$N37)*IF($D$31="Incl.VAT",1+$D$30,1)) -> - | R37: =IF($J37="-",0,IF(AND($D$29="1 Year",K37<>"-"),O37,IF(AND($D$29="2 Years",L37<>"-"),P37,IF(AND($D$29="3 Years",M37<>"-"),Q37,0)))*IF($D$32>0,$D$32,0)) -> 0 | S37: =IF($J37="-",0,IF(AND($D$29="1 Year",K37<>"-"),O37,IF(AND($D$29="2 Years",L37<>"-"),P37,IF(AND($D$29="3 Years",M37<>"-"),Q37,0)))*IF($D$33>0,$D$33-$D$32,0)) -> 0 | U37: =VLOOKUP(G37,$U$54:$V$66,2,0) -> #N/A | V37: =VLOOKUP(J37,Data!$A$120:$B$137,2) -> #N/A | W37: =CONCATENATE(LEFT($I37,9),"F",IF(OR(U37=$I$60,U37=$I$61,U37=$I$62),"H",Data!$B$107)) -> #N/A | X37: =CONCATENATE(LEFT($I37,9),"D",IF(OR(U37=$I$60,U37=$I$61,U37=$I$62),"H",Data!$B$107)) -> #N/A | Y37: =CONCATENATE(LEFT($I37,9),"T",IF(OR(U37=$I$60,U37=$I$61,U37=$I$62),"H",Data!$B$107)) -> #N/A
G38: 4 | H38: =IF(I38<>"",VLOOKUP(U38,$G$54:$H$66,2,0),"") | I38: =IF(ISERROR(U38),"",CONCATENATE("KL",U38,Data!$D$4,V38,Data!$B$100,IF(OR(U38=$I$60,U38=$I$61,U38=$I$62),"H",Data!$B$107))) | J38: =IF(ISERROR(U38),"",IF(U38=$I$64,$D$23,IF(U38=$I$65,$D$24,MAX(IF(U38=$I$54,$D$13,IF(U38=$I$58,$D$14,IF(U38=$I$59,$D$18,IF(U38=$I$56,MAX($D$12,$D$18),IF(U38=$I$60,ROUNDUP($D$19/1.5,0),IF(U38=$I$61,ROUNDUP($D$20/1.1,0),IF(U38=$I$62,$D$21,IF(U38=$I$63,$D$22,IF(U38=$I$66,$D$25,$D$12))))))))),10)))) | K38: =IF(ISERROR(VLOOKUP(W38,'SaleListSMB+Enterprise'!$A:$M,13,FALSE)),"-",$S$3*VLOOKUP(W38,'SaleListSMB+Enterprise'!$A:$M,13,FALSE)) -> - | L38: =IF($J38="-","-",IF(ISERROR(VLOOKUP(X38,'SaleListSMB+Enterprise'!$A:$M,13,FALSE)),"-",$S$3*VLOOKUP(X38,'SaleListSMB+Enterprise'!$A:$M,13,FALSE))) -> - | M38: =IF($J38="-","-",IF(ISERROR(VLOOKUP(Y38,'SaleListSMB+Enterprise'!$A:$M,13,FALSE)),"-",$S$3*VLOOKUP(Y38,'SaleListSMB+Enterprise'!$A:$M,13,FALSE))) -> - | O38: =IF(OR($J38="-",K38="-"),"-",J38*K38*(1-$N38)*IF($D$31="Incl.VAT",1+$D$30,1)) -> - | P38: =IF(OR($J38="-",L38="-"),"-",J38*L38*(1-$N38)*IF($D$31="Incl.VAT",1+$D$30,1)) -> - | Q38: =IF(OR($J38="-",M38="-"),"-",J38*M38*(1-$N38)*IF($D$31="Incl.VAT",1+$D$30,1)) -> - | R38: =IF($J38="-",0,IF(AND($D$29="1 Year",K38<>"-"),O38,IF(AND($D$29="2 Years",L38<>"-"),P38,IF(AND($D$29="3 Years",M38<>"-"),Q38,0)))*IF($D$32>0,$D$32,0)) -> 0 | S38: =IF($J38="-",0,IF(AND($D$29="1 Year",K38<>"-"),O38,IF(AND($D$29="2 Years",L38<>"-"),P38,IF(AND($D$29="3 Years",M38<>"-"),Q38,0)))*IF($D$33>0,$D$33-$D$32,0)) -> 0 | U38: =VLOOKUP(G38,$U$54:$V$66,2,0) -> #N/A | V38: =VLOOKUP(J38,Data!$A$120:$B$137,2) -> #N/A | W38: =CONCATENATE(LEFT($I38,9),"F",IF(OR(U38=$I$60,U38=$I$61,U38=$I$62),"H",Data!$B$107)) -> #N/A | X38: =CONCATENATE(LEFT($I38,9),"D",IF(OR(U38=$I$60,U38=$I$61,U38=$I$62),"H",Data!$B$107)) -> #N/A | Y38: =CONCATENATE(LEFT($I38,9),"T",IF(OR(U38=$I$60,U38=$I$61,U38=$I$62),"H",Data!$B$107)) -> #N/A
G39: 5 | H39: =IF(I39<>"",VLOOKUP(U39,$G$54:$H$66,2,0),"") | I39: =IF(ISERROR(U39),"",CONCATENATE("KL",U39,Data!$D$4,V39,Data!$B$100,IF(OR(U39=$I$60,U39=$I$61,U39=$I$62),"H",Data!$B$107))) | J39: =IF(ISERROR(U39),"",IF(U39=$I$64,$D$23,IF(U39=$I$65,$D$24,MAX(IF(U39=$I$54,$D$13,IF(U39=$I$58,$D$14,IF(U39=$I$59,$D$18,IF(U39=$I$56,MAX($D$12,$D$18),IF(U39=$I$60,ROUNDUP($D$19/1.5,0),IF(U39=$I$61,ROUNDUP($D$20/1.1,0),IF(U39=$I$62,$D$21,IF(U39=$I$63,$D$22,IF(U39=$I$66,$D$25,$D$12))))))))),10)))) | K39: =IF(ISERROR(VLOOKUP(W39,'SaleListSMB+Enterprise'!$A:$M,13,FALSE)),"-",$S$3*VLOOKUP(W39,'SaleListSMB+Enterprise'!$A:$M,13,FALSE)) -> - | L39: =IF($J39="-","-",IF(ISERROR(VLOOKUP(X39,'SaleListSMB+Enterprise'!$A:$M,13,FALSE)),"-",$S$3*VLOOKUP(X39,'SaleListSMB+Enterprise'!$A:$M,13,FALSE))) -> - | M39: =IF($J39="-","-",IF(ISERROR(VLOOKUP(Y39,'SaleListSMB+Enterprise'!$A:$M,13,FALSE)),"-",$S$3*VLOOKUP(Y39,'SaleListSMB+Enterprise'!$A:$M,13,FALSE))) -> - | O39: =IF(OR($J39="-",K39="-"),"-",J39*K39*(1-$N39)*IF($D$31="Incl.VAT",1+$D$30,1)) -> - | P39: =IF(OR($J39="-",L39="-"),"-",J39*L39*(1-$N39)*IF($D$31="Incl.VAT",1+$D$30,1)) -> - | Q39: =IF(OR($J39="-",M39="-"),"-",J39*M39*(1-$N39)*IF($D$31="Incl.VAT",1+$D$30,1)) -> - | R39: =IF($J39="-",0,IF(AND($D$29="1 Year",K39<>"-"),O39,IF(AND($D$29="2 Years",L39<>"-"),P39,IF(AND($D$29="3 Years",M39<>"-"),Q39,0)))*IF($D$32>0,$D$32,0)) -> 0 | S39: =IF($J39="-",0,IF(AND($D$29="1 Year",K39<>"-"),O39,IF(AND($D$29="2 Years",L39<>"-"),P39,IF(AND($D$29="3 Years",M39<>"-"),Q39,0)))*IF($D$33>0,$D$33-$D$32,0)) -> 0 | U39: =VLOOKUP(G39,$U$54:$V$66,2,0) -> #N/A | V39: =VLOOKUP(J39,Data!$A$120:$B$137,2) -> #N/A | W39: =CONCATENATE(LEFT($I39,9),"F",IF(OR(U39=$I$60,U39=$I$61,U39=$I$62),"H",Data!$B$107)) -> #N/A | X39: =CONCATENATE(LEFT($I39,9),"D",IF(OR(U39=$I$60,U39=$I$61,U39=$I$62),"H",Data!$B$107)) -> #N/A | Y39: =CONCATENATE(LEFT($I39,9),"T",IF(OR(U39=$I$60,U39=$I$61,U39=$I$62),"H",Data!$B$107)) -> #N/A
G40: 6 | H40: =IF(I40<>"",VLOOKUP(U40,$G$54:$H$66,2,0),"") | I40: =IF(ISERROR(U40),"",CONCATENATE("KL",U40,Data!$D$4,V40,Data!$B$100,IF(OR(U40=$I$60,U40=$I$61,U40=$I$62),"H",Data!$B$107))) | J40: =IF(ISERROR(U40),"",IF(U40=$I$64,$D$23,IF(U40=$I$65,$D$24,MAX(IF(U40=$I$54,$D$13,IF(U40=$I$58,$D$14,IF(U40=$I$59,$D$18,IF(U40=$I$56,MAX($D$12,$D$18),IF(U40=$I$60,ROUNDUP($D$19/1.5,0),IF(U40=$I$61,ROUNDUP($D$20/1.1,0),IF(U40=$I$62,$D$21,IF(U40=$I$63,$D$22,IF(U40=$I$66,$D$25,$D$12))))))))),10)))) | K40: =IF(ISERROR(VLOOKUP(W40,'SaleListSMB+Enterprise'!$A:$M,13,FALSE)),"-",$S$3*VLOOKUP(W40,'SaleListSMB+Enterprise'!$A:$M,13,FALSE)) -> - | L40: =IF($J40="-","-",IF(ISERROR(VLOOKUP(X40,'SaleListSMB+Enterprise'!$A:$M,13,FALSE)),"-",$S$3*VLOOKUP(X40,'SaleListSMB+Enterprise'!$A:$M,13,FALSE))) -> - | M40: =IF($J40="-","-",IF(ISERROR(VLOOKUP(Y40,'SaleListSMB+Enterprise'!$A:$M,13,FALSE)),"-",$S$3*VLOOKUP(Y40,'SaleListSMB+Enterprise'!$A:$M,13,FALSE))) -> - | O40: =IF(OR($J40="-",K40="-"),"-",J40*K40*(1-$N40)*IF($D$31="Incl.VAT",1+$D$30,1)) -> - | P40: =IF(OR($J40="-",L40="-"),"-",J40*L40*(1-$N40)*IF($D$31="Incl.VAT",1+$D$30,1)) -> - | Q40: =IF(OR($J40="-",M40="-"),"-",J40*M40*(1-$N40)*IF($D$31="Incl.VAT",1+$D$30,1)) -> - | R40: =IF($J40="-",0,IF(AND($D$29="1 Year",K40<>"-"),O40,IF(AND($D$29="2 Years",L40<>"-"),P40,IF(AND($D$29="3 Years",M40<>"-"),Q40,0)))*IF($D$32>0,$D$32,0)) -> 0 | S40: =IF($J40="-",0,IF(AND($D$29="1 Year",K40<>"-"),O40,IF(AND($D$29="2 Years",L40<>"-"),P40,IF(AND($D$29="3 Years",M40<>"-"),Q40,0)))*IF($D$33>0,$D$33-$D$32,0)) -> 0 | U40: =VLOOKUP(G40,$U$54:$V$66,2,0) -> #N/A | V40: =VLOOKUP(J40,Data!$A$120:$B$137,2) -> #N/A | W40: =CONCATENATE(LEFT($I40,9),"F",IF(OR(U40=$I$60,U40=$I$61,U40=$I$62),"H",Data!$B$107)) -> #N/A | X40: =CONCATENATE(LEFT($I40,9),"D",IF(OR(U40=$I$60,U40=$I$61,U40=$I$62),"H",Data!$B$107)) -> #N/A | Y40: =CONCATENATE(LEFT($I40,9),"T",IF(OR(U40=$I$60,U40=$I$61,U40=$I$62),"H",Data!$B$107)) -> #N/A
G41: 7 | H41: =IF(I41<>"",VLOOKUP(U41,$G$54:$H$66,2,0),"") | I41: =IF(ISERROR(U41),"",CONCATENATE("KL",U41,Data!$D$4,V41,Data!$B$100,IF(OR(U41=$I$60,U41=$I$61,U41=$I$62),"H",Data!$B$107))) | J41: =IF(ISERROR(U41),"",IF(U41=$I$64,$D$23,IF(U41=$I$65,$D$24,MAX(IF(U41=$I$54,$D$13,IF(U41=$I$58,$D$14,IF(U41=$I$59,$D$18,IF(U41=$I$56,MAX($D$12,$D$18),IF(U41=$I$60,ROUNDUP($D$19/1.5,0),IF(U41=$I$61,ROUNDUP($D$20/1.1,0),IF(U41=$I$62,$D$21,IF(U41=$I$63,$D$22,IF(U41=$I$66,$D$25,$D$12))))))))),10)))) | K41: =IF(ISERROR(VLOOKUP(W41,'SaleListSMB+Enterprise'!$A:$M,13,FALSE)),"-",$S$3*VLOOKUP(W41,'SaleListSMB+Enterprise'!$A:$M,13,FALSE)) -> - | L41: =IF($J41="-","-",IF(ISERROR(VLOOKUP(X41,'SaleListSMB+Enterprise'!$A:$M,13,FALSE)),"-",$S$3*VLOOKUP(X41,'SaleListSMB+Enterprise'!$A:$M,13,FALSE))) -> - | M41: =IF($J41="-","-",IF(ISERROR(VLOOKUP(Y41,'SaleListSMB+Enterprise'!$A:$M,13,FALSE)),"-",$S$3*VLOOKUP(Y41,'SaleListSMB+Enterprise'!$A:$M,13,FALSE))) -> - | O41: =IF(OR($J41="-",K41="-"),"-",J41*K41*(1-$N41)*IF($D$31="Incl.VAT",1+$D$30,1)) -> - | P41: =IF(OR($J41="-",L41="-"),"-",J41*L41*(1-$N41)*IF($D$31="Incl.VAT",1+$D$30,1)) -> - | Q41: =IF(OR($J41="-",M41="-"),"-",J41*M41*(1-$N41)*IF($D$31="Incl.VAT",1+$D$30,1)) -> - | R41: =IF($J41="-",0,IF(AND($D$29="1 Year",K41<>"-"),O41,IF(AND($D$29="2 Years",L41<>"-"),P41,IF(AND($D$29="3 Years",M41<>"-"),Q41,0)))*IF($D$32>0,$D$32,0)) -> 0 | S41: =IF($J41="-",0,IF(AND($D$29="1 Year",K41<>"-"),O41,IF(AND($D$29="2 Years",L41<>"-"),P41,IF(AND($D$29="3 Years",M41<>"-"),Q41,0)))*IF($D$33>0,$D$33-$D$32,0)) -> 0 | U41: =VLOOKUP(G41,$U$54:$V$66,2,0) -> #N/A | V41: =VLOOKUP(J41,Data!$A$120:$B$137,2) -> #N/A | W41: =CONCATENATE(LEFT($I41,9),"F",IF(OR(U41=$I$60,U41=$I$61,U41=$I$62),"H",Data!$B$107)) -> #N/A | X41: =CONCATENATE(LEFT($I41,9),"D",IF(OR(U41=$I$60,U41=$I$61,U41=$I$62),"H",Data!$B$107)) -> #N/A | Y41: =CONCATENATE(LEFT($I41,9),"T",IF(OR(U41=$I$60,U41=$I$61,U41=$I$62),"H",Data!$B$107)) -> #N/A
G42: 8 | H42: =IF(I42<>"",VLOOKUP(U42,$G$54:$H$66,2,0),"") | I42: =IF(ISERROR(U42),"",CONCATENATE("KL",U42,Data!$D$4,V42,Data!$B$100,IF(OR(U42=$I$60,U42=$I$61,U42=$I$62),"H",Data!$B$107))) | J42: =IF(ISERROR(U42),"",IF(U42=$I$64,$D$23,IF(U42=$I$65,$D$24,MAX(IF(U42=$I$54,$D$13,IF(U42=$I$58,$D$14,IF(U42=$I$59,$D$18,IF(U42=$I$56,MAX($D$12,$D$18),IF(U42=$I$60,ROUNDUP($D$19/1.5,0),IF(U42=$I$61,ROUNDUP($D$20/1.1,0),IF(U42=$I$62,$D$21,IF(U42=$I$63,$D$22,IF(U42=$I$66,$D$25,$D$12))))))))),10)))) | K42: =IF(ISERROR(VLOOKUP(W42,'SaleListSMB+Enterprise'!$A:$M,13,FALSE)),"-",$S$3*VLOOKUP(W42,'SaleListSMB+Enterprise'!$A:$M,13,FALSE)) -> - | L42: =IF($J42="-","-",IF(ISERROR(VLOOKUP(X42,'SaleListSMB+Enterprise'!$A:$M,13,FALSE)),"-",$S$3*VLOOKUP(X42,'SaleListSMB+Enterprise'!$A:$M,13,FALSE))) -> - | M42: =IF($J42="-","-",IF(ISERROR(VLOOKUP(Y42,'SaleListSMB+Enterprise'!$A:$M,13,FALSE)),"-",$S$3*VLOOKUP(Y42,'SaleListSMB+Enterprise'!$A:$M,13,FALSE))) -> - | O42: =IF(OR($J42="-",K42="-"),"-",J42*K42*(1-$N42)*IF($D$31="Incl.VAT",1+$D$30,1)) -> - | P42: =IF(OR($J42="-",L42="-"),"-",J42*L42*(1-$N42)*IF($D$31="Incl.VAT",1+$D$30,1)) -> - | Q42: =IF(OR($J42="-",M42="-"),"-",J42*M42*(1-$N42)*IF($D$31="Incl.VAT",1+$D$30,1)) -> - | R42: =IF($J42="-",0,IF(AND($D$29="1 Year",K42<>"-"),O42,IF(AND($D$29="2 Years",L42<>"-"),P42,IF(AND($D$29="3 Years",M42<>"-"),Q42,0)))*IF($D$32>0,$D$32,0)) -> 0 | S42: =IF($J42="-",0,IF(AND($D$29="1 Year",K42<>"-"),O42,IF(AND($D$29="2 Years",L42<>"-"),P42,IF(AND($D$29="3 Years",M42<>"-"),Q42,0)))*IF($D$33>0,$D$33-$D$32,0)) -> 0 | U42: =VLOOKUP(G42,$U$54:$V$66,2,0) -> #N/A | V42: =VLOOKUP(J42,Data!$A$120:$B$137,2) -> #N/A | W42: =CONCATENATE(LEFT($I42,9),"F",IF(OR(U42=$I$60,U42=$I$61,U42=$I$62),"H",Data!$B$107)) -> #N/A | X42: =CONCATENATE(LEFT($I42,9),"D",IF(OR(U42=$I$60,U42=$I$61,U42=$I$62),"H",Data!$B$107)) -> #N/A | Y42: =CONCATENATE(LEFT($I42,9),"T",IF(OR(U42=$I$60,U42=$I$61,U42=$I$62),"H",Data!$B$107)) -> #N/A
H43: Total Option 3: | O43: =SUM(O35:O42) -> 0 | P43: =SUM(P35:P42) -> 0 | Q43: =SUM(Q35:Q42) -> 0 | R43: =SUM(R35:R42) -> 0 | S43: =SUM(S35:S42) -> 0
H44: Option 4
G45: 1 | H45: =IF(I45<>"",VLOOKUP(U45,$G$54:$H$66,2,0),"") | I45: =IF(ISERROR(U45),"",CONCATENATE("KL",U45,Data!$D$4,V45,Data!$B$100,Data!$B$107)) | J45: =IF(ISERROR(U45),"",IF(U45=$I$64,$D$23,IF(U45=$I$65,$D$24,MAX(IF(U45=$I$57,MAX($D$12,$D$18,ROUNDUP($D$19/1.5,0),ROUNDUP($D$20/1.1,0),$D$21),IF(U45=$I$63,$D$22,IF(U45=$I$66,$D$25,$D$12))),10)))) | K45: =IF(ISERROR(VLOOKUP(W45,'SaleListSMB+Enterprise'!$A:$M,13,FALSE)),"-",$S$3*VLOOKUP(W45,'SaleListSMB+Enterprise'!$A:$M,13,FALSE)) -> - | L45: =IF($J45="-","-",IF(ISERROR(VLOOKUP(X45,'SaleListSMB+Enterprise'!$A:$M,13,FALSE)),"-",$S$3*VLOOKUP(X45,'SaleListSMB+Enterprise'!$A:$M,13,FALSE))) -> - | M45: =IF($J45="-","-",IF(ISERROR(VLOOKUP(Y45,'SaleListSMB+Enterprise'!$A:$M,13,FALSE)),"-",$S$3*VLOOKUP(Y45,'SaleListSMB+Enterprise'!$A:$M,13,FALSE))) -> - | O45: =IF(OR($J45="-",K45="-"),"-",J45*K45*(1-$N45)*IF($D$31="Incl.VAT",1+$D$30,1)) -> - | P45: =IF(OR($J45="-",L45="-"),"-",J45*L45*(1-$N45)*IF($D$31="Incl.VAT",1+$D$30,1)) -> - | Q45: =IF(OR($J45="-",M45="-"),"-",J45*M45*(1-$N45)*IF($D$31="Incl.VAT",1+$D$30,1)) -> - | R45: =IF($J45="-",0,IF(AND($D$29="1 Year",K45<>"-"),O45,IF(AND($D$29="2 Years",L45<>"-"),P45,IF(AND($D$29="3 Years",M45<>"-"),Q45,0)))*IF($D$32>0,$D$32,0)) -> 0 | S45: =IF($J45="-",0,IF(AND($D$29="1 Year",K45<>"-"),O45,IF(AND($D$29="2 Years",L45<>"-"),P45,IF(AND($D$29="3 Years",M45<>"-"),Q45,0)))*IF($D$33>0,$D$33-$D$32,0)) -> 0 | U45: =VLOOKUP(G45,$X$54:$Y$66,2,0) -> #N/A | V45: =VLOOKUP(J45,Data!$A$120:$B$137,2) -> #N/A | W45: =CONCATENATE(LEFT($I45,9),"F",Data!$B$107) -> #N/A | X45: =CONCATENATE(LEFT($I45,9),"D",Data!$B$107) -> #N/A | Y45: =CONCATENATE(LEFT($I45,9),"T",Data!$B$107) -> #N/A
G46: 2 | H46: =IF(I46<>"",VLOOKUP(U46,$G$54:$H$66,2,0),"") | I46: =IF(ISERROR(U46),"",CONCATENATE("KL",U46,Data!$D$4,V46,Data!$B$100,Data!$B$107)) | J46: =IF(ISERROR(U46),"",IF(U46=$I$64,$D$23,IF(U46=$I$65,$D$24,MAX(IF(U46=$I$57,MAX($D$12,$D$18,ROUNDUP($D$19/1.5,0),ROUNDUP($D$20/1.1,0),$D$21),IF(U46=$I$63,$D$22,IF(U46=$I$66,$D$25,$D$12))),10)))) | K46: =IF(ISERROR(VLOOKUP(W46,'SaleListSMB+Enterprise'!$A:$M,13,FALSE)),"-",$S$3*VLOOKUP(W46,'SaleListSMB+Enterprise'!$A:$M,13,FALSE)) -> - | L46: =IF($J46="-","-",IF(ISERROR(VLOOKUP(X46,'SaleListSMB+Enterprise'!$A:$M,13,FALSE)),"-",$S$3*VLOOKUP(X46,'SaleListSMB+Enterprise'!$A:$M,13,FALSE))) -> - | M46: =IF($J46="-","-",IF(ISERROR(VLOOKUP(Y46,'SaleListSMB+Enterprise'!$A:$M,13,FALSE)),"-",$S$3*VLOOKUP(Y46,'SaleListSMB+Enterprise'!$A:$M,13,FALSE))) -> - | O46: =IF(OR($J46="-",K46="-"),"-",J46*K46*(1-$N46)*IF($D$31="Incl.VAT",1+$D$30,1)) -> - | P46: =IF(OR($J46="-",L46="-"),"-",J46*L46*(1-$N46)*IF($D$31="Incl.VAT",1+$D$30,1)) -> - | Q46: =IF(OR($J46="-",M46="-"),"-",J46*M46*(1-$N46)*IF($D$31="Incl.VAT",1+$D$30,1)) -> - | R46: =IF($J46="-",0,IF(AND($D$29="1 Year",K46<>"-"),O46,IF(AND($D$29="2 Years",L46<>"-"),P46,IF(AND($D$29="3 Years",M46<>"-"),Q46,0)))*IF($D$32>0,$D$32,0)) -> 0 | S46: =IF($J46="-",0,IF(AND($D$29="1 Year",K46<>"-"),O46,IF(AND($D$29="2 Years",L46<>"-"),P46,IF(AND($D$29="3 Years",M46<>"-"),Q46,0)))*IF($D$33>0,$D$33-$D$32,0)) -> 0 | U46: =VLOOKUP(G46,$X$54:$Y$66,2,0) -> #N/A | V46: =VLOOKUP(J46,Data!$A$120:$B$137,2) -> #N/A | W46: =CONCATENATE(LEFT($I46,9),"F",Data!$B$107) -> #N/A | X46: =CONCATENATE(LEFT($I46,9),"D",Data!$B$107) -> #N/A | Y46: =CONCATENATE(LEFT($I46,9),"T",Data!$B$107) -> #N/A
G47: 3 | H47: =IF(I47<>"",VLOOKUP(U47,$G$54:$H$66,2,0),"") | I47: =IF(ISERROR(U47),"",CONCATENATE("KL",U47,Data!$D$4,V47,Data!$B$100,Data!$B$107)) | J47: =IF(ISERROR(U47),"",IF(U47=$I$64,$D$23,IF(U47=$I$65,$D$24,MAX(IF(U47=$I$57,MAX($D$12,$D$18,ROUNDUP($D$19/1.5,0),ROUNDUP($D$20/1.1,0),$D$21),IF(U47=$I$63,$D$22,IF(U47=$I$66,$D$25,$D$12))),10)))) | K47: =IF(ISERROR(VLOOKUP(W47,'SaleListSMB+Enterprise'!$A:$M,13,FALSE)),"-",$S$3*VLOOKUP(W47,'SaleListSMB+Enterprise'!$A:$M,13,FALSE)) -> - | L47: =IF($J47="-","-",IF(ISERROR(VLOOKUP(X47,'SaleListSMB+Enterprise'!$A:$M,13,FALSE)),"-",$S$3*VLOOKUP(X47,'SaleListSMB+Enterprise'!$A:$M,13,FALSE))) -> - | M47: =IF($J47="-","-",IF(ISERROR(VLOOKUP(Y47,'SaleListSMB+Enterprise'!$A:$M,13,FALSE)),"-",$S$3*VLOOKUP(Y47,'SaleListSMB+Enterprise'!$A:$M,13,FALSE))) -> - | O47: =IF(OR($J47="-",K47="-"),"-",J47*K47*(1-$N47)*IF($D$31="Incl.VAT",1+$D$30,1)) -> - | P47: =IF(OR($J47="-",L47="-"),"-",J47*L47*(1-$N47)*IF($D$31="Incl.VAT",1+$D$30,1)) -> - | Q47: =IF(OR($J47="-",M47="-"),"-",J47*M47*(1-$N47)*IF($D$31="Incl.VAT",1+$D$30,1)) -> - | R47: =IF($J47="-",0,IF(AND($D$29="1 Year",K47<>"-"),O47,IF(AND($D$29="2 Years",L47<>"-"),P47,IF(AND($D$29="3 Years",M47<>"-"),Q47,0)))*IF($D$32>0,$D$32,0)) -> 0 | S47: =IF($J47="-",0,IF(AND($D$29="1 Year",K47<>"-"),O47,IF(AND($D$29="2 Years",L47<>"-"),P47,IF(AND($D$29="3 Years",M47<>"-"),Q47,0)))*IF($D$33>0,$D$33-$D$32,0)) -> 0 | U47: =VLOOKUP(G47,$X$54:$Y$66,2,0) -> #N/A | V47: =VLOOKUP(J47,Data!$A$120:$B$137,2) -> #N/A | W47: =CONCATENATE(LEFT($I47,9),"F",Data!$B$107) -> #N/A | X47: =CONCATENATE(LEFT($I47,9),"D",Data!$B$107) -> #N/A | Y47: =CONCATENATE(LEFT($I47,9),"T",Data!$B$107) -> #N/A
G48: 4 | H48: =IF(I48<>"",VLOOKUP(U48,$G$54:$H$66,2,0),"") | I48: =IF(ISERROR(U48),"",CONCATENATE("KL",U48,Data!$D$4,V48,Data!$B$100,Data!$B$107)) | J48: =IF(ISERROR(U48),"",IF(U48=$I$64,$D$23,IF(U48=$I$65,$D$24,MAX(IF(U48=$I$57,MAX($D$12,$D$18,ROUNDUP($D$19/1.5,0),ROUNDUP($D$20/1.1,0),$D$21),IF(U48=$I$63,$D$22,IF(U48=$I$66,$D$25,$D$12))),10)))) | K48: =IF(ISERROR(VLOOKUP(W48,'SaleListSMB+Enterprise'!$A:$M,13,FALSE)),"-",$S$3*VLOOKUP(W48,'SaleListSMB+Enterprise'!$A:$M,13,FALSE)) -> - | L48: =IF($J48="-","-",IF(ISERROR(VLOOKUP(X48,'SaleListSMB+Enterprise'!$A:$M,13,FALSE)),"-",$S$3*VLOOKUP(X48,'SaleListSMB+Enterprise'!$A:$M,13,FALSE))) -> - | M48: =IF($J48="-","-",IF(ISERROR(VLOOKUP(Y48,'SaleListSMB+Enterprise'!$A:$M,13,FALSE)),"-",$S$3*VLOOKUP(Y48,'SaleListSMB+Enterprise'!$A:$M,13,FALSE))) -> - | O48: =IF(OR($J48="-",K48="-"),"-",J48*K48*(1-$N48)*IF($D$31="Incl.VAT",1+$D$30,1)) -> - | P48: =IF(OR($J48="-",L48="-"),"-",J48*L48*(1-$N48)*IF($D$31="Incl.VAT",1+$D$30,1)) -> - | Q48: =IF(OR($J48="-",M48="-"),"-",J48*M48*(1-$N48)*IF($D$31="Incl.VAT",1+$D$30,1)) -> - | R48: =IF($J48="-",0,IF(AND($D$29="1 Year",K48<>"-"),O48,IF(AND($D$29="2 Years",L48<>"-"),P48,IF(AND($D$29="3 Years",M48<>"-"),Q48,0)))*IF($D$32>0,$D$32,0)) -> 0 | S48: =IF($J48="-",0,IF(AND($D$29="1 Year",K48<>"-"),O48,IF(AND($D$29="2 Years",L48<>"-"),P48,IF(AND($D$29="3 Years",M48<>"-"),Q48,0)))*IF($D$33>0,$D$33-$D$32,0)) -> 0 | U48: =VLOOKUP(G48,$X$54:$Y$66,2,0) -> #N/A | V48: =VLOOKUP(J48,Data!$A$120:$B$137,2) -> #N/A | W48: =CONCATENATE(LEFT($I48,9),"F",Data!$B$107) -> #N/A | X48: =CONCATENATE(LEFT($I48,9),"D",Data!$B$107) -> #N/A | Y48: =CONCATENATE(LEFT($I48,9),"T",Data!$B$107) -> #N/A
G49: 5 | H49: =IF(I49<>"",VLOOKUP(U49,$G$54:$H$66,2,0),"") | I49: =IF(ISERROR(U49),"",CONCATENATE("KL",U49,Data!$D$4,V49,Data!$B$100,Data!$B$107)) | J49: =IF(ISERROR(U49),"",IF(U49=$I$64,$D$23,IF(U49=$I$65,$D$24,MAX(IF(U49=$I$57,MAX($D$12,$D$18,ROUNDUP($D$19/1.5,0),ROUNDUP($D$20/1.1,0),$D$21),IF(U49=$I$63,$D$22,IF(U49=$I$66,$D$25,$D$12))),10)))) | K49: =IF(ISERROR(VLOOKUP(W49,'SaleListSMB+Enterprise'!$A:$M,13,FALSE)),"-",$S$3*VLOOKUP(W49,'SaleListSMB+Enterprise'!$A:$M,13,FALSE)) -> - | L49: =IF($J49="-","-",IF(ISERROR(VLOOKUP(X49,'SaleListSMB+Enterprise'!$A:$M,13,FALSE)),"-",$S$3*VLOOKUP(X49,'SaleListSMB+Enterprise'!$A:$M,13,FALSE))) -> - | M49: =IF($J49="-","-",IF(ISERROR(VLOOKUP(Y49,'SaleListSMB+Enterprise'!$A:$M,13,FALSE)),"-",$S$3*VLOOKUP(Y49,'SaleListSMB+Enterprise'!$A:$M,13,FALSE))) -> - | O49: =IF(OR($J49="-",K49="-"),"-",J49*K49*(1-$N49)*IF($D$31="Incl.VAT",1+$D$30,1)) -> - | P49: =IF(OR($J49="-",L49="-"),"-",J49*L49*(1-$N49)*IF($D$31="Incl.VAT",1+$D$30,1)) -> - | Q49: =IF(OR($J49="-",M49="-"),"-",J49*M49*(1-$N49)*IF($D$31="Incl.VAT",1+$D$30,1)) -> - | R49: =IF($J49="-",0,IF(AND($D$29="1 Year",K49<>"-"),O49,IF(AND($D$29="2 Years",L49<>"-"),P49,IF(AND($D$29="3 Years",M49<>"-"),Q49,0)))*IF($D$32>0,$D$32,0)) -> 0 | S49: =IF($J49="-",0,IF(AND($D$29="1 Year",K49<>"-"),O49,IF(AND($D$29="2 Years",L49<>"-"),P49,IF(AND($D$29="3 Years",M49<>"-"),Q49,0)))*IF($D$33>0,$D$33-$D$32,0)) -> 0 | U49: =VLOOKUP(G49,$X$54:$Y$66,2,0) -> #N/A | V49: =VLOOKUP(J49,Data!$A$120:$B$137,2) -> #N/A | W49: =CONCATENATE(LEFT($I49,9),"F",Data!$B$107) -> #N/A | X49: =CONCATENATE(LEFT($I49,9),"D",Data!$B$107) -> #N/A | Y49: =CONCATENATE(LEFT($I49,9),"T",Data!$B$107) -> #N/A
H50: Total Option 4: | O50: =SUM(O45:O49) -> 0 | P50: =SUM(P45:P49) -> 0 | Q50: =SUM(Q45:Q49) -> 0 | R50: =SUM(R45:R49) -> 0 | S50: =SUM(S45:S49) -> 0 | U50: =IF(T50<>"",$I54,"")
U51: =IF(T51<>"",$I55,"")
G52: =I59 -> 9121
G53: =I60 -> 4313 | H53: Product Name | I53: Product Code \ Options | J53: I | K53: II | L53: III | M53: IV | N53: AccS - I | O53: # - I | P53: Code - I | Q53: AccS - II | R53: # - II | S53: Code - II | T53: AccS - III | U53: # - III | V53: Code - III | W53: AccS - IV | X53: # - IV | Y53: Code - IV
G54: =I54 -> 4861 | H54: Kaspersky Endpoint Security for Business - Core | I54: 4861 | J54: =IF(AND($D$13>0,$D$15<=0,$D$16<>"+",$D$17<>"+"),1,0) -> 0 | N54: =J54 -> 0 | O54: =IF(J54<>0,N54,"") | P54: =IF(O54<>"",$I54,"") | Q54: =K54 -> 0 | R54: =IF(K54<>0,Q54,"") | S54: =IF(R54<>"",$I54,"") | T54: =L54 -> 0 | U54: =IF(L54<>0,T54,"") | V54: =IF(U54<>"",$I54,"") | W54: =M54 -> 0 | X54: =IF(M54<>0,W54,"") | Y54: =IF(X54<>"",$I54,"")
G55: =I55 -> 4863 | H55: Kaspersky Endpoint Security for Business - Select | I55: 4863 | K55: =IF(AND($D$12>0,$D$17<>"+"),1,0) -> 0 | N55: =J55+N54 -> 0 | O55: =IF(J55<>0,N55,"") | P55: =IF(O55<>"",I55,"") | Q55: =K55+Q54 -> 0 | R55: =IF(K55<>0,Q55,"") | S55: =IF(R55<>"",$I55,"") | T55: =L55+T54 -> 0 | U55: =IF(L55<>0,T55,"") | V55: =IF(U55<>"",$I55,"") | W55: =M55+W54 -> 0 | X55: =IF(M55<>0,W55,"") | Y55: =IF(X55<>"",$I55,"")
G56: =I56 -> 4867 | H56: Kaspersky Endpoint Security for Business - Advanced | I56: 4867 | L56: =IF(AND($D$12>0,OR($D$17="+",$D$18>0)),1,0) -> 0 | N56: =J56+N55 -> 0 | O56: =IF(J56<>0,N56,"") | P56: =IF(O56<>"",I56,"") | Q56: =K56+Q55 -> 0 | R56: =IF(K56<>0,Q56,"") | S56: =IF(R56<>"",$I56,"") | T56: =L56+T55 -> 0 | U56: =IF(L56<>0,T56,"") | V56: =IF(U56<>"",$I56,"") | W56: =M56+W55 -> 0 | X56: =IF(M56<>0,W56,"") | Y56: =IF(X56<>"",$I56,"")
G57: =I57 -> 4869 | H57: Kaspersky Total Security for Business | I57: 4869 | M57: =IF(AND(OR(D$12>0,$D$18>0),OR($D$19>0,$D$20>0,$D$21>0)),1,0) -> 0 | N57: =J57+N56 -> 0 | O57: =IF(J57<>0,N57,"") | P57: =IF(O57<>"",I57,"") | Q57: =K57+Q56 -> 0 | R57: =IF(K57<>0,Q57,"") | S57: =IF(R57<>"",$I57,"") | T57: =L57+T56 -> 0 | U57: =IF(L57<>0,T57,"") | V57: =IF(U57<>"",$I57,"") | W57: =M57+W56 -> 0 | X57: =IF(M57<>0,W57,"") | Y57: =IF(X57<>"",$I57,"")
G58: =I58 -> 4025 | H58: Kaspersky Security for Mobile | I58: 4025 | J58: =IF(AND($D$14>0,$D$15<=0,$D$16<>"+",$D$17<>"+"),1,0) -> 0 | N58: =J58+N57 -> 0 | O58: =IF(J58<>0,N58,"") | P58: =IF(O58<>"",I58,"") | Q58: =K58+Q57 -> 0 | R58: =IF(K58<>0,Q58,"") | S58: =IF(R58<>"",$I58,"") | T58: =L58+T57 -> 0 | U58: =IF(L58<>0,T58,"") | V58: =IF(U58<>"",$I58,"") | W58: =M58+W57 -> 0 | X58: =IF(M58<>0,W58,"") | Y58: =IF(X58<>"",$I58,"")
G59: =I59 -> 9121 | H59: Kaspersky Systems Management | I59: 9121 | J59: =IF(AND($D$15<=0,$D$16<>"+",$D$17<>"+",$D$18>0),1,0) -> 0 | K59: =IF(AND($D$17<>"+",$D$18>0,$K$55=1),1,0) -> 0 | N59: =J59+N58 -> 0 | O59: =IF(J59<>0,N59,"") | P59: =IF(O59<>"",I59,"") | Q59: =K59+Q58 -> 0 | R59: =IF(K59<>0,Q59,"") | S59: =IF(R59<>"",$I59,"") | T59: =L59+T58 -> 0 | U59: =IF(L59<>0,T59,"") | V59: =IF(U59<>"",$I59,"") | W59: =M59+W58 -> 0 | X59: =IF(M59<>0,W59,"") | Y59: =IF(X59<>"",$I59,"")
G60: =I60 -> 4313 | H60: Kaspersky Security for Mail Server | I60: 4313 | J60: =IF(AND($D$15<=0,$D$19>0,OR(SUM($K$55:$M$57)=0,SUM($J$54:$J$59)>0)),1,0) -> 0 | K60: =IF(AND($D$19>0,$K$55=1),1,0) -> 0 | L60: =IF(AND($D$19>0,$L$56=1),1,0) -> 0 | N60: =J60+N59 -> 0 | O60: =IF(J60<>0,N60,"") | P60: =IF(O60<>"",I60,"") | Q60: =K60+Q59 -> 0 | R60: =IF(K60<>0,Q60,"") | S60: =IF(R60<>"",$I60,"") | T60: =L60+T59 -> 0 | U60: =IF(L60<>0,T60,"") | V60: =IF(U60<>"",$I60,"") | W60: =M60+W59 -> 0 | X60: =IF(M60<>0,W60,"") | Y60: =IF(X60<>"",$I60,"")
G61: =I61 -> 4413 | H61: Kaspersky Security for Internet Gateway | I61: 4413 | J61: =IF(AND($D$15<=0,$D$20>0,OR(SUM($K$55:$M$57)=0,SUM($J$54:$J$59)>0)),1,0) -> 0 | K61: =IF(AND($D$20>0,$K$55=1),1,0) -> 0 | L61: =IF(AND($D$20>0,$L$56=1),1,0) -> 0 | N61: =J61+N60 -> 0 | O61: =IF(J61<>0,N61,"") | P61: =IF(O61<>"",I61,"") | Q61: =K61+Q60 -> 0 | R61: =IF(K61<>0,Q61,"") | S61: =IF(R61<>"",$I61,"") | T61: =L61+T60 -> 0 | U61: =IF(L61<>0,T61,"") | V61: =IF(U61<>"",$I61,"") | W61: =M61+W60 -> 0 | X61: =IF(M61<>0,W61,"") | Y61: =IF(X61<>"",$I61,"")
G62: =I62 -> 4323 | H62: Kaspersky Security for Collaboration | I62: 4323 | J62: =IF(AND($D$15<=0,$D$21>0,OR(SUM($K$55:$M$57)=0,SUM($J$54:$J$59)>0)),1,0) -> 0 | K62: =IF(AND($D$21>0,$K$55=1),1,0) -> 0 | L62: =IF(AND($D$21>0,$L$56=1),1,0) -> 0 | N62: =J62+N61 -> 0 | O62: =IF(J62<>0,N62,"") | P62: =IF(O62<>"",I62,"") | Q62: =K62+Q61 -> 0 | R62: =IF(K62<>0,Q62,"") | S62: =IF(R62<>"",$I62,"") | T62: =L62+T61 -> 0 | U62: =IF(L62<>0,T62,"") | V62: =IF(U62<>"",$I62,"") | W62: =M62+W61 -> 0 | X62: =IF(M62<>0,W62,"") | Y62: =IF(X62<>"",$I62,"")
G63: =I63 -> 4151 | H63: Kaspersky Security for Virtualization, Desktop | I63: 4151 | J63: =IF(AND($D22>0,OR(SUM($K$55:$M$57)=0,SUM($J$54:$J$59)>0)),1,0) -> 0 | K63: =IF(AND($D22>0,$K$55=1),1,0) -> 0 | L63: =IF(AND($D22>0,$L$56=1),1,0) -> 0 | M63: =IF(AND($D22>0,$M$57=1),1,0) -> 0 | N63: =J63+N62 -> 0 | O63: =IF(J63<>0,N63,"") | P63: =IF(O63<>"",I63,"") | Q63: =K63+Q62 -> 0 | R63: =IF(K63<>0,Q63,"") | S63: =IF(R63<>"",$I63,"") | T63: =L63+T62 -> 0 | U63: =IF(L63<>0,T63,"") | V63: =IF(U63<>"",$I63,"") | W63: =M63+W62 -> 0 | X63: =IF(M63<>0,W63,"") | Y63: =IF(X63<>"",$I63,"")
G64: =I64 -> 4251 | H64: Kaspersky Security for Virtualization, Server | I64: 4251 | J64: =IF(AND($D23>0,OR(SUM($K$55:$M$57)=0,SUM($J$54:$J$59)>0)),1,0) -> 0 | K64: =IF(AND($D23>0,$K$55=1),1,0) -> 0 | L64: =IF(AND($D23>0,$L$56=1),1,0) -> 0 | M64: =IF(AND($D23>0,$M$57=1),1,0) -> 0 | N64: =J64+N63 -> 0 | O64: =IF(J64<>0,N64,"") | P64: =IF(O64<>"",I64,"") | Q64: =K64+Q63 -> 0 | R64: =IF(K64<>0,Q64,"") | S64: =IF(R64<>"",$I64,"") | T64: =L64+T63 -> 0 | U64: =IF(L64<>0,T64,"") | V64: =IF(U64<>"",$I64,"") | W64: =M64+W63 -> 0 | X64: =IF(M64<>0,W64,"") | Y64: =IF(X64<>"",$I64,"")
G65: =I65 -> 4551 | H65: Kaspersky Security for Virtualization, Core | I65: 4551 | J65: =IF(AND($D24>0,OR(SUM($K$55:$M$57)=0,SUM($J$54:$J$59)>0)),1,0) -> 0 | K65: =IF(AND($D24>0,$K$55=1),1,0) -> 0 | L65: =IF(AND($D24>0,$L$56=1),1,0) -> 0 | M65: =IF(AND($D24>0,$M$57=1),1,0) -> 0 | N65: =J65+N64 -> 0 | O65: =IF(J65<>0,N65,"") | P65: =IF(O65<>"",I65,"") | Q65: =K65+Q64 -> 0 | R65: =IF(K65<>0,Q65,"") | S65: =IF(R65<>"",$I65,"") | T65: =L65+T64 -> 0 | U65: =IF(L65<>0,T65,"") | V65: =IF(U65<>"",$I65,"") | W65: =M65+W64 -> 0 | X65: =IF(M65<>0,W65,"") | Y65: =IF(X65<>"",$I65,"")
G66: =I66 -> 4221 | H66: Kaspersky Security for Storage | I66: 4221 | J66: =IF(AND($D25>0,OR(SUM($K$55:$M$57)=0,SUM($J$54:$J$59)>0)),1,0) -> 0 | K66: =IF(AND($D25>0,$K$55=1),1,0) -> 0 | L66: =IF(AND($D25>0,$L$56=1),1,0) -> 0 | M66: =IF(AND($D25>0,$M$57=1),1,0) -> 0 | N66: =J66+N65 -> 0 | O66: =IF(J66<>0,N66,"") | P66: =IF(O66<>"",I66,"") | Q66: =K66+Q65 -> 0 | R66: =IF(K66<>0,Q66,"") | S66: =IF(R66<>"",$I66,"") | T66: =L66+T65 -> 0 | U66: =IF(L66<>0,T66,"") | V66: =IF(U66<>"",$I66,"") | W66: =M66+W65 -> 0 | X66: =IF(M66<>0,W66,"") | Y66: =IF(X66<>"",$I66,"")
H68: MinBand | I68: =INDEX(Data!$U$20:$U$49,Data!E4,1) -> 0

Sheet ProductCompositionMatrix
C7: =CONCATENATE("Price List applicable for ",Data!A9,". Effective from ",Data!A11,". ") -> Price List applicable for Vietnam. Effective from July 1, 2026.
C8: =CONCATENATE(Data!A5,". ",Data!A7) -> Kaspersky Lab. 39A/3 Leningradskoe Shosse Moscow, 125212. 0
B9: Max of Ind | D9: Component
B10: Code | C10: Product | D10: A210: Kaspersky Anti-Virus for Windows Workstation | E10: A211: Kaspersky Endpoint Security 8 for Windows (Workstations component) | F10: A213: Kaspersky Endpoint Security 10 for Windows (Workstations component) | G10: A214: Kaspersky Endpoint Security 10 for Windows (server mode) | H10: A220: Kaspersky Security 10 for Windows Server | I10: A220: Kaspersky Security 10 for Windows Server (App. Control) | J10: A220: Kaspersky Security 10 for Windows Server (NAS protection) | K10: A221: Kaspersky Anti-Virus for Windows Server EE | L10: A221: Kaspersky Anti-Virus for Windows Server EE (EMC Celerra support) | M10: A222: Kaspersky Endpoint Security 8 for Windows (Servers component) | N10: B171: Kaspersky Endpoint Security for Smartphone | O10: C120: Kaspersky Endpoint Security for Linux Workstation | P10: C210: Kaspersky Anti-Virus for Linux File Server | Q10: C301: Kaspersky Security 8.0 for Linux Mail Server | R10: C301: Kaspersky Security 8.0 for Linux Mail Server (AS component) | S10: D110: Kaspersky Endpoint Security for Mac | T10: F111: Kaspersky Security for Microsoft Exchange | U10: G310: Kaspersky Anti-Virus for Proxy Server | V10: H110: Kaspersky Security Center (MDM mode) | W10: H110: Kaspersky Security Center (SME mode) | X10: V201: Kaspersky Security for Virtualization | Y10: V202: Kaspersky Secure Mail Gateway
B11: 4155 | C11: 4155: Kaspersky Hybrid Cloud Security, Desktop | X11: 0
B12: 4221 | C12: 4221: Kaspersky Security for Storage | H12: 0 | I12: 0 | J12: 0 | K12: 0 | L12: 0
B13: 4253 | C13: 4253: Kaspersky Hybrid Cloud Security, Enterprise Server | X13: 0
B14: 4255 | C14: 4255: Kaspersky Hybrid Cloud Security, Server | X14: 0
B15: 4313 | C15: 4313: Kaspersky Security for Mail Server | Q15: 0 | T15: 0 | Y15: 0
B16: 4413 | C16: 4413: Kaspersky Security for Internet Gateway | U16: 0
B17: 4553 | C17: 4553: Kaspersky Hybrid Cloud Security, Enterprise CPU | X17: 0
B18: 4554 | C18: 4554: Kaspersky Hybrid Cloud Security, CPU | X18: 0
B19: 4713 | C19: 4713: Kaspersky Anti-Spam for Linux | R19: 0 | Y19: 0
B20: 4863 | C20: 4863: Kaspersky Endpoint Security for Business - Select | D20: 0 | E20: 0 | F20: 0 | G20: 0 | H20: 0 | K20: 0 | M20: 0 | N20: 0 | O20: 0 | P20: 0 | S20: 0 | V20: 0
B21: 4867 | C21: 4867: Kaspersky Endpoint Security for Business - Advanced | D21: 0 | E21: 0 | F21: 0 | G21: 0 | H21: 0 | I21: 0 | K21: 0 | M21: 0 | N21: 0 | O21: 0 | P21: 0 | S21: 0 | V21: 0 | W21: 0
B22: 4869 | C22: 4869: Kaspersky Total Security for Business | D22: 0 | E22: 0 | F22: 0 | G22: 0 | H22: 0 | I22: 0 | K22: 0 | M22: 0 | N22: 0 | O22: 0 | P22: 0 | Q22: 0 | S22: 0 | T22: 0 | U22: 0 | V22: 0 | W22: 0 | Y22: 0
B23: 9121 | C23: 9121: Kaspersky Vulnerability and Patch Management | W23: 0

Sheet ProductComposition
C7: =CONCATENATE("Price List applicable for ",Data!A9,". Effective from ",Data!A11,". ") -> Price List applicable for Vietnam. Effective from July 1, 2026.
C8: =CONCATENATE(Data!A5,". ",Data!A7) -> Kaspersky Lab. 39A/3 Leningradskoe Shosse Moscow, 125212. 0
B9: Max of Ind
B10: Code | C10: Product | D10: Category | E10: Component | F10: Итог
B11: 4155 | C11: 4155: Kaspersky Hybrid Cloud Security, Desktop | D11: Special Security | E11: V201: Kaspersky Security for Virtualization | F11: 0
B12: 4221 | C12: 4221: Kaspersky Security for Storage | D12: Storage Security | E12: A220: Kaspersky Security 10 for Windows Server | F12: 0
E13: A220: Kaspersky Security 10 for Windows Server (App. Control) | F13: 0
E14: A220: Kaspersky Security 10 for Windows Server (NAS protection) | F14: 0
E15: A221: Kaspersky Anti-Virus for Windows Server EE | F15: 0
E16: A221: Kaspersky Anti-Virus for Windows Server EE (EMC Celerra support) | F16: 0
B17: 4253 | C17: 4253: Kaspersky Hybrid Cloud Security, Enterprise Server | D17: Special Security | E17: V201: Kaspersky Security for Virtualization | F17: 0
B18: 4255 | C18: 4255: Kaspersky Hybrid Cloud Security, Server | D18: Special Security | E18: V201: Kaspersky Security for Virtualization | F18: 0
B19: 4313 | C19: 4313: Kaspersky Security for Mail Server | D19: Mail&Gateway Security | E19: C301: Kaspersky Security 8.0 for Linux Mail Server | F19: 0
E20: F111: Kaspersky Security for Microsoft Exchange | F20: 0
E21: V202: Kaspersky Secure Mail Gateway | F21: 0
B22: 4413 | C22: 4413: Kaspersky Security for Internet Gateway | D22: Mail&Gateway Security | E22: G310: Kaspersky Anti-Virus for Proxy Server | F22: 0
B23: 4553 | C23: 4553: Kaspersky Hybrid Cloud Security, Enterprise CPU | D23: Special Security | E23: V201: Kaspersky Security for Virtualization | F23: 0
B24: 4554 | C24: 4554: Kaspersky Hybrid Cloud Security, CPU | D24: Special Security | E24: V201: Kaspersky Security for Virtualization | F24: 0
B25: 4713 | C25: 4713: Kaspersky Anti-Spam for Linux | D25: Mail&Gateway Security | E25: C301: Kaspersky Security 8.0 for Linux Mail Server (AS component) | F25: 0
E26: V202: Kaspersky Secure Mail Gateway | F26: 0
B27: 4863 | C27: 4863: Kaspersky Endpoint Security for Business - Select | D27: OpenSpace Security | E27: A210: Kaspersky Anti-Virus for Windows Workstation | F27: 0
E28: A211: Kaspersky Endpoint Security 8 for Windows (Workstations component) | F28: 0
E29: A213: Kaspersky Endpoint Security 10 for Windows (Workstations component) | F29: 0
E30: A214: Kaspersky Endpoint Security 10 for Windows (server mode) | F30: 0
E31: A220: Kaspersky Security 10 for Windows Server | F31: 0
E32: A221: Kaspersky Anti-Virus for Windows Server EE | F32: 0
E33: A222: Kaspersky Endpoint Security 8 for Windows (Servers component) | F33: 0
E34: B171: Kaspersky Endpoint Security for Smartphone | F34: 0
E35: C120: Kaspersky Endpoint Security for Linux Workstation | F35: 0
E36: C210: Kaspersky Anti-Virus for Linux File Server | F36: 0
E37: D110: Kaspersky Endpoint Security for Mac | F37: 0
E38: H110: Kaspersky Security Center (MDM mode) | F38: 0
B39: 4867 | C39: 4867: Kaspersky Endpoint Security for Business - Advanced | D39: OpenSpace Security | E39: A210: Kaspersky Anti-Virus for Windows Workstation | F39: 0
E40: A211: Kaspersky Endpoint Security 8 for Windows (Workstations component) | F40: 0
E41: A213: Kaspersky Endpoint Security 10 for Windows (Workstations component) | F41: 0
E42: A214: Kaspersky Endpoint Security 10 for Windows (server mode) | F42: 0
E43: A220: Kaspersky Security 10 for Windows Server | F43: 0
E44: A220: Kaspersky Security 10 for Windows Server (App. Control) | F44: 0
E45: A221: Kaspersky Anti-Virus for Windows Server EE | F45: 0
E46: A222: Kaspersky Endpoint Security 8 for Windows (Servers component) | F46: 0
E47: B171: Kaspersky Endpoint Security for Smartphone | F47: 0
E48: C120: Kaspersky Endpoint Security for Linux Workstation | F48: 0
E49: C210: Kaspersky Anti-Virus for Linux File Server | F49: 0
E50: D110: Kaspersky Endpoint Security for Mac | F50: 0
E51: H110: Kaspersky Security Center (MDM mode) | F51: 0
E52: H110: Kaspersky Security Center (SME mode) | F52: 0
B53: 4869 | C53: 4869: Kaspersky Total Security for Business | D53: OpenSpace Security | E53: A210: Kaspersky Anti-Virus for Windows Workstation | F53: 0
E54: A211: Kaspersky Endpoint Security 8 for Windows (Workstations component) | F54: 0
E55: A213: Kaspersky Endpoint Security 10 for Windows (Workstations component) | F55: 0
E56: A214: Kaspersky Endpoint Security 10 for Windows (server mode) | F56: 0
E57: A220: Kaspersky Security 10 for Windows Server | F57: 0
E58: A220: Kaspersky Security 10 for Windows Server (App. Control) | F58: 0
E59: A221: Kaspersky Anti-Virus for Windows Server EE | F59: 0
E60: A222: Kaspersky Endpoint Security 8 for Windows (Servers component) | F60: 0
E61: B171: Kaspersky Endpoint Security for Smartphone | F61: 0
E62: C120: Kaspersky Endpoint Security for Linux Workstation | F62: 0
E63: C210: Kaspersky Anti-Virus for Linux File Server | F63: 0
E64: C301: Kaspersky Security 8.0 for Linux Mail Server | F64: 0
E65: D110: Kaspersky Endpoint Security for Mac | F65: 0
... E70: V202: Kaspersky Secure Mail Gateway | F70: 0
B71: 9121 | C71: 9121: Kaspersky Vulnerability and Patch Management | D71: Special Security | E71: H110: Kaspersky Security Center (SME mode) | F71: 0

Sheet Migration
C7: =CONCATENATE("Price List applicable for ",Data!A9,". Effective from ",Data!A11,". ") -> Price List applicable for Vietnam. Effective from July 1, 2026. | E7: For additional details please refer to Migration guide
C8: =CONCATENATE(Data!A5,". ",Data!A7) -> Kaspersky Lab. 39A/3 Leningradskoe Shosse Moscow, 125212. 0
C10: OldProduct | D10: Ind | E10: NewProduct
C11: 4213: Kaspersky Anti-Virus for File Server | D11: 1 | E11: 4231: Kaspersky Security for File Server
C12: 4851: Kaspersky WorkSpace Security (default option) | D12: 1 | E12: 4863: Kaspersky Endpoint Security for Business - Select
C13: 4851: Kaspersky WorkSpace Security (2nd migration option) | D13: 1 | E13: 4861: Kaspersky Endpoint Security for Business - Core + 4025: Kaspersky Security for Mobile
C14: 4851: Kaspersky WorkSpace Security (3rd migration option) | D14: 1 | E14: 4861: Kaspersky Endpoint Security for Business - Core
C15: 4851: Kaspersky WorkSpace Security (4th migration option) | D15: 1 | E15: 4867: Kaspersky Endpoint Security for Business - Advanced
C16: 4851: Kaspersky WorkSpace Security (5th migration option) | D16: 1 | E16: 4869: Kaspersky Total Security for Business
C17: 4853: Kaspersky BusinessSpace Security (default option) | D17: 1 | E17: 4863: Kaspersky Endpoint Security for Business - Select
C18: 4853: Kaspersky BusinessSpace Security (2nd migration option) | D18: 1 | E18: 4867: Kaspersky Endpoint Security for Business - Advanced
C19: 4853: Kaspersky BusinessSpace Security (3rd migration option) | D19: 1 | E19: 4869: Kaspersky Total Security for Business
C20: 4857: Kaspersky EnterpriseSpace Security (default option) | D20: 1 | E20: 4863: Kaspersky Endpoint Security for Business - Select + 4313: Kaspersky Security for Mail Server (Add-on)
C21: 4857: Kaspersky EnterpriseSpace Security (2nd migration option) | D21: 1 | E21: 4867: Kaspersky Endpoint Security for Business - Advanced + 4313: Kaspersky Security for Mail Server (Add-on)
C22: 4857: Kaspersky EnterpriseSpace Security (3rd migration option) | D22: 1 | E22: 4869: Kaspersky Total Security for Business
C23: 4859: Kaspersky TotalSpace Security (default option) | D23: 1 | E23: 4869: Kaspersky Total Security for Business
C24: 4859: Kaspersky TotalSpace Security (2nd migration option) | D24: 1 | E24: 4863: Kaspersky Endpoint Security for Business - Select + 4313: Kaspersky Security for Mail Server (Add-on) + 4413: Kaspersky Security for Internet Gateway (Add-on) + 4323: Kaspersky Security for Collaboration (Add-on)
C25: 4859: Kaspersky TotalSpace Security (3rd migration option) | D25: 1 | E25: 4867: Kaspersky Endpoint Security for Business - Advanced + 4313: Kaspersky Security for Mail Server (Add-on) + 4413: Kaspersky Security for Internet Gateway (Add-on) + 4323: Kaspersky Security for Collaboration (Add-on)

Sheet Comment
B7: =CONCATENATE("Price List applicable for ",Data!A9,". Effective from ",Data!A11,". ") -> Price List applicable for Vietnam. Effective from July 1, 2026.
B8: =CONCATENATE(Data!A5,". ",Data!A7) -> Kaspersky Lab. 39A/3 Leningradskoe Shosse Moscow, 125212. 0
B9: Table of contents
B10: Terms | E10: =CONCATENATE("All prices are indicated in ",Data!B4,", ",Data!C4," VAT and local taxes.") -> All prices are indicated in VND, excluding VAT and local taxes.
B11: Products | E11: Please note that products listed on the tab “Home+SOHO”, excluding Kaspersky Small Office Security for Desktops, Mobiles and File Servers, relate to B2C market sector. All the rest products and services presented in this price-list relate to B2B market sector.
E12: Certain additional product pricing, bands, license types, terms are available from Vendor per additional request
B13: Pricing | C13: MSRP | E13: The recommended retail prices (MSRP) specified in this Price List are for informational purposes only and are not binding on the Partner or third parties.
C14: Pack | E14: Prices are indicated per unit.
C15: License / Services Subscription | E15: Prices are indicated per License (user).
B16: Specification | C16: Add-on pricing program terms | E16: Kaspersky introduces Add-on SKUs as a special pricing program available for selected products. Please refer to Kaspersky licensing policy at partner portal for details License type and customer segment discounts are not applied to Add-on SKUs.
E17: If SKU is being bought with Add-on license type, the expiration date of the license for this Add-on SKU will be aligned with the expiration date of the license for the main product to which Add-on license is purchased. It is not possible to sell SKU with Add-on license type for the license term shorter or longer than the license term of the main product.
C18: ATC | E18: ATC SKUs (License packs) can only be distributed by partners with the current Authorized Training Center (ATC) status and the corresponding agreement. These items are distributed exclusively under the agreement mentioned in point 1, provisions of other possibly existing contracts do not apply to them (including discounts from the main distribution contract).
E19: ATC SKUs (Services\Certificates) if available in the price list can be distributed by partners under current Distribution agreement.
C20: Kaspersky Endpoint Detection and Response Expert Telemetry Retention 60 days | E20: The telemetry retention period specified in the certificate applies to new telemetry collected from the moment the certificate is activated until the certificate expires. If the certificate expires, the retention period for new collected telemetry will be determined according to the main product license
C21: Kaspersky Endpoint Detection and Response Expert Telemetry Retention 90 days
C22: CBA Subscription | E22: Products listed on the “CBA Subscription” tab are available to Kaspersky authorized partners who made an integration with Kaspersky Subscription System (KSS) and have the corresponding agreement with Kaspersky for CBA Subscription products distribution. Please contact Kaspersky Consumer Business Alliances (CBA@kaspersky.com ) to discuss integration issues
C23: Kaspersky Research Sandbox | E23: If Research Sandbox product is going to be installed on more than one server than a customer should purchase a separate Research Sandbox license pack per each server.
C24: Kaspersky Remote Compromise Assessment | E24: Compromise Assessment service – perfect offering for clients who are not ready to discuss security products yet. Our experts perform comprehensive checkup of all hosts in customer’s infrastructure to uncover missed incidents: both past and ongoing compromises. Service is designed for enterprise with 400+ hosts. On-site service, available as well, please contact us. your partner account manager. Check more for details here
B25: Disclaimer | E25: Errors, amendments and modifications excepted.
E26: Ordering of some products may require additional confirmation from Vendor – please contact Kaspersky Local Office manager for the deal quotation. In case of placing an order for such products, the order changes to status “Order is awaiting confirmation by vendor”.
E27: This Price List is confidential to Kaspersky and its partners and may not be distributed to any third parties. Kaspersky reserves the right to correct any errors or inaccuracies in the Price List unilaterally and at any time without prior notice.

Sheet Cover
B23: Price list
B27: =CONCATENATE("Applicable for ",Data!A9,) -> Applicable for Vietnam
B30: =CONCATENATE("Effective from ",Data!A11,". ") -> Effective from July 1, 2026.
B56: =CONCATENATE(Data!A5,". ",Data!A7) -> Kaspersky Lab. 39A/3 Leningradskoe Shosse Moscow, 125212. 0

Sheet SaleListHome+SOHO
A1: PositionCode | B1: SKU | C1: Category | D1: Code | E1: Product | F1: LicenceDescription | G1: LicenceObject | H1: Package | I1: Band | J1: LicenceComposition | K1: LicenceType | L1: Term | M1: Price
A2: - | B2: - | C2: New 2022 Product Line | D2: 1000 | E2: New 2022 Product Line | G2: - | H2: - | I2: Band K: 10-14 | J2: - | K2: Base | L2: 1 year
A3: KL1041WDADS | B3: KL1041WDA** | C3: Unknown | D3: 1001 | E3: Kaspersky Standard | F3: Dvc | H3: Download Pack | I3: Band A: 1 | J3: 1Dvc | K3: Base | L3: 2 year | M3: 581818.18
A4: KL1041WDAFS | B4: KL1041WDA** | C4: Unknown | D4: 1001 | E4: Kaspersky Standard | F4: Dvc | H4: Download Pack | I4: Band A: 1 | J4: 1Dvc | K4: Base | L4: 1 year | M4: 290909.09
A5: KL1041WDCDS | B5: KL1041WDC** | C5: Unknown | D5: 1001 | E5: Kaspersky Standard | F5: Dvc | H5: Download Pack | I5: Band C: 3 | J5: 3Dvc | K5: Base | L5: 2 year | M5: 1027272.7
A6: KL1041WDCFS | B6: KL1041WDC** | C6: Unknown | D6: 1001 | E6: Kaspersky Standard | F6: Dvc | H6: Download Pack | I6: Band C: 3 | J6: 3Dvc | K6: Base | L6: 1 year | M6: 513636.36
A7: KL1041WDEDS | B7: KL1041WDE** | C7: Unknown | D7: 1001 | E7: Kaspersky Standard | F7: Dvc | H7: Download Pack | I7: Band E: 5 | J7: 5Dvc | K7: Base | L7: 2 year | M7: 1320000
A8: KL1041WDEFS | B8: KL1041WDE** | C8: Unknown | D8: 1001 | E8: Kaspersky Standard | F8: Dvc | H8: Download Pack | I8: Band E: 5 | J8: 5Dvc | K8: Base | L8: 1 year | M8: 660000
A9: KL1041WDKDS | B9: KL1041WDK** | C9: Unknown | D9: 1001 | E9: Kaspersky Standard | F9: Dvc | H9: Download Pack | I9: Band K: 10 | J9: 10Dvc | K9: Base | L9: 2 year | M9: 1880000
A10: KL1041WDKFS | B10: KL1041WDK** | C10: Unknown | D10: 1001 | E10: Kaspersky Standard | F10: Dvc | H10: Download Pack | I10: Band K: 10 | J10: 10Dvc | K10: Base | L10: 1 year | M10: 940000
A11: KL1041WUADS | B11: KL1041WUA** | C11: Unknown | D11: 1001 | E11: Kaspersky Standard | F11: Dvc | H11: Retail Pack | I11: Band A: 1 | J11: 1Dvc | K11: Base | L11: 2 year | M11: 581818.18
A12: KL1041WUAFS | B12: KL1041WUA** | C12: Unknown | D12: 1001 | E12: Kaspersky Standard | F12: Dvc | H12: Retail Pack | I12: Band A: 1 | J12: 1Dvc | K12: Base | L12: 1 year | M12: 290909.09
A13: KL1041WUCDS | B13: KL1041WUC** | C13: Unknown | D13: 1001 | E13: Kaspersky Standard | F13: Dvc | H13: Retail Pack | I13: Band C: 3 | J13: 3Dvc | K13: Base | L13: 2 year | M13: 1027272.7
A14: KL1041WUCFS | B14: KL1041WUC** | C14: Unknown | D14: 1001 | E14: Kaspersky Standard | F14: Dvc | H14: Retail Pack | I14: Band C: 3 | J14: 3Dvc | K14: Base | L14: 1 year | M14: 513636.36
